Workbook

Sheet I-O
B1: 2022 Input-Output transactions table
B2: Industry | C2: S1 | D2: S2 | E2: S3 | F2: S4 | G2: S5 | H2: S6 | I2: S7 | J2: S8 | K2: S9 | L2: S10 | M2: S11 | N2: S12 | O2: S13 | P2: S14 | Q2: S15 | R2: S16 | S2: S17 | T2: S18 | U2: S19 | V2: S20 | W2: S21 | X2: S22 | Y2: S23 | Z2: S24 | AA2: S25 | AB2: S26 | AC2: S27 | AD2: S28 | AE2: S29 | AF2: S30 | AG2: S31 | AH2: S32 | AI2: S33 | AJ2: S34 | AK2: S35 | AL2: S36 | AM2: S37 | AN2: S38 | AO2: S39 | AP2: S40 | AQ2: S41 | AR2: S42 | AS2: S43 | AT2: S44 | AU2: S45 | AV2: S46 | AW2: S47 | AX2: S48 | AY2: S49 | AZ2: S50 | BA2: S51 | BB2: S52 | BC2: S53 | BD2: S54 | BE2: S55 | BF2: S56 | BG2: S57 | BH2: S58 | BI2: S59 | BJ2: S60 | BK2: S61 | BL2: S62 | BM2: Interindustry demand | BO2: PCE | BP2: VE | BQ2: Change in inventories | BR2: Gross private investment | BS2: State and local gov't investment | BT2: State and local gov't consumption | BU2: Federal defense consumption | BV2: Federal defense investment | BW2: Federal nondefense consumption | BX2: Federal nondefense investment | BY2: Exports | CA2: Output
A3: S1 | B3: Crop production | C3: 8.5381865 | D3: 8.3969568 | E3: 0 | F3: 0 | G3: 1.6640221 | H3: 0 | I3: 1.4474393 | J3: 2.6483887 | K3: 1.1334982 | L3: 3.8306382 | M3: 56.165439 | N3: 0 | O3: 0.34579119 | P3: 0.00031602302 | Q3: 1.3808298 | R3: 0 | S3: 0 | T3: 0 | U3: 0 | V3: 0 | W3: 0 | X3: 0 | Y3: 0 | Z3: 0 | AA3: 0 | AB3: 0 | AC3: 0 | AD3: 0 | AE3: 0 | AF3: 0 | AG3: 0.15001639 | AH3: 0.14209403 | AI3: 0 | AJ3: 0 | AK3: 0 | AL3: 2.6562587 | AM3: 0.50591263 | AN3: 0 | AO3: 0 | AP3: 0.042594292 | AQ3: 0 | AR3: 0 | AS3: 0.029811432 | AT3: 0 | AU3: 0 | AV3: 0.31940818 | AW3: 0 | AX3: 0 | AY3: 0.00020254059 | AZ3: 0 | BA3: 0.39056493 | BB3: 0.10906114 | BC3: 0.04703278 | BD3: 0.029125541 | BE3: 0 | BF3: 8.6131266 | BG3: 0.00025694845 | BH3: 0 | BI3: 0.017387604 | BJ3: 0 | BK3: 0 | BL3: 0 | BM3: =SUM(C3:BL3) -> 98.604359 | BO3: 100.24274 | BP3: 24.565133 | BQ3: 0 | BR3: 0 | BS3: 0 | BT3: 6.5844684 | BU3: 0 | BV3: 0 | BW3: 0 | BX3: 0 | BY3: 258.77357 | CA3: 488.77025
A4: S2 | B4: Animal production | C4: 0 | D4: 4.9066513 | E4: 0 | F4: 0.014359611 | G4: 6.3731374 | H4: 0 | I4: 0 | J4: 0 | K4: 0 | L4: 0 | M4: 20.401501 | N4: 0 | O4: 0 | P4: 0 | Q4: 0.00059786306 | R4: 0 | S4: 0 | T4: 0 | U4: 0 | V4: 0 | W4: 0 | X4: 0 | Y4: 0 | Z4: 0 | AA4: 0 | AB4: 0 | AC4: 0 | AD4: 0 | AE4: 0 | AF4: 0 | AG4: 0.040582459 | AH4: 0.030475902 | AI4: 0 | AJ4: 0 | AK4: 0 | AL4: 0 | AM4: 0 | AN4: 0 | AO4: 0 | AP4: 0 | AQ4: 0 | AR4: 2.2652355 | AS4: 0 | AT4: 0 | AU4: 0 | AV4: 0.0022269757 | AW4: 0 | AX4: 0.0065253905 | AY4: 0 | AZ4: 0 | BA4: 3.2901857 | BB4: 0.039085363 | BC4: 0.00081745056 | BD4: 0.15555654 | BE4: 0 | BF4: 10.856264 | BG4: 0 | BH4: 1.3991243 | BI4: 0.00015722824 | BJ4: 0 | BK4: 0 | BL4: 0 | BM4: =SUM(C4:BL4) -> 49.782483 | BO4: 32.443013 | BP4: 1.6741951 | BQ4: 0 | BR4: 0 | BS4: 0 | BT4: 0.61605677 | BU4: 0 | BV4: 0 | BW4: 0 | BX4: 0 | BY4: 74.766259 | CA4: 159.282
A5: S3 | B5: Commercial fishing | C5: 0 | D5: 0 | E5: 1.0241778 | F5: 0 | G5: 0 | H5: 0 | I5: 0 | J5: 0 | K5: 0 | L5: 0 | M5: 0.41638406 | N5: 0 | O5: 0 | P5: 0 | Q5: 0 | R5: 0 | S5: 0 | T5: 0 | U5: 0 | V5: 0 | W5: 0 | X5: 0 | Y5: 0 | Z5: 0 | AA5: 0 | AB5: 0 | AC5: 0 | AD5: 0 | AE5: 0 | AF5: 0 | AG5: 0 | AH5: 0 | AI5: 0 | AJ5: 0 | AK5: 0 | AL5: 0 | AM5: 0 | AN5: 0 | AO5: 0 | AP5: 0 | AQ5: 0 | AR5: 0 | AS5: 0 | AT5: 0 | AU5: 0 | AV5: 0 | AW5: 0 | AX5: 0 | AY5: 0 | AZ5: 0 | BA5: 2.0892656 | BB5: 0.082190336 | BC5: 0 | BD5: 0.0022121324 | BE5: 0 | BF5: 50.564143 | BG5: 0 | BH5: 0 | BI5: 0.014061734 | BJ5: 0 | BK5: 0 | BL5: 0 | BM5: =SUM(C5:BL5) -> 54.192435 | BO5: 24.305093 | BP5: 2.0611506 | BQ5: 0 | BR5: 0 | BS5: 0 | BT5: 0.83359265 | BU5: 0 | BV5: 0 | BW5: 0 | BX5: 0 | BY5: 87.71279 | CA5: 169.10505
A6: S4 | B6: Forestry & logging | C6: 1.0119086 | D6: 0 | E6: 0 | F6: 4.6571413 | G6: 2.6339373 | H6: 2.995254 | I6: 0 | J6: 0 | K6: 0 | L6: 0 | M6: 0.16988413 | N6: 0.66966574 | O6: 0.3685589 | P6: 0.20016018 | Q6: 0.32921154 | R6: 0 | S6: 0.021167589 | T6: 0 | U6: 0 | V6: 0 | W6: 0 | X6: 0 | Y6: 0 | Z6: 0 | AA6: 0 | AB6: 0 | AC6: 0 | AD6: 0 | AE6: 0 | AF6: 0 | AG6: 0 | AH6: 0 | AI6: 0 | AJ6: 0 | AK6: 0 | AL6: 0 | AM6: 0 | AN6: 0 | AO6: 0 | AP6: 0 | AQ6: 0 | AR6: 1.1349575 | AS6: 0 | AT6: 0 | AU6: 0 | AV6: 0.41064789 | AW6: 0 | AX6: 0.0252469 | AY6: 0 | AZ6: 0 | BA6: 0 | BB6: 0 | BC6: 0 | BD6: 0.011975948 | BE6: 0 | BF6: 0 | BG6: 0.0028171382 | BH6: 0 | BI6: 0 | BJ6: 0 | BK6: 0 | BL6: 0 | BM6: =SUM(C6:BL6) -> 14.642535 | BO6: 0 | BP6: 0 | BQ6: 0 | BR6: 0 | BS6: 0 | BT6: 0 | BU6: 0 | BV6: 0 | BW6: 0 | BX6: 0 | BY6: 0 | CA6: 14.64253
A7: S5 | B7: Support activities for agriculture | C7: 29.192728 | D7: 0.58153411 | E7: 0 | F7: 0.11517377 | G7: 2.3004131 | H7: 0 | I7: 0 | J7: 0 | K7: 0 | L7: 0 | M7: 0 | N7: 0 | O7: 0 | P7: 0 | Q7: 0.60145955 | R7: 0.032094051 | S7: 0.00086566914 | T7: 0 | U7: 0 | V7: 0.048206724 | W7: 0 | X7: 0 | Y7: 0.00090775831 | Z7: 0 | AA7: 0.00019143739 | AB7: 0.0059559674 | AC7: 5.074651e-05 | AD7: 1.6653421e-05 | AE7: 0.029184629 | AF7: 0.0045300687 | AG7: 0 | AH7: 0 | AI7: 0.0011107979 | AJ7: 0 | AK7: 0 | AL7: 29.878822 | AM7: 3.3770791 | AN7: 0 | AO7: 0.0010076152 | AP7: 0 | AQ7: 0.00021757235 | AR7: 0 | AS7: 0 | AT7: 0.00019548458 | AU7: 0 | AV7: 0 | AW7: 0 | AX7: 0 | AY7: 0 | AZ7: 0.00062337292 | BA7: 0 | BB7: 0 | BC7: 0 | BD7: 0 | BE7: 0.18409218 | BF7: 0 | BG7: 0 | BH7: 0 | BI7: 0 | BJ7: 0 | BK7: 0.070744955 | BL7: 0.18772866 | BM7: =SUM(C7:BL7) -> 66.614933 | BO7: 108.76256 | BP7: 0 | BQ7: 0 | BR7: 0 | BS7: 0 | BT7: 0 | BU7: 0 | BV7: 0 | BW7: 0 | BX7: 0 | BY7: 0 | CA7: 175.37747
A8: S6 | B8: Mining | C8: 0.13628429 | D8: 0 | E8: 0 | F8: 2.8548435e-05 | G8: 0.00059135841 | H8: 0.91683476 | I8: 0 | J8: 0 | K8: 0 | L8: 0 | M8: 0 | N8: 0 | O8: 0 | P8: 0 | Q8: 0 | R8: 0 | S8: 0 | T8: 0 | U8: 0 | V8: 0 | W8: 0 | X8: 0 | Y8: 0 | Z8: 0 | AA8: 0 | AB8: 0 | AC8: 0 | AD8: 0 | AE8: 2.3811771 | AF8: 4.3033001 | AG8: 0 | AH8: 0 | AI8: 0 | AJ8: 0 | AK8: 0 | AL8: 0 | AM8: 0 | AN8: 0 | AO8: 0 | AP8: 0 | AQ8: 0 | AR8: 0 | AS8: 0 | AT8: 0 | AU8: 0 | AV8: 0 | AW8: 0 | AX8: 0 | AY8: 0 | AZ8: 0 | BA8: 0 | BB8: 0 | BC8: 0 | BD8: 0 | BE8: 0 | BF8: 0 | BG8: 0 | BH8: 0 | BI8: 0 | BJ8: 0 | BK8: 0 | BL8: 0 | BM8: =SUM(C8:BL8) -> 7.7382162 | BO8: 0 | BP8: 0 | BQ8: 0 | BR8: 0 | BS8: 0 | BT8: 0 | BU8: 0 | BV8: 0 | BW8: 0.18648008 | BX8: 0 | BY8: 146.24597 | CA8: 154.17066
A9: S7 | B9: Single family construction | C9: 0 | D9: 0 | E9: 0 | F9: 0 | G9: 0 | H9: 0 | I9: 0 | J9: 0 | K9: 0 | L9: 0 | M9: 0 | N9: 0 | O9: 0 | P9: 0 | Q9: 0 | R9: 0 | S9: 0 | T9: 0 | U9: 0 | V9: 0 | W9: 0 | X9: 0 | Y9: 0 | Z9: 0 | AA9: 0 | AB9: 0 | AC9: 0 | AD9: 0 | AE9: 0 | AF9: 0 | AG9: 0 | AH9: 0 | AI9: 0 | AJ9: 0 | AK9: 0 | AL9: 0 | AM9: 0 | AN9: 0 | AO9: 0 | AP9: 0 | AQ9: 0 | AR9: 0 | AS9: 0 | AT9: 0 | AU9: 0 | AV9: 0 | AW9: 0 | AX9: 0 | AY9: 0 | AZ9: 0 | BA9: 0 | BB9: 0 | BC9: 0 | BD9: 0 | BE9: 0 | BF9: 0 | BG9: 0 | BH9: 0 | BI9: 0 | BJ9: 0 | BK9: 0 | BL9: 0 | BM9: =SUM(C9:BL9) -> 0 | BO9: 0 | BP9: 0 | BQ9: 0 | BR9: 1161.9896 | BS9: 0 | BT9: 0 | BU9: 0 | BV9: 0 | BW9: 0 | BX9: 0 | BY9: 0 | CA9: 1161.9896
A10: S8 | B10: Construction of other buildings | C10: 0 | D10: 0 | E10: 0 | F10: 0 | G10: 0 | H10: 0 | I10: 0 | J10: 0 | K10: 0 | L10: 0 | M10: 0 | N10: 0 | O10: 0 | P10: 0 | Q10: 0 | R10: 0 | S10: 0 | T10: 0 | U10: 0 | V10: 0 | W10: 0 | X10: 0 | Y10: 0 | Z10: 0 | AA10: 0 | AB10: 0 | AC10: 0 | AD10: 0 | AE10: 0 | AF10: 0 | AG10: 0 | AH10: 0 | AI10: 0 | AJ10: 0 | AK10: 0 | AL10: 0 | AM10: 0 | AN10: 0 | AO10: 0 | AP10: 0 | AQ10: 0 | AR10: 0 | AS10: 0 | AT10: 0 | AU10: 0 | AV10: 0 | AW10: 0 | AX10: 0 | AY10: 0 | AZ10: 0 | BA10: 0 | BB10: 0 | BC10: 0 | BD10: 0 | BE10: 0 | BF10: 0 | BG10: 0 | BH10: 0 | BI10: 0 | BJ10: 0 | BK10: 0 | BL10: 0 | BM10: =SUM(C10:BL10) -> 0 | BO10: 0 | BP10: 0 | BQ10: 0 | BR10: 3769.4173 | BS10: 924.24328 | BT10: 0 | BU10: 0 | BV10: 95.49252 | BW10: 0 | BX10: 47.172703 | BY10: 0 | CA10: 4836.3258
A11: S9 | B11: Heavy and civil engineering construction | C11: 0 | D11: 0 | E11: 0 | F11: 0 | G11: 0 | H11: 0 | I11: 0 | J11: 0 | K11: 0 | L11: 0 | M11: 0 | N11: 0 | O11: 0 | P11: 0 | Q11: 0 | R11: 0 | S11: 0 | T11: 0 | U11: 0 | V11: 0 | W11: 0 | X11: 0 | Y11: 0 | Z11: 0 | AA11: 0 | AB11: 0 | AC11: 0 | AD11: 0 | AE11: 0 | AF11: 0 | AG11: 0 | AH11: 0 | AI11: 0 | AJ11: 0 | AK11: 0 | AL11: 0 | AM11: 0 | AN11: 0 | AO11: 0 | AP11: 0 | AQ11: 0 | AR11: 0 | AS11: 0 | AT11: 0 | AU11: 0 | AV11: 0 | AW11: 0 | AX11: 0 | AY11: 0 | AZ11: 0 | BA11: 0 | BB11: 0 | BC11: 0 | BD11: 0 | BE11: 0 | BF11: 0 | BG11: 0 | BH11: 0 | BI11: 0 | BJ11: 0 | BK11: 0 | BL11: 0 | BM11: =SUM(C11:BL11) -> 0 | BO11: 0 | BP11: 0 | BQ11: 0 | BR11: 1359.1321 | BS11: 1399.3439 | BT11: 0 | BU11: 0 | BV11: 18.381739 | BW11: 0 | BX11: 11.687236 | BY11: 0 | CA11: 2788.545
A12: S10 | B12: Maintenance & repairs | C12: 1.6458905 | D12: 0.25997292 | E12: 20.476315 | F12: 0.0017674563 | G12: 0.31308327 | H12: 0.0056098928 | I12: 1.3586608 | J12: 9.3920204 | K12: 7.2095943 | L12: 4.937027 | M12: 7.8507114 | N12: 0.69737629 | O12: 0.17525611 | P12: 1.4681342 | Q12: 1.3580373 | R12: 132.07305 | S12: 0.025495998 | T12: 0.20821224 | U12: 0 | V12: 5.975214 | W12: 1.7455474 | X12: 1.7345743 | Y12: 3.1863516 | Z12: 2.7990962 | AA12: 0.55918497 | AB12: 17.397268 | AC12: 0.2622134 | AD12: 0.086050256 | AE12: 161.22645 | AF12: 26.708392 | AG12: 13.707423 | AH12: 43.668212 | AI12: 40.987437 | AJ12: 0.54939195 | AK12: 3.8136635 | AL12: 1037.6781 | AM12: 124.41123 | AN12: 6.4138198 | AO12: 5.3643505 | AP12: 7.6599744 | AQ12: 0.30929371 | AR12: 20.813718 | AS12: 7.1636058 | AT12: 17.318506 | AU12: 1.4107857 | AV12: 1.7332617 | AW12: 1.0823461 | AX12: 0.41650025 | AY12: 10.873885 | AZ12: 2.0596027 | BA12: 29.600313 | BB12: 4.5937816 | BC12: 3.6338538 | BD12: 1.9167031 | BE12: 490.13385 | BF12: 179.89718 | BG12: 0.90935159 | BH12: 13.831323 | BI12: 2.972767 | BJ12: 0 | BK12: 32.971791 | BL12: 13.549606 | BM12: =SUM(C12:BL12) -> 2532.5822 | BO12: 410.53387 | BP12: 0 | BQ12: 0 | BR12: 0 | BS12: 0 | BT12: 0 | BU12: 30.88315 | BV12: 112.2929 | BW12: 0 | BX12: 0 | BY12: 280.8482 | CA12: 3367.1395
A13: S11 | B13: Food processing | C13: 0.20061159 | D13: 4.0105684 | E13: 0.0094439814 | F13: 0.009916852 | G13: 0.14033734 | H13: 0 | I13: 0 | J13: 0 | K13: 0 | L13: 0 | M13: 27.438855 | N13: 24.359072 | O13: 0.13789508 | P13: 0.19020718 | Q13: 0.14502651 | R13: 0 | S13: 0.031378653 | T13: 0 | U13: 0 | V13: 2.5763147 | W13: 0.42102834 | X13: 0 | Y13: 0.054111715 | Z13: 1.008624 | AA13: 0 | AB13: 0 | AC13: 0 | AD13: 0 | AE13: 0 | AF13: 0 | AG13: 0.82190002 | AH13: 0.50738059 | AI13: 0 | AJ13: 0 | AK13: 0 | AL13: 0 | AM13: 0 | AN13: 0 | AO13: 0 | AP13: 0 | AQ13: 0 | AR13: 0.42014004 | AS13: 1.2100074 | AT13: 0 | AU13: 0 | AV13: 0.0029201458 | AW13: 0 | AX13: 0.0090701247 | AY13: 0.0017476863 | AZ13: 0.0040349882 | BA13: 13.145095 | BB13: 6.72647 | BC13: 2.8968509 | BD13: 0.071392393 | BE13: 5.305507 | BF13: 259.58437 | BG13: 0 | BH13: 0.42171541 | BI13: 0.28088153 | BJ13: 0 | BK13: 1.3925484 | BL13: 0.075079326 | BM13: =SUM(C13:BL13) -> 353.6105 | BO13: 275.96967 | BP13: 36.758369 | BQ13: 0.53506616 | BR13: 0 | BS13: 0 | BT13: 15.711225 | BU13: 4.4242067 | BV13: 0 | BW13: 0.39464466 | BX13: 0 | BY13: 342.50937 | CA13: 1029.913
A14: S12 | B14: Beverage manufacturing | C14: 0 | D14: 0.011609399 | E14: 0.96093889 | F14: 0 | G14: 0 | H14: 0 | I14: 0 | J14: 0 | K14: 0 | L14: 0 | M14: 5.7202159 | N14: 12.093982 | O14: 0.019930818 | P14: 0.027491804 | Q14: 0.016769253 | R14: 0 | S14: 0.0036282785 | T14: 0 | U14: 0 | V14: 0.29789639 | W14: 0.049011392 | X14: 0 | Y14: 0.0062568771 | Z14: 0.11662606 | AA14: 0 | AB14: 0 | AC14: 0 | AD14: 0 | AE14: 0 | AF14: 0 | AG14: 0.095035381 | AH14: 0.058667851 | AI14: 0 | AJ14: 0 | AK14: 0 | AL14: 0 | AM14: 0 | AN14: 0 | AO14: 0 | AP14: 0 | AQ14: 0 | AR14: 0 | AS14: 0.067262487 | AT14: 0 | AU14: 0 | AV14: 0 | AW14: 0 | AX14: 0.0032601714 | AY14: 0.0042820577 | AZ14: 0.00046656117 | BA14: 0.75285949 | BB14: 0.081571709 | BC14: 0.33495963 | BD14: 0.0082550227 | BE14: 0.61346985 | BF14: 83.518187 | BG14: 0 | BH14: 0 | BI14: 0.29224733 | BJ14: 0 | BK14: 0.61604234 | BL14: 0.21671331 | BM14: =SUM(C14:BL14) -> 105.98764 | BO14: 311.82324 | BP14: 15.278001 | BQ14: 0.3808399 | BR14: 0 | BS14: 0 | BT14: 18.407665 | BU14: 0.0027006642 | BV14: 0 | BW14: 0.11537332 | BX14: 0 | BY14: 14.68086 | CA14: 466.67629
... A64: S62 | B64: State and local government | C64: 5.2813698 | D64: 2.6950364 | E64: 0.19810529 | F64: 0 | G64: 0 | H64: 0.025964244 | I64: 0 | J64: 0 | K64: 0 | L64: 0 | M64: 1.5168324 | N64: 7.2384493 | O64: 0.16191807 | P64: 12.984786 | Q64: 4.9521033 | R64: 505.03101 | S64: 12.148015 | T64: 1.6573962 | U64: 11.720029 | V64: 4.2841661 | W64: 36.411267 | X64: 0.69898082 | Y64: 2.6603921 | Z64: 1.1085737 | AA64: 0.55170347 | AB64: 8.5113365 | AC64: 0.051693202 | AD64: 0.016966192 | AE64: 3.8060106 | AF64: 0.10067376 | AG64: 6.9944225 | AH64: 130.86008 | AI64: 12.130406 | AJ64: 4.2499319 | AK64: 0.99456828 | AL64: 0 | AM64: 79.830966 | AN64: 171.14741 | AO64: 3.5631358 | AP64: 0 | AQ64: 0.10020231 | AR64: 3.5639323 | AS64: 6.8362135 | AT64: 7.238115 | AU64: 1.6688254 | AV64: 5.7020106 | AW64: 62.501671 | AX64: 0.34876376 | AY64: 0.40087994 | AZ64: 0.90243144 | BA64: 73.377864 | BB64: 0 | BC64: 1.1274602 | BD64: 3.472552 | BE64: 180.49929 | BF64: 43.882155 | BG64: 0 | BH64: 2.1179885 | BI64: 0 | BJ64: 0 | BK64: 9.40542 | BL64: 5.0514291 | BM64: =SUM(C64:BL64) -> 1441.7809 | BO64: 5163.1967 | BP64: 100.04999 | BQ64: 0 | BR64: 0 | BS64: 0 | BT64: 2410.852 | BU64: 0.11283455 | BV64: 0 | BW64: 21.160655 | BX64: 0 | BY64: 0 | CA64: 9137.1528
BM65: =+SUM(BM3:BM64) -> 40963.58
B66: Intermediate demand | C66: =SUM(C3:C64) -> 130.26612 | D66: =SUM(D3:D64) -> 37.83655 | E66: =SUM(E3:E64) -> 51.679875 | F66: =SUM(F3:F64) -> 5.0579977 | G66: =SUM(G3:G64) -> 55.40831 | H66: =SUM(H3:H64) -> 54.905408 | I66: =SUM(I3:I64) -> 397.38246 | J66: =SUM(J3:J64) -> 1759.5121 | ... BL66: =SUM(BL3:BL64) -> 136.34871 | BM66: =SUM(C66:BL66) -> 40963.58 | BO66: =+SUM(BO3:BO64) -> 62731.926 | BP66: =+SUM(BP3:BP64) -> 21195.175 | BQ66: =+SUM(BQ3:BQ64) -> 23.833183 | BR66: =+SUM(BR3:BR64) -> 8567.705 | BS66: =+SUM(BS3:BS64) -> 2482.7292 | BT66: =+SUM(BT3:BT64) -> 4406.8903 | BU66: =+SUM(BU3:BU64) -> 8716.7647 | BV66: =+SUM(BV3:BV64) -> 295.36304 | ... BY66: =+SUM(BY3:BY64) -> 7258.2872 | CA66: =+SUM(CA3:CA64) -> 158618.07
B67: Imports | C67: 77.207241 | D67: 29.775526 | E67: 20.332291 | F67: 1.1774179 | G67: 19.035977 | H67: 8.7652549 | I67: 211.35708 | J67: 774.12731 | K67: 446.73359 | L67: 609.39192 | M67: 201.35918 | N67: 96.976045 | O67: 14.31403 | P67: 2287.25 | Q67: 152.68339 | R67: 528.60243 | S67: 17.203128 | T67: 7.904875 | U67: 50.000115 | V67: 158.43093 | W67: 32.797126 | X67: 9.4113704 | Y67: 208.8226 | Z67: 62.567432 | AA67: 44.810197 | AB67: 872.82742 | AC67: 15.830676 | AD67: 5.8378505 | AE67: 137.7255 | AF67: 114.78842 | AG67: 512.22218 | AH67: 796.8142 | AI67: 531.94718 | AJ67: 130.32824 | AK67: 193.15673 | AL67: 320.35035 | AM67: 154.17052 | AN67: 177.81851 | AO67: 82.803835 | AP67: 132.28674 | AQ67: 13.556494 | AR67: 290.15656 | AS67: 208.93494 | AT67: 73.139687 | AU67: 35.341669 | AV67: 60.164299 | AW67: 32.720539 | AX67: 3.5477907 | AY67: 8.5359838 | AZ67: 163.16678 | BA67: 844.30618 | BB67: 85.300012 | BC67: 30.458452 | BD67: 16.450099 | BE67: 882.31512 | BF67: 1188.4896 | BG67: 57.937492 | BH67: 102.28341 | BI67: 25.79092 | BJ67: 0 | BK67: 82.357409 | BL67: 46.394346 | BM67: =+SUM(C67:BL67) -> 14501.293 | BO67: 10288.719 | BP67: 1450.1507 | BQ67: 22.502766 | BR67: 8477.4453 | BS67: 228.57951 | BT67: 6798.93 | BU67: 274.55027 | BV67: 97.055048 | BW67: 148.80802 | BX67: 98.191865 | BY67: 964.74182 | CA67: =+SUM(BO67:BZ67)+BM67 -> 43350.967
B69: Compensation of employees | C69: 122.98711 | D69: 40.079429 | E69: 71.180589 | F69: 6.1634107 | G69: 44.129462 | H69: 33.06 | I69: 362.84871 | J69: 1510.2154 | K69: 870.76505 | L69: 1051.4399 | M69: 311.881 | N69: 98.637 | O69: 25.064 | P69: 85.217369 | Q69: 362.00663 | R69: 1130.266 | S69: 173.688 | T69: 250.557 | U69: 195.118 | V69: 668.646 | W69: 139.82682 | X69: 53.228178 | Y69: 206.95391 | Z69: 176.475 | AA69: 103.32973 | AB69: 363.683 | AC69: 44.308892 | AD69: 15.318464 | AE69: 508.29396 | AF69: 116.68004 | AG69: 1521.088 | AH69: 3199.156 | AI69: 820.866 | AJ69: 797.688 | AK69: 234.933 | AL69: 0 | AM69: 713.03285 | AN69: 299.67315 | AO69: 627.8126 | AP69: 537.11353 | AQ69: 324.28971 | AR69: 548.36835 | AS69: 874.95181 | AT69: 1182.23 | AU69: 511.51011 | AV69: 1381.6969 | AW69: 182.621 | AX69: 301.59053 | AY69: 117.78691 | AZ69: 1924.71 | BA69: 1793.984 | BB69: 463.292 | BC69: 334.2775 | BD69: 643.144 | BE69: 2895.626 | BF69: 2629.691 | BG69: 366.40163 | BH69: 454.47607 | BI69: 80.738687 | BJ69: 7012.7115 | BK69: 2340.7526 | BL69: 7682.026 | BM69: =+SUM(C69:BL69) -> 51940.287
B70: Proprietor's income | C70: 47.692259 | D70: 15.542105 | E70: 8.5874286 | F70: 0.74357139 | G70: 17.112637 | H70: 3.726 | I70: 78.337547 | J70: 326.0493 | K70: 187.9946 | L70: 227.00155 | M70: -1.281 | N70: 0.251 | O70: 5.481 | P70: 0.70458088 | Q70: 92.994581 | R70: 11.11 | S70: -2.463 | T70: 54.561 | U70: 143.704 | V70: 85.267 | W70: 1.7455266 | X70: 0.66447338 | Y70: -4.7124114 | Z70: 15.445 | AA70: -2.3528534 | AB70: -7.022 | AC70: -1.0089286 | AD70: -0.34880666 | AE70: 11.840895 | AF70: 2.7181047 | AG70: 68.26 | AH70: 173.038 | AI70: 14.755 | AJ70: 29.826 | AK70: 11.378 | AL70: 0 | AM70: 1328.4391 | AN70: 558.31586 | AO70: 197.93539 | AP70: 169.33998 | AQ70: 102.24135 | AR70: 172.88838 | AS70: 275.8529 | AT70: 1.656 | AU70: 99.031363 | AV70: 267.50464 | AW70: 12.92 | AX70: 22.132967 | AY70: 36.923033 | AZ70: 469.217 | BA70: 1.417 | BB70: 87.548 | BC70: 45.924 | BD70: 260.246 | BE70: 127.091 | BF70: 253.172 | BG70: 122.7665 | BH70: 276.54667 | BI70: 98.258266 | BJ70: 0 | BK70: 0 | BL70: 0 | BM70: =+SUM(C70:BL70) -> 6604.7096
B71: Taxes on Production and Imports less Subsidies | C71: -3.3549062 | D71: -1.0933075 | E71: 2.6735055 | F71: 0.23149447 | G71: -1.2037864 | H71: 6.078 | I71: 12.570693 | J71: 52.320578 | K71: 30.167175 | L71: 36.426554 | M71: 28.675499 | N71: 12.993501 | O71: 1.07 | P71: 7.1510639 | Q71: 29.381936 | R71: 983.749 | S71: 21.797 | T71: 57.481 | U71: 7.727 | V71: 12.484546 | W71: 1.9774543 | X71: 0.61 | Y71: 4.037 | Z71: 8.665 | AA71: 9.7290049 | AB71: 78.503995 | AC71: 2.4291832 | AD71: 0.83981685 | AE71: 326.01785 | AF71: 74.838146 | AG71: 773.513 | AH71: 2836.754 | AI71: 71.731618 | AJ71: 231.938 | AK71: 13.839382 | AL71: 0 | AM71: 1544.2319 | AN71: 649.00913 | AO71: 83.965 | AP71: 28.582639 | AQ71: 76.356 | AR71: 29.181568 | AS71: 46.560793 | AT71: 15.603 | AU71: 32.141099 | AV71: 86.819901 | AW71: 27.285 | AX71: 47.696734 | AY71: 16.765266 | AZ71: 109.116 | BA71: 50.452 | BB71: 18.476 | BC71: 55.062 | BD71: 123.13 | BE71: 1371.686 | BF71: 200.227 | BG71: 39.605529 | BH71: 49.894889 | BI71: 10 | BJ71: -1.158 | BK71: 0 | BL71: -269.44 | BM71: =+SUM(C71:BL71) -> 10173.999
B72: Other capital costs | C72: 113.97243 | D72: 37.141697 | E72: 14.651363 | F72: 1.2686375 | G72: 40.894872 | H72: 47.636 | I72: 99.493139 | J72: 414.10115 | K72: 238.76383 | L72: 288.30488 | M72: 54.841429 | N72: 66.701571 | O72: 3.185 | P72: 398.32699 | Q72: 212.21685 | R72: 865.375 | S72: 167.978 | T72: 92.801 | U72: 39.551 | V72: 293.00188 | W72: 24.250776 | X72: 5.6973489 | Y72: 51.4215 | Z72: 231.815 | AA72: 205.88824 | AB72: 828.24738 | AC72: 90.029792 | AD72: 31.125086 | AE72: 1071.7757 | AF72: 263.4353 | AG72: 976.339 | AH72: 1618.352 | AI72: 1067.2474 | AJ72: 929.848 | AK72: -47.150382 | AL72: 9603.419 | AM72: 2372.335 | AN72: 997.04398 | AO72: 1.8870091 | AP72: 44.866468 | AQ72: 374.71294 | AR72: 45.806613 | AS72: 73.086966 | AT72: 109.011 | AU72: 76.808272 | AV72: 236.98773 | AW72: 120.774 | AX72: 493.71008 | AY72: 66.694475 | AZ72: 1608.357 | BA72: 265.847 | BB72: -34.116 | BC72: 339.5365 | BD72: 270.68 | BE72: 1863.197 | BF72: 562.11 | BG72: 272.49954 | BH72: 1.0670379 | BI72: 737.14518 | BJ72: 1162.6824 | BK72: 387.70184 | BL72: 1541.8238 | BM72: =+SUM(C72:BL72) -> 34434.204
B73: Value added | C73: 281.29689 | D73: 91.669924 | E73: 97.092886 | F73: 8.407114 | G73: 100.93318 | H73: 90.5 | I73: 553.25009 | J73: 2302.6864 | K73: 1327.6907 | L73: 1603.1729 | M73: 394.11693 | N73: 178.58307 | O73: 34.8 | P73: 491.4 | Q73: 696.6 | R73: 2990.5 | S73: 361 | T73: 455.4 | U73: 386.1 | V73: 1059.3994 | W73: 167.80058 | X73: 60.2 | Y73: 257.7 | Z73: 432.4 | AA73: 316.59412 | AB73: 1263.4124 | AC73: 135.75894 | AD73: 46.93456 | AE73: 1917.9284 | AF73: 457.6716 | AG73: 3339.2 | AH73: 7827.3 | AI73: 1974.6 | AJ73: 1989.3 | AK73: 213 | AL73: 9603.419 | AM73: 5958.0389 | AN73: 2504.0421 | AO73: 911.6 | AP73: 779.90261 | AQ73: 877.6 | AR73: 796.24491 | AS73: 1270.4525 | AT73: 1308.5 | AU73: 719.49084 | AV73: 1973.0092 | AW73: 343.6 | AX73: 865.13032 | AY73: 238.16968 | AZ73: 4111.4 | BA73: 2111.7 | BB73: 535.2 | BC73: 774.8 | BD73: 1297.2 | BE73: 6257.6 | BF73: 3645.2 | BG73: 801.2732 | BH73: 781.98467 | BI73: 926.14214 | BJ73: 8174.2358 | BK73: 2728.4544 | BL73: 8954.4098 | BM73: =+SUM(C73:BL73) -> 103153.2
B75: Output | C75: 488.77025 | D75: 159.282 | E75: 169.10505 | F75: 14.64253 | G75: 175.37747 | H75: 154.17066 | I75: 1161.9896 | J75: 4836.3258 | K75: 2788.545 | L75: 3367.1395 | M75: 1029.913 | N75: 466.67629 | O75: 70.365944 | P75: 2991.6094 | Q75: 983.60706 | R75: 4942.578 | S75: 417.61 | T75: 516.724 | U75: 572.27244 | V75: 2130.1676 | W75: 337.40188 | X75: 128.4395 | Y75: 831.58693 | Z75: 722.42225 | AA75: 415.20189 | AB75: 3350.292 | AC75: 178.043 | AD75: 61.553 | AE75: 3541.4 | AF75: 812.93649 | AG75: 4926.8152 | AH75: 10832.069 | AI75: 4714.5037 | AJ75: 2858.2201 | AK75: 909.58244 | AL75: 12888.098 | AM75: 7995.88 | AN75: 3360.5052 | AO75: 1839.8455 | AP75: 1574.046 | AQ75: 950.352 | AR75: 1607.029 | AS75: 2564.103 | AT75: 1839.3234 | AU75: 899.36355 | AV75: 2429.371 | AW75: 637.561 | AX75: 901.92273 | AY75: 317.02328 | AZ75: 4927.027 | BA75: 5451.497 | BB75: 826.843 | BC75: 912.508 | BD75: 1385.704 | BE75: 12175.872 | BF75: 7531.7134 | BG75: 937.49539 | BH75: 1181.053 | BI75: 1083.5929 | BJ75: 8174.2358 | BK75: 3031.616 | BL75: 9137.1528 | BM75: 143110.57 | BO75: =+BO66+BO67 -> 73020.645 | BP75: =+BP66+BP67 -> 22645.325 | BQ75: =+BQ66+BQ67 -> 46.33595 | BR75: =+BR66+BR67 -> 17045.15 | BS75: =+BS66+BS67 -> 2711.3087 | BT75: =+BT66+BT67 -> 11205.82 | BU75: =+BU66+BU67 -> 8991.315 | BV75: =+BV66+BV67 -> 392.41808 | ... BY75: =+BY66+BY67 -> 8223.029 | CA75: =+CA66+CA67 -> 201969.04
B77: Wage and salary jobs | C77: 3387.553 | D77: 1103.9465 | E77: 1495.5065 | F77: 129.49346 | G77: 1215.5005 | H77: 256 | I77: 3606.8143 | J77: 15011.949 | K77: 8655.64 | L77: 10451.597 | M77: 5862 | N77: 1261 | O77: 489 | P77: 389.32644 | Q77: 4527.6736 | R77: 9385 | S77: 1230 | T77: 3329 | U77: 3944 | V77: 8616 | W77: 2229.3489 | X77: 848.65106 | Y77: 1291.946 | Z77: 2423 | AA77: 645.05396 | AB77: 3227 | AC77: 617 | AD77: 306 | AE77: 2940.9079 | AF77: 675.09215 | AG77: 17333 | AH77: 64327 | AI77: 7718 | AJ77: 7403 | AK77: 1223 | AL77: 0 | AM77: 8791.9309 | AN77: 3695.0691 | AO77: 5648.4114 | AP77: 4832.3945 | AQ77: 2917.6249 | AR77: 4933.6538 | AS77: 7871.9155 | AT77: 8670 | AU77: 9441.5036 | AV77: 25503.496 | AW77: 2136 | AX77: 3747.6261 | AY77: 12387.374 | AZ77: 32521 | BA77: 16395 | BB77: 7893 | BC77: 16530 | BD77: 12045 | BE77: 37127 | BF77: 63783 | BG77: 4231 | BH77: 7424 | BI77: 15398 | BJ77: 63902.253 | BK77: 21329.747 | BL77: 87250 | BM77: =+SUM(C77:BL77) -> 683961
B78: Proprietor's jobs | C78: 3486.6806 | D78: 1136.2505 | E78: 2280.5324 | F78: 197.46757 | G78: 1251.0688 | H78: 445 | I78: 1103.2878 | J78: 4592.0027 | K78: 2647.6723 | L78: 3197.0372 | M78: 616 | N78: 44 | O78: 673 | P78: 97.33161 | Q78: 2302.6684 | R78: 96 | S78: 65 | T78: 366 | U78: 7453 | V78: 848 | W78: 4313.1166 | X78: 1641.8834 | Y78: 640.97065 | Z78: 533 | AA78: 320.02935 | AB78: 525 | AC78: 396 | AD78: 94 | AE78: 355.41392 | AF78: 81.586081 | AG78: 4356 | AH78: 19981 | AI78: 1256 | AJ78: 6402 | AK78: 11780 | AL78: 0 | AM78: 28588.737 | AN78: 12015.263 | AO78: 5105.6431 | AP78: 4368.039 | AQ78: 2637.2639 | AR78: 4459.5682 | AS78: 7115.4858 | AT78: 863 | AU78: 3904.3975 | AV78: 10546.603 | AW78: 195 | AX78: 1007.806 | AY78: 3331.194 | AZ78: 9051 | BA78: 14 | BB78: 1450 | BC78: 2100 | BD78: 9803 | BE78: 1392 | BF78: 4072 | BG78: 15730.536 | BH78: 17335.826 | BI78: 1133.199 | BJ78: 0 | BK78: 0 | BL78: 0 | BM78: =+SUM(C78:BL78) -> 231793.56
B79: Total jobs | C79: 6874.2336 | D79: 2240.1971 | E79: 3776.039 | F79: 326.96103 | G79: 2466.5693 | H79: 701 | I79: 4710.1021 | J79: 19603.952 | K79: 11303.312 | L79: 13648.634 | M79: 6478 | N79: 1305 | O79: 1162 | P79: 486.65805 | Q79: 6830.3419 | R79: 9481 | S79: 1295 | T79: 3695 | U79: 11397 | V79: 9464 | W79: 6542.4655 | X79: 2490.5345 | Y79: 1932.9167 | Z79: 2956 | AA79: 965.08331 | AB79: 3752 | AC79: 1013 | AD79: 400 | AE79: 3296.3218 | AF79: 756.67823 | AG79: 21689 | AH79: 84308 | AI79: 8974 | AJ79: 13805 | AK79: 13003 | AL79: 0 | AM79: 37380.668 | AN79: 15710.332 | AO79: 10754.054 | AP79: 9200.4335 | AQ79: 5554.8887 | AR79: 9393.222 | AS79: 14987.401 | AT79: 9533 | AU79: 13345.901 | AV79: 36050.099 | AW79: 2331 | AX79: 4755.4321 | AY79: 15718.568 | AZ79: 41572 | BA79: 16409 | BB79: 9343 | BC79: 18630 | BD79: 21848 | BE79: 38519 | BF79: 67855 | BG79: 19961.536 | BH79: 24759.826 | BI79: 16531.199 | BJ79: 63902.253 | BK79: 21329.747 | BL79: 87250 | BM79: =+SUM(C79:BL79) -> 915754.56
AX80: =+AX75*1000000/AX79 -> 189661.57
B81: Earnings (RIMS II for multiplier calculations) | C81: 150.39096 | D81: 49.009885 | E81: 63.454996 | F81: 5.4944642 | G81: 53.962341 | H81: 31.479864 | I81: 383.43947 | J81: 1595.9163 | K81: 920.1788 | L81: 1111.1065 | M81: 235.61937 | N81: 75.724265 | O81: 24.930259 | P81: 53.52504 | Q81: 383.27005 | R81: 870.64325 | S81: 130.67959 | T81: 242.53697 | U81: 302.10117 | V81: 638.8098 | W81: 122.66947 | X81: 46.696852 | Y81: 146.77936 | Z81: 154.71931 | AA81: 73.285262 | AB81: 286.43302 | AC81: 31.425502 | AD81: 12.250379 | AE81: 368.15318 | AF81: 84.510407 | AG81: 1348.9181 | AH81: 2821.9954 | AI81: 707.83897 | AJ81: 708.83084 | AK81: 206.20417 | AL81: 0 | AM81: 1942.1751 | AN81: 816.25653 | AO81: 739.46204 | AP81: 632.63315 | AQ81: 381.961 | AR81: 645.88952 | AS81: 1030.5522 | AT81: 976.10811 | AU81: 535.00999 | AV81: 1445.175 | AW81: 169.22639 | AX81: 287.94888 | AY81: 133.64024 | AZ81: 2049.6353 | BA81: 1481.1146 | BB81: 458.50754 | BC81: 320.40602 | BD81: 801.63314 | BE81: 2755.5666 | BF81: 2617.4861 | BG81: 366.38055 | BH81: 599.00469 | BI81: 164.55443 | BJ81: 4950.7132 | BK81: 1652.4842 | BL81: 5491.9292 | BM81: =+SUM(C81:BL81) -> 47888.437
B82: State taxes (for multiplier calculations) | C82: 13.109729 | D82: 3.6459777 | E82: 5.2030705 | F82: 0.44786418 | G82: 8.0197402 | H82: 4.0651307 | I82: 74.031267 | J82: 308.1261 | K82: 177.94522 | L82: 214.86703 | M82: 28.702418 | N82: 10.636998 | O82: 2.7879974 | P82: 25.087275 | Q82: 40.356702 | R82: 125.08111 | S82: 19.05467 | T82: 33.557272 | U82: 35.482623 | V82: 103.61785 | W82: 19.593509 | X82: 7.2275377 | Y82: 35.269555 | Z82: 33.232261 | AA82: 16.12209 | AB82: 101.85138 | AC82: 7.7648808 | AD82: 2.6086645 | AE82: 213.98603 | AF82: 23.576275 | AG82: 253.97659 | AH82: 2002.0327 | AI82: 115.69256 | AJ82: 335.24236 | AK82: 32.701912 | AL82: 76.584694 | AM82: 709.86377 | AN82: 262.38979 | AO82: 109.79346 | AP82: 94.121818 | AQ82: 57.340451 | AR82: 87.825278 | AS82: 148.6496 | AT82: 135.59548 | AU82: 60.10272 | AV82: 175.17915 | AW82: 30.974664 | AX82: 53.089502 | AY82: 19.70379 | AZ82: 294.04072 | BA82: 279.77956 | BB82: 39.318359 | BC82: 49.703737 | BD82: 88.91374 | BE82: 1299.1189 | BF82: 384.52473 | BG82: 42.825363 | BH82: 72.17788 | BI82: 19.7652 | BJ82: 541.70052 | BK82: 183.80308 | BL82: 527.91369 | BM82: =+SUM(C82:BL82) -> 10279.504
B83: State individual income tax | C83: 8.0309122 | D83: 2.0530837 | E83: 3.6646173 | F83: 0.30881504 | G83: 3.0559297 | H83: 2.4420489 | I83: 25.555093 | J83: 106.36305 | K83: 61.327162 | L83: 74.05192 | M83: 18.600401 | N83: 5.9317561 | O83: 2.0243331 | P83: 5.6805334 | Q83: 29.549226 | R83: 72.072446 | S83: 11.037169 | T83: 18.250093 | U83: 18.706851 | V83: 41.842152 | W83: 9.7107938 | X83: 3.1759367 | Y83: 11.159289 | Z83: 12.125326 | AA83: 4.2271131 | AB83: 22.069497 | AC83: 2.6230248 | AD83: 0.81862357 | AE83: 29.086505 | AF83: 6.4302895 | AG83: 98.767962 | AH83: 186.75572 | AI83: 52.148997 | AJ83: 55.685183 | AK83: 15.820277 | AL83: 0 | AM83: 124.09666 | AN83: 51.36815 | AO83: 53.49414 | AP83: 45.557595 | AQ83: 27.725812 | AR83: 39.242726 | AS83: 71.509983 | AT83: 77.54845 | AU83: 33.6212 | AV83: 100.6567 | AW83: 12.705668 | AX83: 23.83547 | AY83: 9.8379313 | AZ83: 142.69659 | BA83: 116.31812 | BB83: 32.31875 | BC83: 22.161396 | BD83: 48.579977 | BE83: 150.82839 | BF83: 162.46685 | BG83: 22.298074 | BH83: 37.244193 | BI83: 11.297604 | BJ83: 461.04954 | BK83: 153.89238 | BL83: 443.70252 | BM83: =+SUM(C83:BL83) -> 3497.207
B84: State GET | C84: 1.2539404 | D84: 0.40963305 | E84: 0.4411787 | F84: 0.039581564 | G84: 3.6173173 | H84: 0.43429808 | I84: 39.491872 | J84: 164.36942 | K84: 94.772673 | L84: 114.43703 | M84: 2.8484791 | N84: 1.2842259 | O84: 0.19880327 | P84: 0 | Q84: 2.7032912 | R84: 0 | S84: 0 | T84: 11.18682 | U84: 12.496819 | V84: 44.979609 | W84: 7.3371751 | X84: 2.8065807 | Y84: 18.365608 | Z84: 15.954704 | AA84: 8.9606683 | AB84: 0 | AC84: 3.9320819 | AD84: 1.3593988 | AE84: 0 | AF84: 0 | AG84: 117.902 | AH84: 1732.276 | AI84: 0 | AJ84: 2.3979659 | AK84: 0.76214058 | AL84: 0 | AM84: 441.13941 | AN84: 190.52559 | AO84: 41.08623 | AP84: 35.396739 | AQ84: 21.24473 | AR84: 34.567675 | AS84: 56.69017 | AT84: 41.631565 | AU84: 19.797981 | AV84: 52.776816 | AW84: 13.68995 | AX84: 20.581579 | AY84: 6.9338904 | AZ84: 107.99488 | BA84: 120.24495 | BB84: 0 | BC84: 20.132339 | BD84: 29.21132 | BE84: 252.05102 | BF84: 163.68294 | BG84: 14.943765 | BH84: 25.649131 | BI84: 0 | BJ84: 0 | BK84: 0 | BL84: 0 | BM84: =+SUM(C84:BL84) -> 4116.992
B85: State TAT | BE85: 810.038 | BM85: =+SUM(C85:BL85) -> 810.038
B86: State other taxes | C86: 3.8248767 | D86: 1.183261 | E86: 1.0972745 | F86: 0.099467582 | G86: 1.3464931 | H86: 1.1887837 | I86: 8.9843022 | J86: 37.393633 | K86: 21.84538 | L86: 26.378073 | M86: 7.2535377 | N86: 3.4210158 | O86: 0.5648611 | P86: 19.406741 | Q86: 8.1041847 | R86: 53.008663 | S86: 8.0175007 | T86: 4.1203584 | U86: 4.2789528 | V86: 16.796092 | W86: 2.5455406 | X86: 1.2450204 | Y86: 5.7446589 | Z86: 5.1522303 | AA86: 2.9343086 | AB86: 79.781883 | AC86: 1.2097742 | AD86: 0.43064217 | AE86: 184.89953 | AF86: 17.145985 | AG86: 37.306631 | AH86: 83.001025 | AI86: 63.543558 | AJ86: 277.15921 | AK86: 16.119494 | AL86: 76.584694 | AM86: 144.6277 | AN86: 20.496048 | AO86: 15.213085 | AP86: 13.167484 | AQ86: 8.3699093 | AR86: 14.014878 | AS86: 20.449451 | AT86: 16.415463 | AU86: 6.6835395 | AV86: 21.745635 | AW86: 4.579046 | AX86: 8.6724528 | AY86: 2.9319684 | AZ86: 43.349249 | BA86: 43.216485 | BB86: 6.9996086 | BC86: 7.4100017 | BD86: 11.122444 | BE86: 86.201462 | BF86: 58.374931 | BG86: 5.5835249 | BH86: 9.2845557 | BI86: 8.4675962 | BJ86: 80.650986 | BK86: 29.910693 | BL86: 84.211166 | BM86: =+SUM(C86:BL86) -> 1855.267
B88: Earnings (Labor Income) | C88: =C69+C70 -> 170.67937 | D88: =D69+D70 -> 55.621534 | E88: =E69+E70 -> 79.768018 | F88: =F69+F70 -> 6.9069821 | G88: =G69+G70 -> 61.242098 | H88: =H69+H70 -> 36.786 | I88: =I69+I70 -> 441.18625 | J88: =J69+J70 -> 1836.2647 | ... BM88: =BM69+BM70 -> 58544.997
B89: Earnings (Labor Income)/Output Ratio | C89: =C88/C75 -> 0.34920163 | D89: =D88/D75 -> 0.34920163 | E89: =E88/E75 -> 0.47170689 | F89: =F88/F75 -> 0.47170689 | G89: =G88/G75 -> 0.34920163 | H89: =H88/H75 -> 0.23860571 | I89: =I88/I75 -> 0.37968175 | J89: =J88/J75 -> 0.37968175 | ... BM89: =BM88/BM75 -> 0.40908926

Sheet fd, income ML
A1: 2022Detailed Output, Earnings, Employment, and Tax Multipliers for Hawaii
C3: Final demand multipliers | T3: Direct effect multipliers
C4: Output multipliers | F4: Earnings multipliers | I4: State tax multipliers | K4: State income tax multipliers | M4: State GET multipliers | O4: State TAT multipliers | Q4: State Other Taxes multipliers | T4: Earnings multipliers | DG4: Federal military consumption | DH4: Federal civilian consumption
B5: Industry | C5: type 1 | D5: type 2 | F5: type 1 | G5: type 2 | I5: type 1 | J5: type 2 | K5: type 1 | L5: type 2 | M5: type 1 | N5: type 2 | O5: type 1 | P5: type 2 | Q5: type 1 | R5: type 2 | T5: type 1 | U5: type 2
A6: 1 | B6: Crop production | C6: 1.3700296 | D6: 1.878914 | E6: =D6/C6 -> 1.3714404 | F6: 0.41330547 | G6: 0.54943284 | I6: 0.049811614 | J6: 0.079954802 | K6: 0.023577817 | L6: 0.033345632 | M6: 0.011720837 | N6: 0.024385689 | O6: 0.0010067034 | P6: 0.0021199625 | Q6: 0.013506257 | R6: 0.020103518 | T6: 1.3432417 | U6: 1.7856553
A7: =A6+1 -> 2 | B7: Animal production | C7: 1.3255298 | D7: 1.8234871 | E7: =D7/C7 -> 1.3756666 | F7: 0.40443071 | G7: 0.53763507 | I7: 0.038064329 | J7: 0.067560263 | K7: 0.019364517 | L7: 0.028922591 | M7: 0.0066948245 | N7: 0.019087729 | O7: 0.00065799961 | P7: 0.0017473541 | Q7: 0.011346988 | R7: 0.017802589 | T7: 1.3143988 | U7: 1.7473126
A8: =A7+1 -> 3 | B8: Commercial fishing | C8: 1.4311491 | D8: 2.0558189 | E8: =D8/C8 -> 1.4364812 | F8: 0.50734397 | G8: 0.67444411 | I8: 0.058773103 | J8: 0.095774705 | K8: 0.03082976 | L8: 0.042820024 | M8: 0.016477139 | N8: 0.032023598 | O8: 0.00064616984 | P8: 0.0020127263 | Q8: 0.010820034 | R8: 0.018918357 | T8: 1.3520516 | U8: 1.7973668
A9: =A8+1 -> 4 | B9: Forestry & logging | C9: 1.5222268 | D9: 2.2192086 | E9: =D9/C9 -> 1.4578699 | F9: 0.56607437 | G9: 0.75251811 | I9: 0.048089113 | J9: 0.089374041 | K9: 0.031976121 | L9: 0.045354384 | M9: 0.0054054892 | N9: 0.022751614 | O9: 9.1402346e-05 | P9: 0.0016161521 | Q9: 0.010616101 | R9: 0.01965189 | T9: 1.5085658 | U9: 2.005431
A10: =A9+1 -> 5 | B10: Support activities for agriculture | C10: 1.432057 | D10: 1.957929 | E10: =D10/C10 -> 1.3672144 | F10: 0.42710244 | G10: 0.56777402 | I10: 0.065141687 | J10: 0.096291116 | K10: 0.025662069 | L10: 0.035755954 | M10: 0.026738047 | N10: 0.039825678 | O10: 0.00049353912 | P10: 0.001643961 | Q10: 0.012248032 | R10: 0.019065523 | T10: 1.3880819 | U10: 1.8452641
A11: =A10+1 -> 6 | B11: Mining | C11: 1.4978496 | D11: 1.9308596 | E11: =D11/C11 -> 1.2890878 | F11: 0.3516819 | G11: 0.46751277 | I11: 0.056316205 | J11: 0.081965064 | K11: 0.026068495 | L11: 0.034379935 | M11: 0.014158335 | N11: 0.024934866 | O11: 0.0015339173 | P11: 0.0024811901 | Q11: 0.014555458 | R11: 0.020169073 | T11: 1.7223401 | U11: 2.2896146
A12: =A11+1 -> 7 | B12: Single family construction | C12: 1.4745155 | D12: 2.0447628 | E12: =D12/C12 -> 1.3867354 | F12: 0.46314317 | G12: 0.61568522 | I12: 0.10147814 | J12: 0.13525609 | K12: 0.031368155 | L12: 0.042313804 | M12: 0.053871173 | N12: 0.068063194 | O12: 0.0017761671 | P12: 0.0030236665 | Q12: 0.014462641 | R12: 0.021855422 | T12: 1.4035268 | U12: 1.865796
A13: =A12+1 -> 8 | B13: Construction of other buildings | C13: 1.5152142 | D13: 2.1186079 | E13: =D13/C13 -> 1.3982233 | F13: 0.49006396 | G13: 0.65147272 | I13: 0.10431306 | J13: 0.1400544 | K13: 0.033237908 | L13: 0.044819787 | M13: 0.054756076 | N13: 0.069773026 | O13: 0.0022917198 | P13: 0.0036117317 | Q13: 0.014027356 | R13: 0.021849852 | T13: 1.4851086 | U13: 1.9742478
A14: =A13+1 -> 9 | B14: Heavy and civil engineering construction | C14: 1.5218928 | D14: 2.130474 | E14: =D14/C14 -> 1.3998844 | F14: 0.49427718 | G14: 0.65707361 | I14: 0.10067601 | J14: 0.13672463 | K14: 0.033509372 | L14: 0.045190824 | M14: 0.050237778 | N14: 0.065383834 | O14: 0.0025399429 | P14: 0.0038713034 | Q14: 0.014388922 | R14: 0.02227867 | T14: 1.4978765 | U14: 1.991221
A15: =A14+1 -> 10 | B15: Maintenance & repairs | C15: 1.4720762 | D15: 2.0506088 | E15: =D15/C15 -> 1.3930046 | F15: 0.46987238 | G15: 0.62463078 | I15: 0.10408979 | J15: 0.13835852 | K15: 0.031724652 | L15: 0.042829335 | M15: 0.057285193 | N15: 0.071683416 | O15: 0.0019951487 | P15: 0.0032607736 | Q15: 0.013084799 | R15: 0.020584993 | T15: 1.4239192 | U15: 1.892905
A16: =A15+1 -> 11 | B16: Food processing | C16: 1.5958613 | D16: 2.113805 | E16: =D16/C16 -> 1.3245544 | F16: 0.42066327 | G16: 0.55921403 | I16: 0.064371558 | J16: 0.095051365 | K16: 0.031255458 | L16: 0.041197163 | M16: 0.015719985 | N16: 0.028610302 | O16: 0.0038267074 | P16: 0.0049597851 | Q16: 0.013569407 | R16: 0.020284115 | T16: 1.8387562 | U16: 2.4443738
A17: =A16+1 -> 12 | B17: Beverage manufacturing | C17: 1.5841104 | D17: 2.0003106 | E17: =D17/C17 -> 1.2627343 | F17: 0.33802929 | G17: 0.4493635 | I17: 0.05726688 | J17: 0.081920026 | K17: 0.025324344 | L17: 0.033313127 | M17: 0.015481775 | N17: 0.025839952 | O17: 0.0031189649 | P17: 0.0040294638 | Q17: 0.013341795 | R17: 0.018737484 | T17: 2.0832193 | U17: 2.7693539
A18: =A17+1 -> 13 | B18: Apparel and textile manufacturing | C18: 1.418927 | D18: 2.0151392 | E18: =D18/C18 -> 1.4201852 | F18: 0.48423133 | G18: 0.64371903 | I18: 0.067233143 | J18: 0.10254909 | K18: 0.037903784 | L18: 0.049347818 | M18: 0.013692009 | N18: 0.028530231 | O18: 0.0025253249 | P18: 0.0038296264 | Q18: 0.013112025 | R18: 0.020841419 | T18: 1.3667485 | U18: 1.8169044
... A40: =A39+1 -> 35 | B40: Other finance and insurance | C40: 1.8639635 | D40: 2.4525619 | E40: =D40/C40 -> 1.3157778 | F40: 0.47804751 | G40: 0.6354985 | I40: 0.088972378 | J40: 0.12383733 | K40: 0.035384707 | L40: 0.046682597 | M40: 0.018829262 | N40: 0.033477994 | O40: 0.0049164824 | P40: 0.0062041274 | Q40: 0.029841927 | R40: 0.037472614 | T40: 2.1087043 | U40: 2.8032327
A41: =A40+1 -> 36 | B41: Owner-occupied dwellings | C41: 1.3208347 | D41: 1.4300097 | E41: =D41/C41 -> 1.082656 | F41: 0.088669664 | G41: 0.11787414 | I41: 0.029176152 | J41: 0.035643006 | K41: 0.0061836243 | L41: 0.0082791902 | M41: 0.0092969883 | N41: 0.012014078 | O41: 0.00051303497 | P41: 0.00075187116 | Q41: 0.013182504 | R41: 0.014597867 | T41: NA | U41: NA
A42: =A41+1 -> 37 | B42: Real estate | C42: 1.3348462 | D42: 1.755656 | E42: =D42/C42 -> 1.3152496 | F42: 0.34177309 | G42: 0.45434037 | I42: 0.11351556 | J42: 0.13844175 | K42: 0.02239259 | L42: 0.030469851 | M42: 0.064575648 | N42: 0.075048545 | O42: 0.002720517 | P42: 0.0036411 | Q42: 0.023826805 | R42: 0.029282253 | T42: 1.4070702 | U42: 1.8705065
A43: =A42+1 -> 38 | B43: Rental & leasing and others | C43: 1.2754109 | D43: 1.6934186 | E43: =D43/C43 -> 1.3277436 | F43: 0.33949734 | G43: 0.45131508 | I43: 0.09608714 | J43: 0.12084735 | K43: 0.022264881 | L43: 0.030288358 | M43: 0.061744095 | N43: 0.072147257 | O43: 0.0023667457 | P43: 0.0032811989 | Q43: 0.0097114187 | R43: 0.015130541 | T43: 1.397701 | U43: 1.8580514
A44: =A43+1 -> 39 | B44: Legal services | C44: 1.6827391 | D44: 2.4278698 | E44: =D44/C44 -> 1.4428082 | F44: 0.60517985 | G44: 0.80450348 | I44: 0.11150755 | J44: 0.15564451 | K44: 0.04285265 | L44: 0.05715511 | M44: 0.040395873 | N44: 0.058940301 | O44: 0.01225248 | P44: 0.013882562 | Q44: 0.016006543 | R44: 0.025666541 | T44: 1.5057398 | U44: 2.0016742
A45: =A44+1 -> 40 | B45: Architectural and engineering services | C45: 1.5996094 | D45: 2.3196113 | E45: =D45/C45 -> 1.450111 | F45: 0.58477076 | G45: 0.77737239 | I45: 0.099691003 | J45: 0.1423395 | K45: 0.041663198 | L45: 0.055483321 | M45: 0.040000426 | N45: 0.057919461 | O45: 0.0019900351 | P45: 0.0035651445 | Q45: 0.016037344 | R45: 0.025371568 | T45: 1.4549602 | U45: 1.9341698
A46: =A45+1 -> 41 | B46: Computer systems design services | C46: 1.0896405 | D46: 1.6168268 | E46: =D46/C46 -> 1.4838167 | F46: 0.42816991 | G46: 0.56919308 | I46: 0.067028891 | J46: 0.098256173 | K46: 0.03095735 | L46: 0.041076462 | M46: 0.024966566 | N46: 0.038086907 | O46: 0.0012993875 | P46: 0.0024526846 | Q46: 0.0098055874 | R46: 0.016640118 | T46: 1.0653238 | U46: 1.4162016
A47: =A46+1 -> 42 | B47: R&D in the physical, engineering, & life sciences | C47: 1.4706667 | D47: 2.1318293 | E47: =D47/C47 -> 1.4495666 | F47: 0.53698272 | G47: 0.71384475 | I47: 0.087208129 | J47: 0.12637134 | K47: 0.03381565 | L47: 0.046506379 | M47: 0.03470436 | N47: 0.051159035 | O47: 0.0038310597 | P47: 0.0052774497 | Q47: 0.014857059 | R47: 0.023428481 | T47: 1.3360595 | U47: 1.7761075
A48: =A47+1 -> 43 | B48: Other professional services | C48: 1.6171634 | D48: 2.3443143 | E48: =D48/C48 -> 1.4496459 | F48: 0.59057705 | G48: 0.78509105 | I48: 0.10068985 | J48: 0.14376181 | K48: 0.040914547 | L48: 0.054871892 | M48: 0.037579736 | N48: 0.055676693 | O48: 0.0071982443 | P48: 0.0087889933 | Q48: 0.014997326 | R48: 0.024424231 | T48: 1.4694068 | U48: 1.9533745
A49: =A48+1 -> 44 | B49: Management of companies and enterprises | C49: 1.3571027 | D49: 2.1548652 | E49: =D49/C49 -> 1.5878424 | F49: 0.64792639 | G49: 0.86132913 | I49: 0.097204103 | J49: 0.14445866 | K49: 0.050236151 | L49: 0.065548857 | M49: 0.03240405 | N49: 0.052258353 | O49: 0.00099192365 | P49: 0.002737146 | Q49: 0.013571978 | R49: 0.023914305 | T49: 1.2209162 | U49: 1.6230404
A50: =A49+1 -> 45 | B50: Travel arrangement and reservation services | C50: 1.2316069 | D50: 2.0513585 | E50: =D50/C50 -> 1.6655952 | F50: 0.66578548 | G50: 0.88507033 | I50: 0.082282795 | J50: 0.13083985 | K50: 0.042343446 | L50: 0.058078223 | M50: 0.027783923 | N50: 0.04818548 | O50: 0.0017849651 | P50: 0.0035782917 | Q50: 0.010370461 | R50: 0.020997857 | T50: 1.1192 | U50: 1.4878227
A51: =A50+1 -> 46 | B51: Administrative and support services | C51: 1.2295735 | D51: 2.0519027 | E51: =D51/C51 -> 1.6687923 | F51: 0.66787897 | G51: 0.88785334 | I51: 0.088833562 | J51: 0.1375433 | K51: 0.046553094 | L51: 0.062337347 | M51: 0.028800022 | N51: 0.049265729 | O51: 0.0017828773 | P51: 0.0035818429 | Q51: 0.011697568 | R51: 0.022358381 | T51: 1.1227192 | U51: 1.492501
A52: =A51+1 -> 47 | B52: Waste management and remediation services | C52: 1.5621899 | D52: 2.12704 | E52: =D52/C52 -> 1.3615758 | F52: 0.45875962 | G52: 0.60985789 | I52: 0.083089538 | J52: 0.11654779 | K52: 0.034259962 | L52: 0.045102013 | M52: 0.032292499 | N52: 0.046350196 | O52: 0.0029325148 | P52: 0.0041682069 | Q52: 0.013604561 | R52: 0.020927371 | T52: 1.7283784 | U52: 2.2976417
A53: =A52+1 -> 48 | B53: Colleges, universities, and professional schools | C53: 1.0525687 | D53: 1.4647983 | E53: =D53/C53 -> 1.3916416 | F53: 0.3348045 | G53: 0.44507659 | I53: 0.062413171 | J53: 0.086831128 | K53: 0.027500666 | L53: 0.035413236 | M53: 0.024250551 | N53: 0.034509911 | O53: 0.00038672429 | P53: 0.0012885371 | Q53: 0.01027523 | R53: 0.015619444 | T53: 1.0486854 | U53: 1.3940832
... A55: =A54+1 -> 50 | B55: Ambulatory health care services | C55: 1.1607409 | D55: 1.7506545 | E55: =D55/C55 -> 1.5082216 | F55: 0.47911575 | G55: 0.63691856 | I55: 0.06965984 | J55: 0.1046027 | K55: 0.033366579 | L55: 0.044689715 | M55: 0.025624898 | N55: 0.040306364 | O55: 0.0003133927 | P55: 0.0016039151 | Q55: 0.01035497 | R55: 0.018002708 | T55: 1.151725 | U55: 1.5310602
A56: =A55+1 -> 51 | B56: Hospitals | C56: 1.6391653 | D56: 2.2345214 | F56: 0.48353595 | G56: 0.64279462 | I56: 0.096290535 | J56: 0.13155577 | K56: 0.03623226 | L56: 0.04765986 | M56: 0.038367664 | N56: 0.053184578 | O56: 0.0055544722 | P56: 0.0068569006 | Q56: 0.016136138 | R56: 0.023854433 | T56: 1.7797372 | U56: 2.3659161
A57: =A56+1 -> 52 | B57: Nursing and residential care facilities | C57: 1.3623604 | D57: 2.176905 | F57: 0.66155646 | G57: 0.87944843 | I57: 0.070304472 | J57: 0.1185531 | K57: 0.046425385 | L57: 0.062060216 | M57: 0.0082568184 | N57: 0.028528786 | O57: 0.0018995495 | P57: 0.0036814851 | Q57: 0.013722718 | R57: 0.02428261 | T57: 1.1930084 | U57: 1.5859407
A58: =A57+1 -> 53 | B58: Social assistance | C58: 1.1670253 | D58: 1.6657918 | F58: 0.40508788 | G58: 0.53850869 | I58: 0.065232532 | J58: 0.094776396 | K58: 0.028123258 | L58: 0.037696863 | M58: 0.026091422 | N58: 0.038504464 | O58: 0.0007893872 | P58: 0.0018805118 | Q58: 0.010228466 | R58: 0.016694557 | T58: 1.1536798 | U58: 1.5336587
A59: =A58+1 -> 54 | B59: Arts and entertainment | C59: 1.0701682 | D59: 1.81337 | F59: 0.60361332 | G59: 0.80242099 | I59: 0.068616813 | J59: 0.11263953 | K59: 0.036799794 | L59: 0.051065231 | M59: 0.022631317 | N59: 0.041127743 | O59: 0.00023509784 | P59: 0.0018609607 | Q59: 0.0089506034 | R59: 0.018585596 | T59: 1.0434067 | U59: 1.3870659
A60: =A59+1 -> 55 | B60: Accommodation | C60: 1.5887531 | D60: 2.1022555 | F60: 0.41705614 | G60: 0.55441884 | I60: 0.14493547 | J60: 0.1753522 | K60: 0.025852527 | L60: 0.035708982 | M60: 0.03379446 | N60: 0.046574243 | O60: 0.069595049 | P60: 0.070718411 | Q60: 0.015693436 | R60: 0.022350566 | T60: 1.8428232 | U60: 2.4497802
A61: =A60+1 -> 56 | B61: Eating and drinking | C61: 1.5189485 | D61: 2.1393386 | F61: 0.50386815 | G61: 0.66982348 | I61: 0.083250679 | J61: 0.11999878 | K61: 0.0324781 | L61: 0.044386219 | M61: 0.033540958 | N61: 0.048980908 | O61: 0.0028233992 | P61: 0.0041805934 | Q61: 0.014408223 | R61: 0.022451063 | T61: 1.4498608 | U61: 1.9273908
A62: =A61+1 -> 57 | B62: Repair and maintenance | C62: 1.1186764 | D62: 1.6430934 | F62: 0.42592077 | G62: 0.56620316 | I62: 0.054358261 | J62: 0.085421509 | K62: 0.026253679 | L62: 0.036319637 | M62: 0.019256446 | N62: 0.032307867 | O62: 0.0014055224 | P62: 0.0025527614 | Q62: 0.0074426137 | R62: 0.014241243 | T62: 1.089847 | U62: 1.4488019
A63: =A62+1 -> 58 | B63: Personal and laundry services | C63: 1.3578701 | D63: 2.1166241 | F63: 0.61624447 | G63: 0.81921237 | I63: 0.086844964 | J63: 0.1317889 | K63: 0.039168647 | L63: 0.053732601 | M63: 0.032081802 | N63: 0.050965281 | O63: 0.0029726832 | P63: 0.0046325687 | Q63: 0.012621832 | R63: 0.022458445 | T63: 1.2150446 | U63: 1.6152348
A64: =A63+1 -> 59 | B64: Organizations | C64: 1.1720234 | D64: 1.4246669 | F64: 0.20519186 | G64: 0.27277439 | I64: 0.029664573 | J64: 0.044629622 | K64: 0.014150344 | L64: 0.018999726 | M64: 0.004287776 | N64: 0.010575437 | O64: 0.00074768594 | P64: 0.0013003805 | Q64: 0.010478767 | R64: 0.013754079 | T64: 1.3511909 | U64: 1.7962226
A65: =A64+1 -> 60 | B65: Federal government military | C65: 1 | D65: 1.7457076 | F65: 0.60564844 | G65: 0.8051264 | I65: 0.066269256 | J65: 0.1104404 | K65: 0.056402769 | L65: 0.070716303 | M65: 0 | N65: 0.018558787 | O65: 0 | P65: 0.0016313445 | Q65: 0.0098664864 | R65: 0.019533964 | T65: 1 | U65: 1.3293626
A66: =A65+1 -> 61 | B66: Federal government: civilian | C66: 1.102632 | D66: 1.8112969 | F66: 0.5755631 | G66: 0.76513208 | I66: 0.066276046 | J66: 0.10825301 | K66: 0.052975267 | L66: 0.066577782 | M66: 0.001863268 | N66: 0.019500155 | O66: 0.00032392455 | P66: 0.0018742327 | Q66: 0.011113586 | R66: 0.020300836 | T66: 1.0559171 | U66: 1.4036967
A67: =A66+1 -> 62 | B67: State and local government | C67: 1.0213749 | D67: 1.7694974 | F67: 0.60760978 | G67: 0.80773373 | I67: 0.05913851 | J67: 0.1034527 | K67: 0.049019591 | L67: 0.063379478 | M67: 0.00045820863 | N67: 0.019077097 | O67: 0.00016977664 | P67: 0.0018064041 | Q67: 0.009490934 | R67: 0.019189719 | T67: 1.0109059 | U67: 1.3438605
B69: PCE | C69: 1.1577493 | D69: 1.5390686 | F69: 0.30969976 | G69: 0.41170328 | I69: 0.068577963 | J69: 0.091164981 | K69: 0.022222495 | L69: 0.029541754 | M69: 0.028813468 | N69: 0.038303548 | O69: 0.002532746 | P69: 0.0033669379 | Q69: 0.015009254 | R69: 0.019952742
B70: Visitor's expenditures | C70: 1.3425405 | D70: 1.8182147 | F70: 0.38633283 | G70: 0.51357642 | I70: 0.11168015 | J70: 0.13985617 | K70: 0.02552008 | L70: 0.034650439 | M70: 0.048237767 | N70: 0.060076102 | O70: 0.024805433 | P70: 0.02584604 | Q70: 0.013116868 | R70: 0.019283588
B71: State and local government consumption | C71: 0.46964813 | D71: 0.69995673 | F71: 0.18705192 | G71: 0.24865983 | I71: 0.027082074 | J71: 0.040724142 | K71: 0.014485111 | L71: 0.018905784 | M71: 0.0049179725 | N71: 0.010649774 | O71: 0.00063321689 | P71: 0.0011370506 | Q71: 0.007045774 | R71: 0.010031533
B72: Federal defense consumption | C72: 0.99553514 | D72: 1.7104684 | F72: 0.58065413 | G72: 0.7718999 | I72: 0.065295283 | J72: 0.10764354 | K72: 0.053282944 | L72: 0.067005777 | M72: 0.0018064704 | N72: 0.019599361 | O72: 0.0001826016 | P72: 0.0017466227 | Q72: 0.010023267 | R72: 0.019291781
B73: Federal nondefense consumption | C73: 1.0839563 | D73: 1.7172084 | F73: 0.51431433 | G73: 0.68371024 | I73: 0.065366557 | J73: 0.10287652 | K73: 0.045166536 | L73: 0.057321534 | M73: 0.0060728277 | N73: 0.021832878 | O73: 0.0021490158 | P73: 0.0035343473 | Q73: 0.011978178 | R73: 0.020187763

Sheet job ML
B1: Job multipliers for years 2022-2032
D2: Direct effect multipliers | J2: Final demand multipliers
D3: w&s job/w&s job multipliers | G3: total job/total job multipliers | J3: W&S job multipliers | M3: Total jobs multipliers | P3: W&S job multipliers | S3: Total jobs multipliers | V3: W&S job multipliers | Y3: Total jobs multipliers | AB3: W&S job multipliers | AE3: Total jobs multipliers | AH3: W&S job multipliers | AK3: Total jobs multipliers | AN3: W&S job multipliers | AQ3: Total jobs multipliers | AT3: W&S job multipliers | AW3: Total jobs multipliers | AZ3: W&S job multipliers | BC3: Total jobs multipliers | BF3: W&S job multipliers | BI3: Total jobs multipliers | BL3: W&S job multipliers | BO3: Total jobs multipliers | BR3: W&S job multipliers | BU3: Total jobs multipliers
B4: Industry | D4: Type 1 | E4: Type 2 | G4: Type 1 | H4: Type 2 | J4: type 1 | K4: type 2 | M4: type 1 | N4: type 2 | P4: type 1 | Q4: type 2 | S4: type 1 | T4: type 2 | V4: type 1 | W4: type 2 | Y4: type 1 | Z4: type 2 | AB4: type 1 | AC4: type 2 | AE4: type 1 | AF4: type 2 | AH4: type 1 | AI4: type 2 | AK4: type 1 | AL4: type 2 | AN4: type 1 | AO4: type 2 | AQ4: type 1 | AR4: type 2 | AT4: type 1 | AU4: type 2 | AW4: type 1 | AX4: type 2 | AZ4: type 1 | BA4: type 2 | BC4: type 1 | BD4: type 2 | BF4: type 1 | BG4: type 2 | BI4: type 1 | BJ4: type 2 | BL4: type 1 | BM4: type 2 | BO4: type 1 | BP4: type 2 | BR4: type 1 | BS4: type 2 | BU4: type 1 | BV4: type 2
D5: 2022 | E5: 2022 | G5: 2022 | H5: 2022 | J5: 2022 | K5: 2022 | M5: 2022 | N5: 2022 | P5: 2023 | Q5: 2023 | S5: 2023 | T5: 2023 | V5: 2024 | W5: 2024 | Y5: 2024 | Z5: 2024 | AB5: 2025 | AC5: 2025 | AE5: 2025 | AF5: 2025 | AH5: 2026 | AI5: 2026 | AK5: 2026 | AL5: 2026 | AN5: 2027 | AO5: 2027 | AQ5: 2027 | AR5: 2027 | AT5: 2028 | AU5: 2028 | AW5: 2028 | AX5: 2028 | AZ5: 2029 | BA5: 2029 | BC5: 2029 | BD5: 2029 | BF5: 2030 | BG5: 2030 | BI5: 2030 | BJ5: 2030 | BL5: 2031 | BM5: 2031 | BO5: 2031 | BP5: 2031 | BR5: 2032 | BS5: 2032 | BU5: 2032 | BV5: 2032
A6: 1 | B6: Crop production | D6: 1.2263863 | E6: 1.5286101 | G6: 1.1951236 | H6: 1.4012304 | J6: 8.4997987 | K6: 10.594441 | M6: 16.808631 | N6: 19.707388 | P6: 7.8711865 | Q6: 9.9193666 | S6: 15.563229 | T6: 18.417679 | V6: 7.2984074 | W6: 9.3065027 | Y6: 14.43212 | Z6: 17.254066 | AB6: 7.1611977 | AC6: 9.1044286 | AE6: 14.168715 | AF6: 16.900212 | AH6: 7.0268604 | AI6: 8.9074044 | AK6: 13.910527 | AL6: 16.554585 | AN6: 6.8953249 | AO6: 8.7152835 | AQ6: 13.657439 | AR6: 16.216963 | AT6: 6.7665225 | AU6: 8.5279244 | AW6: 13.409336 | AX6: 15.887132 | AZ6: 6.6403868 | BA6: 8.3451901 | BC6: 13.166107 | BD6: 15.564883 | BF6: 6.5168531 | BG6: 8.1669479 | BI6: 12.927643 | BJ6: 15.250015 | BL6: 6.3958586 | BM6: 7.9930699 | BO6: 12.693837 | BP6: 14.942332 | BR6: 6.2773426 | BS6: 7.8234319 | BU6: 12.464587 | BV6: 14.641645
A7: =A6+1 -> 2 | B7: Animal production | D7: 1.2320225 | E7: 1.5277567 | G7: 1.1854351 | H7: 1.3871162 | J7: 8.5388615 | K7: 10.588526 | M7: 16.672369 | N7: 19.508882 | P7: 8.3056027 | Q7: 10.309803 | S7: 16.206234 | T7: 18.999391 | V7: 8.0831599 | W7: 10.048136 | Y7: 15.761453 | Z7: 18.522804 | AB7: 7.9364555 | AC7: 9.8379601 | AE7: 15.48317 | AF7: 18.156015 | AH7: 7.7926354 | AI7: 9.6327991 | AK7: 15.210086 | AL7: 17.797369 | AN7: 7.6516349 | AO7: 9.4325142 | AQ7: 14.942093 | AR7: 17.446658 | AT7: 7.5133911 | AU7: 9.236971 | AW7: 14.679088 | AX7: 17.103679 | AZ7: 7.3778426 | BA7: 9.0460393 | BC7: 14.420967 | BD7: 16.768235 | BF7: 7.2449299 | BG7: 8.8595929 | BI7: 14.167631 | BJ7: 16.440136 | BL7: 7.1145949 | BM7: 8.6775097 | BO7: 13.918982 | BP7: 16.119196 | BR7: 6.9867808 | BS7: 8.4996714 | BU7: 13.674925 | BV7: 15.805236
A8: =A7+1 -> 3 | B8: Commercial fishing | D8: 1.1992215 | E8: 1.4899646 | G8: 1.1088648 | H8: 1.2682189 | J8: 10.6055 | K8: 13.176731 | M8: 24.760448 | N8: 28.318753 | P8: 11.540288 | Q8: 14.054486 | S8: 27.201616 | T8: 30.705532 | V8: 12.589994 | W8: 15.054987 | Y8: 29.928823 | Z8: 33.392839 | AB8: 12.354217 | AC8: 14.739587 | AE8: 29.395936 | AF8: 32.748925 | AH8: 12.123313 | AI8: 14.431733 | AK8: 28.87317 | AL8: 32.118825 | AN8: 11.897165 | AO8: 14.131215 | AQ8: 28.360309 | AR8: 31.502196 | AT8: 11.675661 | AU8: 13.83783 | AW8: 27.857144 | AX8: 30.898707 | AZ8: 11.458689 | BA8: 13.551383 | BC8: 27.363471 | BD8: 30.308035 | BF8: 11.246144 | BG8: 13.271682 | BI8: 26.879092 | BJ8: 29.729868 | BL8: 11.037922 | BM8: 12.998543 | BO8: 26.403811 | BP8: 29.163901 | BR8: 10.833922 | BS8: 12.731789 | BU8: 25.937439 | BV8: 28.609839
A9: =A8+1 -> 4 | B9: Forestry & logging | D9: 1.491963 | E9: 1.8163628 | G9: 1.4850204 | H9: 1.6628214 | J9: 13.194405 | K9: 16.063283 | M9: 33.159831 | N9: 37.130047 | P9: 15.531878 | Q9: 18.337121 | S9: 39.070105 | T9: 42.979636 | V9: 18.293974 | W9: 21.044316 | Y9: 46.052512 | Z9: 49.917525 | AB9: 17.988098 | AC9: 20.6496 | AE9: 45.284024 | AF9: 49.025157 | AH9: 17.687371 | AI9: 20.263015 | AK9: 44.528416 | AL9: 48.14979 | AN9: 17.391706 | AO9: 19.884371 | AQ9: 43.78547 | AR9: 47.291063 | AT9: 17.101017 | AU9: 19.513481 | AW9: 43.054971 | AX9: 46.448626 | AZ9: 16.815217 | BA9: 19.150162 | BC9: 42.336709 | BD9: 45.622137 | BF9: 16.534225 | BG9: 18.794239 | BI9: 41.630477 | BJ9: 44.811261 | BL9: 16.257957 | BM9: 18.445541 | BO9: 40.936073 | BP9: 44.015672 | BR9: 15.986333 | BS9: 18.103899 | BU9: 40.253295 | BV9: 43.235053
A10: =A9+1 -> 5 | B10: Support activities for agriculture | D10: 1.2574079 | E10: 1.5697205 | G10: 1.2058209 | H10: 1.418808 | J10: 8.7148022 | K10: 10.879368 | M10: 16.959082 | N10: 19.954605 | P10: 8.2736325 | Q10: 10.390185 | S10: 16.09775 | T10: 19.047487 | V10: 7.872688 | W10: 9.9478176 | Y10: 15.320704 | Z10: 18.236852 | AB10: 7.7237346 | AC10: 9.7318345 | AE10: 15.041787 | AF10: 17.864468 | AH10: 7.5779307 | AI10: 9.5212511 | AK10: 14.768401 | AL10: 17.500723 | AN10: 7.4351978 | AO10: 9.3159104 | AQ10: 14.500419 | AR10: 17.145385 | AT10: 7.2954596 | AU10: 9.1156607 | AW10: 14.237718 | AX10: 16.798227 | AZ10: 7.1586422 | BA10: 8.9203553 | BC10: 13.98018 | BD10: 16.459032 | BF10: 7.0246739 | BG10: 8.7298523 | BI10: 13.727687 | BJ10: 16.127585 | BL10: 6.8934851 | BM10: 8.5440145 | BO10: 13.480128 | BP10: 15.803682 | BR10: 6.7650082 | BS10: 8.3627091 | BU10: 13.23739 | BV10: 15.487123
A11: =A10+1 -> 6 | B11: Mining | D11: 2.2372322 | E11: 3.3106048 | G11: 1.7560701 | H11: 2.2985384 | J11: 3.7149184 | K11: 5.497251 | M11: 7.9846911 | N11: 10.451245 | P11: 3.4998588 | Q11: 5.2426565 | S11: 7.4684544 | T11: 9.8973076 | V11: 3.3268446 | W11: 5.0355343 | Y11: 7.0625841 | Z11: 9.4637795 | AB11: 3.2226497 | AC11: 4.8761461 | AE11: 6.8453526 | AF11: 9.1695856 | AH11: 3.1219651 | AI11: 4.7221212 | AK11: 6.6352352 | AL11: 8.885066 | AN11: 3.0246655 | AO11: 4.5732695 | AQ11: 6.4319877 | AR11: 8.6098884 | AT11: 2.9306304 | AU11: 4.4294084 | AW11: 6.2353744 | AX11: 8.3437321 | AZ11: 2.8397436 | BA11: 4.2903619 | BC11: 6.0451683 | BD11: 8.0862881 | BF11: 2.7518934 | BG11: 4.1559602 | BI11: 5.8611502 | BJ11: 7.8372582 | BL11: 2.6669721 | BM11: 4.0260402 | BO11: 5.6831088 | BP11: 7.5963547 | BR11: 2.5848761 | BS11: 3.9004444 | BU11: 5.5108403 | BV11: 7.3633004
A12: =A11+1 -> 7 | B12: Single family construction | D12: 1.5870662 | E12: 2.3432588 | G12: 1.6561498 | H12: 2.4575102 | J12: 4.9262514 | K12: 7.2734724 | M12: 6.7131707 | N12: 9.9614692 | P12: 4.7970504 | Q12: 7.0922066 | S12: 6.5748735 | T12: 9.773522 | V12: 4.6760056 | W12: 6.9262435 | Y12: 6.4517075 | Z12: 9.6139324 | AB12: 4.517231 | AC12: 6.694783 | AE12: 6.2350566 | AF12: 9.2959268 | AH12: 4.3639411 | AI12: 6.4712471 | AK12: 6.0258097 | AL12: 8.9886968 | AN12: 4.2159428 | AO12: 6.255358 | AQ12: 5.823709 | AR12: 8.6918686 | AT12: 4.0730503 | AU12: 6.0468477 | AW12: 5.6285062 | AX12: 8.405082 | AZ12: 3.9350841 | BA12: 5.8454581 | BC12: 5.4399615 | BD12: 8.1279893 | BF12: 3.8018714 | BG12: 5.6509401 | BI12: 5.257844 | BJ12: 7.8602552 | BL12: 3.6732455 | BM12: 5.4630536 | BO12: 5.0819304 | BP12: 7.6015562 | BR12: 3.5490455 | BS12: 5.2815672 | BU12: 4.9120059 | BV12: 7.3515805
A13: =A12+1 -> 8 | B13: Construction of other buildings | D13: 1.6353525 | E13: 2.4354998 | G13: 1.7389435 | H13: 2.586884 | J13: 5.076132 | K13: 7.5597882 | M13: 7.0487733 | N13: 10.485883 | P13: 4.9525491 | Q13: 7.3811142 | S13: 6.9195858 | T13: 10.30416 | V13: 4.8374223 | W13: 7.2184582 | Y13: 6.8068186 | Z13: 10.152852 | AB13: 4.6727516 | AC13: 6.9768765 | AE13: 6.5776972 | AF13: 9.8164843 | AH13: 4.5137748 | AI13: 6.7435707 | AK13: 6.3564083 | AL13: 9.4915171 | AN13: 4.3602918 | AO13: 6.5182506 | AQ13: 6.1426799 | AR13: 9.1775551 | AT13: 4.2121095 | AU13: 6.3006364 | AW13: 5.9362495 | AX13: 8.8742174 | AZ13: 4.0690416 | BA13: 6.0904585 | BC13: 5.7368638 | BD13: 8.5811366 | BF13: 3.9309087 | BG13: 5.8874568 | BI13: 5.5442785 | BJ13: 8.2979582 | BL13: 3.7975377 | BM13: 5.6913808 | BO13: 5.358258 | BP13: 8.0243403 | BR13: 3.6687618 | BS13: 5.5019885 | BU13: 5.178575 | BV13: 7.759953
A14: =A13+1 -> 9 | B14: Heavy and civil engineering construction | D14: 1.6392062 | E14: 2.4462326 | G14: 1.7597604 | H14: 2.6149908 | J14: 5.0880939 | K14: 7.5931028 | M14: 7.133154 | N14: 10.599814 | P14: 4.9353608 | Q14: 7.3848049 | S14: 6.9731835 | T14: 10.386856 | V14: 4.7935202 | W14: 7.1950265 | Y14: 6.8338105 | Z14: 10.208611 | AB14: 4.6304938 | AC14: 6.954428 | AE14: 6.6039464 | AF14: 9.8705784 | AH14: 4.4731019 | AI14: 6.7220679 | AK14: 6.3819363 | AL14: 9.5439985 | AN14: 4.3211461 | AO14: 6.4976575 | AQ14: 6.1675075 | AR14: 9.2284743 | AT14: 4.1744357 | AU14: 6.2809183 | AW14: 5.9603968 | AX14: 8.9236233 | AZ14: 4.0327864 | BA14: 6.0715819 | BC14: 5.7603505 | BD14: 8.6290764 | BF14: 3.8960206 | BG14: 5.8693897 | BI14: 5.5671239 | BJ14: 8.3444778 | BL14: 3.7639671 | BM14: 5.674092 | BO14: 5.3804806 | BP14: 8.069484 | BR14: 3.6364609 | BS14: 5.4854484 | BU14: 5.2001929 | BV14: 7.8037638
A15: =A14+1 -> 10 | B15: Maintenance & repairs | D15: 1.6102018 | E15: 2.3773815 | G15: 1.6958354 | H15: 2.508839 | J15: 4.9980641 | K15: 7.3793889 | M15: 6.8740353 | N15: 10.16953 | P15: 4.832533 | Q15: 7.1610365 | S15: 6.6942114 | T15: 9.9393344 | V15: 4.6780107 | W15: 6.9609433 | Y15: 6.5346992 | Z15: 9.7428694 | AB15: 4.5192455 | AC15: 6.728436 | AE15: 6.3154227 | AF15: 9.4207656 | AH15: 4.3659574 | AI15: 6.5038814 | AK15: 6.1036267 | AL15: 9.1095628 | AN15: 4.2179543 | AO15: 6.2870009 | AQ15: 5.8990515 | AR15: 8.8088839 | AT15: 4.0750506 | AU15: 6.0775262 | AW15: 5.7014469 | AX15: 8.5183649 | AZ15: 3.9370677 | BA15: 5.8751983 | BC15: 5.5105714 | BD15: 8.2376546 | BF15: 3.8038331 | BG15: 5.6797677 | BI15: 5.3261918 | BJ15: 7.9664146 | BL15: 3.6751808 | BM15: 5.4909938 | BO15: 5.1480836 | BP15: 7.7043181 | BR15: 3.5509503 | BS15: 5.3086445 | BU15: 4.9760298 | BV15: 7.45105
A16: =A15+1 -> 11 | B16: Food processing | D16: 1.4953643 | E16: 1.8699301 | G16: 1.6607991 | H16: 2.1298661 | J16: 8.5112293 | K16: 10.643161 | M16: 10.44618 | N16: 13.396542 | P16: 8.7597298 | Q16: 10.844372 | S16: 10.696974 | T16: 13.602239 | V16: 9.0371695 | W16: 11.081014 | Y16: 10.98688 | Z16: 13.859063 | AB16: 8.8469525 | AC16: 10.824777 | AE16: 10.75266 | AF16: 13.532784 | AH16: 8.6613831 | AI16: 10.575405 | AK16: 10.524218 | AL16: 13.215346 | AN16: 8.4803261 | AO16: 10.332684 | AQ16: 10.301386 | AR16: 12.906475 | AT16: 8.3036506 | AU16: 10.09641 | AW16: 10.084001 | AX16: 12.605907 | AZ16: 8.1312304 | BA16: 9.8663832 | BC16: 9.8719065 | BD16: 12.313386 | BF16: 7.9629434 | BG16: 9.6424138 | BI16: 9.6649503 | BJ16: 12.028666 | BL16: 7.7986716 | BM16: 9.424317 | BO16: 9.4629853 | BP16: 11.751509 | BR16: 7.6383012 | BS16: 9.2119145 | BU16: 9.2658696 | BV16: 11.481684
A17: =A16+1 -> 12 | B17: Beverage manufacturing | D17: 1.9405115 | E17: 2.574518 | G17: 2.2625668 | H17: 3.1103801 | J17: 5.2434312 | K17: 6.956572 | M17: 6.326976 | N17: 8.6977765 | P17: 5.0095769 | Q17: 6.6847177 | S17: 6.1036747 | T17: 8.4382376 | V17: 4.7999821 | W17: 6.4423388 | Y17: 5.9133873 | Z17: 8.2213661 | AB17: 4.6401272 | AC17: 6.2294335 | AE17: 5.7198991 | AF17: 7.9539033 | AH17: 4.4858467 | AI17: 6.0238833 | AK17: 5.5330693 | AL17: 7.6955596 | AN17: 4.3369392 | AO17: 5.825425 | AQ17: 5.3526593 | AR17: 7.4460119 | AT17: 4.1932106 | AU17: 5.6338047 | AW17: 5.1784397 | AX17: 7.2049491 | AZ17: 4.0544742 | BA17: 5.4487781 | BC17: 5.0101895 | BD17: 6.9720712 | BF17: 3.9205503 | BG17: 5.2701099 | BI17: 4.8476959 | BJ17: 6.7470895 | BL17: 3.7912656 | BM17: 5.0975735 | BO17: 4.6907537 | BP17: 6.5297256 | BR17: 3.6664536 | BS17: 4.9309504 | BU17: 4.5391655 | BV17: 6.3197114
A18: =A17+1 -> 13 | B18: Apparel and textile manufacturing | D18: 1.2675024 | E18: 1.6206411 | G18: 1.1761992 | H18: 1.3818592 | J18: 8.8083617 | K18: 11.262458 | M18: 19.423365 | N18: 22.819567 | P18: 8.6751718 | Q18: 11.074833 | S18: 19.173054 | T18: 22.517346 | V18: 8.5516891 | W18: 10.904386 | Y18: 18.943745 | Z18: 22.249955 | AB18: 8.2601096 | AC18: 10.536811 | AE18: 18.300086 | AF18: 21.500326 | AH18: 7.9786197 | AI18: 10.181877 | AK18: 17.678544 | AL18: 20.776339 | AN18: 7.7068657 | AO18: 9.8391409 | AQ18: 17.078351 | AR18: 20.077106 | AT18: 7.4445067 | AU18: 9.5081764 | AW18: 16.498768 | AX18: 19.401769 | AZ18: 7.1912137 | BA18: 9.1885721 | BC18: 15.939081 | BD18: 18.749502 | BF18: 6.9466696 | BG18: 8.8799313 | BI18: 15.398601 | BJ18: 18.119507 | BL18: 6.7105683 | BM18: 8.5818712 | BO18: 14.876663 | BP18: 17.511014 | BR18: 6.4826146 | BS18: 8.2940227 | BU18: 14.372626 | BV18: 16.923281
... A40: =A39+1 -> 35 | B40: Other finance and insurance | D40: 2.9559539 | E40: 4.7578319 | G40: 1.4409121 | H40: 1.6754485 | J40: 3.9744958 | K40: 6.3972524 | M40: 20.598661 | N40: 23.951493 | P40: 3.7182789 | Q40: 6.0872952 | S40: 18.586029 | T40: 21.887613 | V40: 3.4927828 | W40: 5.8154353 | Y40: 16.81273 | Z40: 20.076718 | AB40: 3.3772283 | AC40: 5.6248558 | AE40: 16.294424 | AF40: 19.453795 | AH40: 3.265634 | AI40: 5.4407549 | AK40: 15.792287 | AL40: 18.850523 | AN40: 3.1578587 | AO40: 5.2629039 | AQ40: 15.305808 | AR40: 18.266267 | AT40: 3.0537668 | AU40: 5.0910827 | AW40: 14.83449 | AX40: 17.700419 | AZ40: 2.9532274 | BA40: 4.9250788 | BC40: 14.377854 | BD40: 17.152385 | BF40: 2.8561147 | BG40: 4.7646879 | BI40: 13.935436 | BJ40: 16.621595 | BL40: 2.7623074 | BM40: 4.609713 | BO40: 13.506787 | BP40: 16.107496 | BR40: 2.6716887 | BS40: 4.4599643 | BU40: 13.091471 | BV40: 15.609553
A41: =A40+1 -> 36 | B41: Owner-occupied dwellings | D41: NA | E41: NA | G41: NA | H41: NA | J41: 1.5258642 | K41: 1.9752442 | M41: 2.0849375 | N41: 2.7068306 | P41: 1.461177 | Q41: 1.9005892 | S41: 2.0167242 | T41: 2.6291117 | V41: 1.4020124 | W41: 1.8328248 | Y41: 1.9565572 | Z41: 2.5619714 | AB41: 1.3539571 | AC41: 1.7708536 | AE41: 1.8908933 | AF41: 2.4769029 | AH41: 1.3075773 | AI41: 1.7110251 | AK41: 1.8274756 | AL41: 2.3947261 | AN41: 1.2628138 | AO41: 1.6532638 | AQ41: 1.7662258 | AR41: 2.3153406 | AT41: 1.2196093 | AU41: 1.5974966 | AW41: 1.7070686 | AX41: 2.2386495 | AZ41: 1.1779086 | BA41: 1.5436534 | BC41: 1.6499312 | BD41: 2.1645594 | BF41: 1.1376586 | BG41: 1.4916664 | BI41: 1.5947436 | BJ41: 2.0929803 | BL41: 1.098808 | BM41: 1.4414703 | BO41: 1.541438 | BP41: 2.0238253 | BR41: 1.0613074 | BS41: 1.393002 | BU41: 1.4899491 | BV41: 1.9570105
A42: =A41+1 -> 37 | B42: Real estate | D42: 2.0792016 | E42: 3.6544846 | G42: 1.3895974 | H42: 1.902338 | J42: 2.286202 | K42: 4.0183164 | M42: 6.4963553 | N42: 8.8934133 | P42: 2.3276703 | Q42: 4.0213639 | S42: 6.7619652 | T42: 9.1223842 | V42: 2.3769828 | W42: 4.0375292 | Y42: 7.051037 | Z42: 9.3845775 | AB42: 2.2985244 | AC42: 3.9054328 | AE42: 6.8287209 | AF42: 9.0874675 | AH42: 2.2227228 | AI42: 3.7777938 | AK42: 6.6135026 | AL42: 8.7999433 | AN42: 2.1494855 | AO42: 3.6544568 | AQ42: 6.4051519 | AR42: 8.5216892 | AT42: 2.0787229 | AU42: 3.5352722 | AW42: 6.2034462 | AX42: 8.2523999 | AZ42: 2.010349 | BA42: 3.4200954 | BC42: 6.00817 | BD42: 7.9917803 | BF42: 1.9442807 | BG42: 3.3087872 | BI42: 5.8191154 | BJ42: 7.7395456 | BL42: 1.8804379 | BM42: 3.2012136 | BO42: 5.636081 | BP42: 7.4954202 | BR42: 1.8187435 | BS42: 3.0972451 | BU42: 5.4588721 | BV42: 7.2591381
A43: =A42+1 -> 38 | B43: Rental & leasing and others | D43: 2.2723378 | E43: 3.8371316 | G43: 1.3691761 | H43: 1.8785026 | J43: 2.4985664 | K43: 4.2191473 | M43: 6.4008861 | N43: 8.7819829 | P43: 2.6436668 | Q43: 4.3260827 | S43: 7.1043604 | T43: 9.4490622 | V43: 2.8203698 | W43: 4.4698593 | Y43: 7.9283642 | Z43: 10.246366 | AB43: 2.7279754 | AC43: 4.3241839 | AE43: 7.6788177 | AF43: 9.922524 | AH43: 2.638679 | AI43: 4.1833953 | AK43: 7.4372159 | AL43: 9.6090978 | AN43: 2.5523742 | AO43: 4.0473244 | AQ43: 7.2033022 | AR43: 9.3057462 | AT43: 2.4689578 | AU43: 3.9158084 | AW43: 6.9768285 | AX43: 9.0121389 | AZ43: 2.3883307 | BA43: 3.78869 | BC43: 6.7575547 | BD43: 8.7279568 | BF43: 2.310397 | BG43: 3.6658178 | BI43: 6.5452488 | BJ43: 8.4528915 | BL43: 2.2350646 | BM43: 3.5470457 | BO43: 6.3396863 | BP43: 8.1866449 | BR43: 2.1622442 | BS43: 3.4322327 | BU43: 6.14065 | BV43: 7.9289288
A44: =A43+1 -> 39 | B44: Legal services | D44: 1.790648 | E44: 2.7896773 | G44: 1.5997144 | H44: 2.3258777 | J44: 5.4973728 | K44: 8.5644392 | M44: 9.3504676 | N44: 13.594954 | P44: 5.4275017 | Q44: 8.4265361 | S44: 9.2853681 | T44: 13.464978 | V44: 5.3672063 | W44: 8.3075469 | Y44: 9.2369211 | Z44: 13.368937 | AB44: 5.1782737 | AC44: 8.023637 | AE44: 8.9187064 | AF44: 12.918284 | AH44: 4.9961788 | AI44: 7.7497532 | AK44: 8.6116784 | AL44: 12.483223 | AN44: 4.8206665 | AO44: 7.4855291 | AQ44: 8.3154346 | AR44: 12.063201 | AT44: 4.6514911 | AU44: 7.2306125 | AW44: 8.0295873 | AX44: 11.657683 | AZ44: 4.4884168 | BA44: 6.984664 | BC44: 7.7537631 | BD44: 11.266155 | BF44: 4.3312166 | BG44: 6.7473574 | BI44: 7.4876024 | BJ44: 10.888121 | BL44: 4.1796725 | BM44: 6.5183787 | BO44: 7.2307589 | BP44: 10.523103 | BR44: 4.0335745 | BS44: 6.2974257 | BU44: 6.982899 | BV44: 10.170642
A45: =A44+1 -> 40 | B45: Architectural and engineering services | D45: 1.6313652 | E45: 2.5967032 | G45: 1.5636223 | H45: 2.2652964 | J45: 5.0083669 | K45: 7.9719996 | M45: 9.1395062 | N45: 13.240851 | P45: 4.9674185 | Q45: 7.8653134 | S45: 9.1061909 | T45: 13.144847 | V45: 4.9357548 | W45: 7.7769353 | Y45: 9.0911841 | Z45: 13.083852 | AB45: 4.7688654 | AC45: 7.5182716 | AE45: 8.7864917 | AF45: 12.651187 | AH45: 4.6076954 | AI45: 7.2684081 | AK45: 8.4921186 | AL45: 12.2331 | AN45: 4.452046 | AO45: 7.0270388 | AQ45: 8.2077119 | AR45: 11.829089 | AT45: 4.3017257 | AU45: 6.7938687 | AW45: 7.9329306 | AX45: 11.438672 | AZ45: 4.1565494 | BA45: 6.568613 | BC45: 7.6674455 | BD45: 11.061385 | BF45: 4.0163387 | BG45: 6.3509975 | BI45: 7.4109391 | BJ45: 10.696778 | BL45: 3.8809215 | BM45: 6.1407572 | BO45: 7.1631045 | BP45: 10.344418 | BR45: 3.7501318 | BS45: 5.9376368 | BU45: 6.9236455 | BV45: 10.003885
A46: =A45+1 -> 41 | B46: Computer systems design services | D46: 1.11691 | E46: 1.8237318 | G46: 1.0884084 | H46: 1.6021751 | J46: 3.4289657 | K46: 5.5989414 | M46: 6.3618402 | N46: 9.3648505 | P46: 3.2648765 | Q46: 5.3867189 | S46: 6.0614126 | T46: 9.018522 | V46: 3.1098587 | W46: 5.1901748 | Y46: 5.778241 | Z46: 8.7016773 | AB46: 3.0040822 | AC46: 5.017201 | AE46: 5.5823567 | AF46: 8.4120919 | AH46: 2.9019319 | AI46: 4.8501093 | AK46: 5.3931472 | AL46: 8.1322983 | AN46: 2.8032824 | AO46: 4.6886955 | AQ46: 5.2103837 | AR46: 7.8619604 | AT46: 2.7080127 | AU46: 4.5327631 | AW46: 5.0338452 | AX46: 7.6007539 | AZ46: 2.6160059 | BA46: 4.3821221 | BC46: 4.8633186 | BD46: 7.3483658 | BF46: 2.5271492 | BG46: 4.2365894 | BI46: 4.6985981 | BJ46: 7.1044938 | BL46: 2.441334 | BM46: 4.0959886 | BO46: 4.5394847 | BP46: 6.8688464 | BR46: 2.358455 | BS46: 3.9601491 | BU46: 4.3857866 | BV46: 6.641142
A47: =A46+1 -> 42 | B47: R&D in the physical, engineering, & life sciences | D47: 1.5194194 | E47: 2.405869 | G47: 1.4227225 | H47: 2.0670551 | J47: 4.6646882 | K47: 7.3861299 | M47: 8.3159349 | N47: 12.082114 | P47: 4.4806351 | Q47: 7.1417112 | S47: 8.0086997 | T47: 11.717313 | V47: 4.3104169 | W47: 6.9194133 | Y47: 7.7285133 | Z47: 11.394896 | AB47: 4.163606 | AC47: 6.6883281 | AE47: 7.4683681 | AF47: 11.017237 | AH47: 4.0218964 | AI47: 6.4651731 | AK47: 7.2171161 | AL47: 10.65238 | AN47: 3.885107 | AO47: 6.2496689 | AQ47: 6.9744484 | AR47: 10.299883 | AT47: 3.7530635 | AU47: 6.0415461 | AW47: 6.7400672 | AX47: 9.9593164 | AZ47: 3.6255977 | BA47: 5.8405451 | BC47: 6.5136852 | BD47: 9.6302689 | BF47: 3.5025476 | BG47: 5.6464157 | BI47: 6.2950251 | BJ47: 9.3123422 | BL47: 3.383757 | BM47: 5.4589167 | BO47: 6.0838194 | BP47: 9.0051525 | BR47: 3.2690756 | BS47: 5.2778155 | BU47: 5.8798101 | BV47: 8.7083294
A48: =A47+1 -> 43 | B48: Other professional services | D48: 1.8233282 | E48: 2.7982512 | G48: 1.6379957 | H48: 2.3466368 | J48: 5.5977024 | K48: 8.5907614 | M48: 9.574225 | N48: 13.716293 | P48: 5.1930972 | Q48: 8.1197658 | S48: 8.8696349 | T48: 12.948392 | V48: 4.8360136 | W48: 7.7054046 | Y48: 8.2546602 | Z48: 12.286971 | AB48: 4.6699068 | AC48: 7.4466123 | AE48: 7.9763883 | AF48: 11.879457 | AH48: 4.5096661 | AI48: 7.1967976 | AK48: 7.7077117 | AL48: 11.485837 | AN48: 4.3550783 | AO48: 6.9556386 | AQ48: 7.4482916 | AR48: 11.105626 | AT48: 4.2059379 | AU48: 6.7228258 | AW48: 7.1978016 | AX48: 10.738352 | AZ48: 4.0620473 | BA48: 6.4980608 | BC48: 6.955927 | BD48: 10.383566 | BF48: 3.9232164 | BG48: 6.2810564 | BI48: 6.7223646 | BJ48: 10.040829 | BL48: 3.7892621 | BM48: 6.071536 | BO48: 6.4968222 | BP48: 9.7097232 | BR48: 3.6600079 | BS48: 5.8692331 | BU48: 6.2790179 | BV48: 9.3898416
A49: =A48+1 -> 44 | B49: Management of companies and enterprises | D49: 1.2482259 | E49: 1.9448578 | G49: 1.3819076 | H49: 2.2586961 | J49: 5.8837495 | K49: 9.1674564 | M49: 7.1622669 | N49: 11.70656 | P49: 5.8247381 | Q49: 9.0356077 | S49: 7.1123009 | T49: 11.587135 | V49: 5.7712904 | W49: 8.9193203 | Y49: 7.0747565 | Z49: 11.498635 | AB49: 5.5573552 | AC49: 8.6036992 | AE49: 6.8159875 | AF49: 11.098073 | AH49: 5.3513925 | AI49: 8.299464 | AK49: 6.5667518 | AL49: 10.711761 | AN49: 5.1531038 | AO49: 8.0061976 | AQ49: 6.3266962 | AR49: 10.339184 | AT49: 4.9622019 | AU49: 7.723498 | AW49: 6.0954804 | AX49: 9.9798447 | AZ49: 4.7784103 | BA49: 7.4509785 | BC49: 5.8727768 | BD49: 9.6332644 | BF49: 4.601463 | BG49: 7.1882665 | BI49: 5.6582702 | BJ49: 9.2989822 | BL49: 4.4311039 | BM49: 6.9350033 | BO49: 5.4516569 | BP49: 8.9765541 | BR49: 4.2670866 | BS49: 6.6908436 | BU49: 5.2526446 | BV49: 8.6655521
A50: =A49+1 -> 45 | B50: Travel arrangement and reservation services | D50: 1.086611 | E50: 1.4080267 | G50: 1.0903099 | H50: 1.404985 | J50: 11.407224 | K50: 14.781441 | M50: 16.179406 | N50: 20.848956 | P50: 13.371704 | Q50: 16.671077 | S50: 18.971688 | T50: 23.569863 | V50: 15.716884 | W50: 18.951684 | Y50: 22.304513 | Z50: 26.850329 | AB50: 15.12714 | AC50: 18.257451 | AE50: 21.469064 | AF50: 25.869179 | AH50: 14.559586 | AI50: 17.588917 | AK50: 20.664999 | AL50: 24.924259 | AN50: 14.013387 | AO50: 16.945122 | AQ50: 19.891137 | AR50: 24.014223 | AT50: 13.487737 | AU50: 16.325144 | AW50: 19.14634 | AX50: 23.13777 | AZ50: 12.98186 | BA50: 15.728094 | BC50: 18.429514 | BD50: 22.293653 | BF50: 12.495012 | BG50: 15.153117 | BI50: 17.739606 | BJ50: 21.480669 | BL50: 12.026475 | BM50: 14.599391 | BO50: 17.075604 | BP50: 20.697659 | BR50: 11.575559 | BS50: 14.066123 | BU50: 16.436531 | BV50: 19.94351
A51: =A50+1 -> 46 | B51: Administrative and support services | D51: 1.0960076 | E51: 1.418434 | G51: 1.0979464 | H51: 1.4136109 | J51: 11.50587 | K51: 14.890697 | M51: 16.292726 | N51: 20.976958 | P51: 11.085866 | Q51: 14.395613 | S51: 15.711645 | T51: 20.324279 | V51: 10.685123 | W51: 13.930095 | Y51: 15.159632 | Z51: 19.719741 | AB51: 10.284849 | AC51: 13.425003 | AE51: 14.593279 | AF51: 19.007229 | AH51: 9.8996245 | AI51: 12.93848 | AK51: 14.048171 | AL51: 18.320824 | AN51: 9.5288831 | AO51: 12.469836 | AQ51: 13.523507 | AR51: 17.659558 | AT51: 9.1720783 | AU51: 12.018407 | AW51: 13.018519 | AX51: 17.022501 | AZ51: 8.8286846 | BA51: 11.583553 | BC51: 12.532466 | BD51: 16.408756 | BF51: 8.4981962 | BG51: 11.164659 | BI51: 12.064637 | BJ51: 15.817463 | BL51: 8.1801266 | BM51: 10.761132 | BO51: 11.614345 | BP51: 15.247789 | BR51: 7.8740076 | BS51: 10.372403 | BU51: 11.180931 | BV51: 14.698937
A52: =A51+1 -> 47 | B52: Waste management and remediation services | D52: 1.83068 | E52: 2.5246559 | G52: 1.9373683 | H52: 2.8174142 | J52: 6.1332679 | K52: 8.458273 | M52: 7.0832525 | N52: 10.300807 | P52: 6.0784801 | Q52: 8.3519132 | S52: 7.0207303 | T52: 10.189104 | V52: 6.0282364 | W52: 8.2571763 | Y52: 6.9653009 | Z52: 10.097596 | AB52: 5.8061131 | AC52: 7.963055 | AE52: 6.7100454 | AF52: 9.741945 | AH52: 5.5922535 | AI52: 7.6796144 | AK52: 6.4642425 | AL52: 9.3990865 | AN52: 5.3863476 | AO52: 7.4064601 | AQ52: 6.227539 | AR52: 9.0685521 | AT52: 5.1880969 | AU52: 7.1432128 | AW52: 5.9995947 | AX52: 8.7498909 | AZ52: 4.9972142 | BA52: 6.8895069 | BC52: 5.7800825 | BD52: 8.4426687 | BF52: 4.8134234 | BG52: 6.644991 | BI52: 5.5686875 | BJ52: 8.1464675 | BL52: 4.6364585 | BM52: 6.4093264 | BO52: 5.3651068 | BP52: 7.8608848 | BR52: 4.4660638 | BS52: 6.1821875 | BU52: 5.1690486 | BV52: 7.5855332
A53: =A52+1 -> 48 | B53: Colleges, universities, and professional schools | D53: 1.0524727 | E53: 1.4608326 | G53: 1.0624602 | H53: 1.5078203 | J53: 4.3731841 | K53: 6.0699816 | M53: 5.601874 | N53: 7.9500571 | P53: 3.9307872 | Q53: 5.5899472 | S53: 5.0443381 | T53: 7.3566294 | V53: 3.5349774 | W53: 5.1616662 | Y53: 4.5463809 | Z53: 6.8323417 | AB53: 3.4536102 | AC53: 5.0277545 | AE53: 4.4414325 | AF53: 6.6541244 | AH53: 3.3741507 | AI53: 4.8975145 | AK53: 4.3389517 | AL53: 6.480812 | AN53: 3.2965529 | AO53: 4.7708386 | AQ53: 4.2388787 | AR53: 6.3122608 | AT53: 3.2207717 | AU53: 4.6476226 | AW53: 4.1411552 | AX53: 6.1483318 | AZ53: 3.1467633 | BA53: 4.5277656 | BC53: 4.0457245 | BD53: 5.98889 | BF53: 3.074485 | BG53: 4.4111699 | BI53: 3.9525312 | BJ53: 5.8338048 | BL53: 3.0038951 | BM53: 4.2977409 | BO53: 3.8615214 | BP53: 5.6829497 | BR53: 2.9349532 | BS53: 4.1873868 | BU53: 3.7726424 | BV53: 5.536202
... A67: =A66+1 -> 62 | B67: State and local government | D67: 1.0096432 | E67: 1.3321277 | G67: 1.0130006 | H67: 1.4592842 | J67: 9.6410084 | K67: 12.72039 | M67: 9.6730685 | N67: 13.934597 | P67: 9.6253712 | Q67: 12.636447 | S67: 9.6570138 | T67: 13.853405 | V67: 9.6099901 | W67: 12.562137 | Y67: 9.6414069 | Z67: 13.790013 | AB67: 9.2672874 | AC67: 12.124075 | AE67: 9.2977126 | AF67: 13.313349 | AH67: 8.9368112 | AI67: 11.701442 | AK67: 8.9662771 | AL67: 12.853367 | AN67: 8.618125 | AO67: 11.293688 | AQ67: 8.6466629 | AR67: 12.409477 | AT67: 8.3108082 | AU67: 10.900285 | AW67: 8.3384482 | AX67: 11.981112 | AZ67: 8.014455 | BA67: 10.520725 | BC67: 8.0412262 | BD67: 11.567721 | BF67: 7.728674 | BG67: 10.154516 | BI67: 7.7546046 | BJ67: 11.168777 | BL67: 7.4530879 | BM67: 9.8011845 | BO67: 7.4782053 | BP67: 10.783769 | BR67: 7.187333 | BS67: 9.460274 | BU67: 7.2116633 | BV67: 10.412206
B69: PCE | J69: 4.7654648 | K69: 6.3350308 | M69: 6.5948849 | N69: 8.7669935 | O69: 0 | P69: 4.6597598 | Q69: 6.1945106 | S69: 6.4940824 | T69: 8.6329904 | V69: 4.5685641 | W69: 6.0732783 | X69: 0 | Y69: 6.4201331 | Z69: 8.534685 | AB69: 4.4209928 | AC69: 5.8771026 | AD69: 0 | AE69: 5.6875124 | AF69: 8.2611338 | AH69: 4.2783754 | AI69: 5.8771026 | AK69: 6.015426 | AL69: 7.9966825 | AN69: 4.1405394 | AO69: 5.5042783 | AP69: 0 | AQ69: 5.8231048 | AR69: 7.7410179 | AT69: 4.0073185 | AU69: 5.3271794 | AV69: 0 | AW69: 5.6371661 | AX69: 7.4938379 | AZ69: 3.8785525 | BA69: 5.1560027 | BB69: 0 | BC69: 5.4573905 | BD69: 7.254851 | BF69: 3.7540868 | BG69: 4.9905427 | BI69: 5.2835668 | BJ69: 7.0237763 | BL69: 3.6337727 | BM69: 4.8306016 | BN69: 0 | BO69: 5.115491 | BP69: 6.8003426 | BR69: 3.5174664 | BS69: 4.6759884 | BU69: 4.9529665 | BV69: 6.5842885
B70: Visitor's expenditures | J70: 5.8389468 | K70: 7.7968911 | M70: 7.7277691 | N70: 10.437351 | O70: 0 | P70: 5.6481292 | Q70: 7.5626434 | S70: 7.5380439 | T70: 10.20621 | V70: 5.4839816 | W70: 7.3610271 | X70: 0 | Y70: 7.3906683 | Z70: 10.028452 | AB70: 5.2934562 | AC70: 7.1098703 | AD70: 0 | AE70: 6.8678721 | AF70: 9.6954625 | AH70: 5.1100539 | AI70: 7.1098703 | AK70: 6.9027635 | AL70: 9.3742682 | AN70: 4.9334909 | AO70: 6.6346777 | AP70: 0 | AQ70: 6.6719383 | AR70: 9.0644257 | AT70: 4.7634953 | AU70: 6.4099467 | AV70: 0 | AW70: 6.449417 | AX70: 8.7655095 | AZ70: 4.5998065 | BA70: 6.193353 | BB70: 0 | BC70: 6.2348811 | BD70: 8.4771107 | BF70: 4.442175 | BG70: 5.9845834 | BI70: 6.0280247 | BJ70: 8.198837 | BL70: 4.2903615 | BM70: 5.7833375 | BN70: 0 | BO70: 5.8285548 | BP70: 7.9303112 | BR70: 4.1441371 | BS70: 5.5893273 | BU70: 5.6361898 | BV70: 7.6711712
B71: State and local government consumption | J71: 2.7464018 | K71: 3.6943855 | M71: 3.4718575 | N71: 4.7837639 | O71: 0 | P71: 2.7384703 | Q71: 3.6654264 | S71: 3.5177154 | T71: 4.8095693 | V71: 2.7359969 | W71: 3.6448116 | X71: 0 | Y71: 3.5814119 | Z71: 4.8585553 | AB71: 2.6401933 | AC71: 3.519652 | AD71: 0 | AE71: 3.4573398 | AF71: 4.6935485 | AH71: 2.5477898 | AI71: 3.519652 | AK71: 3.3376351 | AL71: 4.534271 | AN71: 2.4586644 | AO71: 3.282333 | AP71: 0 | AQ71: 3.2221422 | AR71: 4.38052 | AT71: 2.3726994 | AU71: 3.1698667 | AV71: 0 | AW71: 3.1107109 | AX71: 4.2321003 | AZ71: 2.2897816 | BA71: 3.0613337 | BB71: 0 | BC71: 3.0031964 | BD71: 4.0888235 | BF71: 2.2098016 | BG71: 2.9565941 | BI71: 2.8994593 | BJ71: 3.950508 | BL71: 2.1326543 | BM71: 2.8555129 | BN71: 0 | BO71: 2.7993652 | BP71: 3.8169789 | BR71: 2.058238 | BS71: 2.7579601 | BU71: 2.7027843 | BV71: 3.6880674
B72: Federal defense consumption | J72: 7.4363059 | K72: 10.379075 | M72: 7.6231163 | N72: 11.695589 | O72: 0 | P72: 7.2919285 | Q72: 10.169423 | S72: 7.4731749 | T72: 11.4834 | V72: 7.1510138 | W72: 9.9721931 | X72: 0 | Y72: 7.3274833 | Z72: 11.292043 | AB72: 6.8962868 | AC72: 9.6263379 | AD72: 0 | AE72: 9.292625 | AF72: 10.904303 | AH72: 6.650643 | AI72: 9.6263379 | AK72: 6.8154307 | AL72: 10.530076 | AN72: 6.4137583 | AO72: 8.9706239 | AP72: 0 | AQ72: 6.5730025 | AR72: 10.168886 | AT72: 6.1853202 | AU72: 8.6599192 | AV72: 0 | AW72: 6.33921 | AX72: 9.8202723 | AZ72: 5.9650271 | BA72: 8.3601105 | BB72: 0 | BC72: 6.1137451 | BD72: 9.4837925 | BF72: 5.7525884 | BG72: 8.0708118 | BI72: 5.896311 | BJ72: 9.1590188 | BL72: 5.5477239 | BM72: 7.7916509 | BN72: 0 | BO72: 5.6866212 | BP72: 8.8455388 | BR72: 5.3501632 | BS72: 7.5222687 | BU72: 5.4843996 | BV72: 8.5429551
B73: Federal nondefense consumption | J73: 6.5405318 | K73: 9.1470895 | M73: 7.1146217 | N73: 10.721814 | O73: 0 | P73: 6.2998861 | Q73: 8.8486265 | S73: 6.8612205 | T73: 10.413277 | V73: 6.0710222 | W73: 8.5698815 | X73: 0 | Y73: 6.6226131 | Z73: 10.134222 | AB73: 5.8569089 | AC73: 8.2750514 | AD73: 0 | AE73: 7.990547 | AF73: 9.789418 | AH73: 5.6504117 | AI73: 8.2750514 | AK73: 6.1663356 | AL73: 9.4565823 | AN73: 5.4512575 | AO73: 7.7160009 | AP73: 0 | AQ73: 5.9502387 | AR73: 9.1352919 | AT73: 5.2591831 | AU73: 7.4510588 | AV73: 0 | AW73: 5.7417886 | AX73: 8.8251391 | AZ73: 5.0739346 | BA73: 7.1953794 | BB73: 0 | BC73: 5.5407121 | BD73: 8.5257312 | BF73: 4.8952675 | BG73: 6.9486336 | BI73: 5.3467461 | BJ73: 8.2366891 | BL73: 4.7229462 | BM73: 6.7105042 | BN73: 0 | BO73: 5.1596369 | BP73: 7.9576478 | BR73: 4.5567432 | BS73: 6.4806855 | BU73: 4.9791398 | BV73: 7.688255
B75: Note: The jobs per $million of final demand multipliers change every year because of inflation and increases in productivity.
B76: The direct effect w&s job multipliers do not necessarily change because of this.
B78: The multipliers for PCE, Visitor's expenditures, and the S&L, federal defense, and federal nondefense government consumption
B79: are calculated using the purchase of those final demand sectors by industry and the multipliers of those industries to yield a total multiplier.

Sheet direct requirements
B2: 2022 Direct requirements table (A)
B3: Industry | C3: S1 | D3: S2 | E3: S3 | F3: S4 | G3: S5 | H3: S6 | I3: S7 | J3: S8 | K3: S9 | L3: S10 | M3: S11 | N3: S12 | O3: S13 | P3: S14 | Q3: S15 | R3: S16 | S3: S17 | T3: S18 | U3: S19 | V3: S20 | W3: S21 | X3: S22 | Y3: S23 | Z3: S24 | AA3: S25 | AB3: S26 | AC3: S27 | AD3: S28 | AE3: S29 | AF3: S30 | AG3: S31 | AH3: S32 | AI3: S33 | AJ3: S34 | AK3: S35 | AL3: S36 | AM3: S37 | AN3: S38 | AO3: S39 | AP3: S40 | AQ3: S41 | AR3: S42 | AS3: S43 | AT3: S44 | AU3: S45 | AV3: S46 | AW3: S47 | AX3: S48 | AY3: S49 | AZ3: S50 | BA3: S51 | BB3: S52 | BC3: S53 | BD3: S54 | BE3: S55 | BF3: S56 | BG3: S57 | BH3: S58 | BI3: S59 | BJ3: S60 | BK3: S61 | BL3: S62 | BM3: PCE
A4: S1 | B4: Crop production | C4: 0.017468712 | D4: 0.05271755 | E4: 0 | F4: 0 | G4: 0.009488232 | H4: 0 | I4: 0.0012456559 | J4: 0.00054760345 | K4: 0.00040648373 | L4: 0.0011376535 | M4: 0.054534158 | N4: 0 | O4: 0.0049141839 | P4: 1.0563646e-07 | Q4: 0.0014038429 | R4: 0 | S4: 0 | T4: 0 | U4: 0 | V4: 0 | W4: 0 | X4: 0 | Y4: 0 | Z4: 0 | AA4: 0 | AB4: 0 | AC4: 0 | AD4: 0 | AE4: 0 | AF4: 0 | AG4: 3.0448959e-05 | AH4: 1.3117902e-05 | AI4: 0 | AJ4: 0 | AK4: 0 | AL4: 0.00020610169 | AM4: 6.3271664e-05 | AN4: 0 | AO4: 0 | AP4: 2.7060386e-05 | AQ4: 0 | AR4: 0 | AS4: 1.1626457e-05 | AT4: 0 | AU4: 0 | AV4: 0.00013147773 | AW4: 0 | AX4: 0 | AY4: 6.3888238e-07 | AZ4: 0 | BA4: 7.1643612e-05 | BB4: 0.00013190066 | BC4: 5.1542321e-05 | BD4: 2.1018588e-05 | BE4: 0 | BF4: 0.0011435813 | BG4: 2.740797e-07 | BH4: 0 | BI4: 1.6046251e-05 | BJ4: 0 | BK4: 0 | BL4: 0 | BM4: 0
A5: S2 | B5: Animal production | C5: 0 | D5: 0.030804807 | E5: 0 | F5: 0.0009806783 | G5: 0.036339545 | H5: 0 | I5: 0 | J5: 0 | K5: 0 | L5: 0 | M5: 0.019808955 | N5: 0 | O5: 0 | P5: 0 | Q5: 6.0782713e-07 | R5: 0 | S5: 0 | T5: 0 | U5: 0 | V5: 0 | W5: 0 | X5: 0 | Y5: 0 | Z5: 0 | AA5: 0 | AB5: 0 | AC5: 0 | AD5: 0 | AE5: 0 | AF5: 0 | AG5: 8.2370573e-06 | AH5: 2.8134885e-06 | AI5: 0 | AJ5: 0 | AK5: 0 | AL5: 0 | AM5: 0 | AN5: 0 | AO5: 0 | AP5: 0 | AQ5: 0 | AR5: 0.0014095797 | AS5: 0 | AT5: 0 | AU5: 0 | AV5: 9.166882e-07 | AW5: 0 | AX5: 7.2349773e-06 | AY5: 0 | AZ5: 0 | BA5: 0.00060353803 | BB5: 4.7270598e-05 | BC5: 8.9582838e-07 | BD5: 0.00011225813 | BE5: 0 | BF5: 0.0014414069 | BG5: 0 | BH5: 0.0011846414 | BI5: 1.4509899e-07 | BJ5: 0 | BK5: 0 | BL5: 0 | BM5: 0
A6: S3 | B6: Commercial fishing | C6: 0 | D6: 0 | E6: 0.0060564587 | F6: 0 | G6: 0 | H6: 0 | I6: 0 | J6: 0 | K6: 0 | L6: 0 | M6: 0.00040429052 | N6: 0 | O6: 0 | P6: 0 | Q6: 0 | R6: 0 | S6: 0 | T6: 0 | U6: 0 | V6: 0 | W6: 0 | X6: 0 | Y6: 0 | Z6: 0 | AA6: 0 | AB6: 0 | AC6: 0 | AD6: 0 | AE6: 0 | AF6: 0 | AG6: 0 | AH6: 0 | AI6: 0 | AJ6: 0 | AK6: 0 | AL6: 0 | AM6: 0 | AN6: 0 | AO6: 0 | AP6: 0 | AQ6: 0 | AR6: 0 | AS6: 0 | AT6: 0 | AU6: 0 | AV6: 0 | AW6: 0 | AX6: 0 | AY6: 0 | AZ6: 0 | BA6: 0.00038324622 | BB6: 9.9402591e-05 | BC6: 0 | BD6: 1.596396e-06 | BE6: 0 | BF6: 0.0067134981 | BG6: 0 | BH6: 0 | BI6: 1.2976953e-05 | BJ6: 0 | BK6: 0 | BL6: 0 | BM6: 0
A7: S4 | B7: Forestry & logging | C7: 0.0020703155 | D7: 0 | E7: 0 | F7: 0.31805579 | G7: 0.015018676 | H7: 0.019428171 | I7: 0 | J7: 0 | K7: 0 | L7: 0 | M7: 0.00016494999 | N7: 0.0014349684 | O7: 0.0052377454 | P7: 6.6907191e-05 | Q7: 0.00033469823 | R7: 0 | S7: 5.0687457e-05 | T7: 0 | U7: 0 | V7: 0 | W7: 0 | X7: 0 | Y7: 0 | Z7: 0 | AA7: 0 | AB7: 0 | AC7: 0 | AD7: 0 | AE7: 0 | AF7: 0 | AG7: 0 | AH7: 0 | AI7: 0 | AJ7: 0 | AK7: 0 | AL7: 0 | AM7: 0 | AN7: 0 | AO7: 0 | AP7: 0 | AQ7: 0 | AR7: 0.00070624579 | AS7: 0 | AT7: 0 | AU7: 0 | AV7: 0.00016903465 | AW7: 0 | AX7: 2.7992309e-05 | AY7: 0 | AZ7: 0 | BA7: 0 | BB7: 0 | BC7: 0 | BD7: 8.642501e-06 | BE7: 0 | BF7: 0 | BG7: 3.0049621e-06 | BH7: 0 | BI7: 0 | BJ7: 0 | BK7: 0 | BL7: 0 | BM7: 0
A8: S5 | B8: Support activities for agriculture | C8: 0.059726892 | D8: 0.0036509719 | E8: 0 | F8: 0.0078657016 | G8: 0.013116925 | H8: 0 | I8: 0 | J8: 0 | K8: 0 | L8: 0 | M8: 0 | N8: 0 | O8: 0 | P8: 0 | Q8: 0.00061148356 | R8: 6.4933829e-06 | S8: 2.0729129e-06 | T8: 0 | U8: 0 | V8: 2.2630484e-05 | W8: 0 | X8: 0 | Y8: 1.0915976e-06 | Z8: 0 | AA8: 4.6107061e-07 | AB8: 1.7777458e-06 | AC8: 2.850239e-07 | AD8: 2.7055418e-07 | AE8: 8.2409864e-06 | AF8: 5.5724755e-06 | AG8: 0 | AH8: 0 | AI8: 2.3561291e-07 | AJ8: 0 | AK8: 0 | AL8: 0.0023183268 | AM8: 0.0004223524 | AN8: 0 | AO8: 5.4766296e-07 | AP8: 0 | AQ8: 2.289387e-07 | AR8: 0 | AS8: 0 | AT8: 1.062807e-07 | AU8: 0 | AV8: 0 | AW8: 0 | AX8: 0 | AY8: 0 | AZ8: 1.2652111e-07 | BA8: 0 | BB8: 0 | BC8: 0 | BD8: 0 | BE8: 1.5119425e-05 | BF8: 0 | BG8: 0 | BH8: 0 | BI8: 0 | BJ8: 0 | BK8: 2.3335724e-05 | BL8: 2.0545641e-05 | BM8: 0
A9: S6 | B9: Mining | C9: 0.00027883099 | D9: 0 | E9: 0 | F9: 1.9496928e-06 | G9: 3.3719178e-06 | H9: 0.0059468821 | I9: 0 | J9: 0 | K9: 0 | L9: 0 | M9: 0 | N9: 0 | O9: 0 | P9: 0 | Q9: 0 | R9: 0 | S9: 0 | T9: 0 | U9: 0 | V9: 0 | W9: 0 | X9: 0 | Y9: 0 | Z9: 0 | AA9: 0 | AB9: 0 | AC9: 0 | AD9: 0 | AE9: 0.00067238298 | AF9: 0.0052935256 | AG9: 0 | AH9: 0 | AI9: 0 | AJ9: 0 | AK9: 0 | AL9: 0 | AM9: 0 | AN9: 0 | AO9: 0 | AP9: 0 | AQ9: 0 | AR9: 0 | AS9: 0 | AT9: 0 | AU9: 0 | AV9: 0 | AW9: 0 | AX9: 0 | AY9: 0 | AZ9: 0 | BA9: 0 | BB9: 0 | BC9: 0 | BD9: 0 | BE9: 0 | BF9: 0 | BG9: 0 | BH9: 0 | BI9: 0 | BJ9: 0 | BK9: 0 | BL9: 0 | BM9: 0
A10: S7 | B10: Single family construction | C10: 0 | D10: 0 | E10: 0 | F10: 0 | G10: 0 | H10: 0 | I10: 0 | J10: 0 | K10: 0 | L10: 0 | M10: 0 | N10: 0 | O10: 0 | P10: 0 | Q10: 0 | R10: 0 | S10: 0 | T10: 0 | U10: 0 | V10: 0 | W10: 0 | X10: 0 | Y10: 0 | Z10: 0 | AA10: 0 | AB10: 0 | AC10: 0 | AD10: 0 | AE10: 0 | AF10: 0 | AG10: 0 | AH10: 0 | AI10: 0 | AJ10: 0 | AK10: 0 | AL10: 0 | AM10: 0 | AN10: 0 | AO10: 0 | AP10: 0 | AQ10: 0 | AR10: 0 | AS10: 0 | AT10: 0 | AU10: 0 | AV10: 0 | AW10: 0 | AX10: 0 | AY10: 0 | AZ10: 0 | BA10: 0 | BB10: 0 | BC10: 0 | BD10: 0 | BE10: 0 | BF10: 0 | BG10: 0 | BH10: 0 | BI10: 0 | BJ10: 0 | BK10: 0 | BL10: 0 | BM10: 0
A11: S8 | B11: Construction of other buildings | C11: 0 | D11: 0 | E11: 0 | F11: 0 | G11: 0 | H11: 0 | I11: 0 | J11: 0 | K11: 0 | L11: 0 | M11: 0 | N11: 0 | O11: 0 | P11: 0 | Q11: 0 | R11: 0 | S11: 0 | T11: 0 | U11: 0 | V11: 0 | W11: 0 | X11: 0 | Y11: 0 | Z11: 0 | AA11: 0 | AB11: 0 | AC11: 0 | AD11: 0 | AE11: 0 | AF11: 0 | AG11: 0 | AH11: 0 | AI11: 0 | AJ11: 0 | AK11: 0 | AL11: 0 | AM11: 0 | AN11: 0 | AO11: 0 | AP11: 0 | AQ11: 0 | AR11: 0 | AS11: 0 | AT11: 0 | AU11: 0 | AV11: 0 | AW11: 0 | AX11: 0 | AY11: 0 | AZ11: 0 | BA11: 0 | BB11: 0 | BC11: 0 | BD11: 0 | BE11: 0 | BF11: 0 | BG11: 0 | BH11: 0 | BI11: 0 | BJ11: 0 | BK11: 0 | BL11: 0 | BM11: 0
A12: S9 | B12: Heavy and civil engineering construction | C12: 0 | D12: 0 | E12: 0 | F12: 0 | G12: 0 | H12: 0 | I12: 0 | J12: 0 | K12: 0 | L12: 0 | M12: 0 | N12: 0 | O12: 0 | P12: 0 | Q12: 0 | R12: 0 | S12: 0 | T12: 0 | U12: 0 | V12: 0 | W12: 0 | X12: 0 | Y12: 0 | Z12: 0 | AA12: 0 | AB12: 0 | AC12: 0 | AD12: 0 | AE12: 0 | AF12: 0 | AG12: 0 | AH12: 0 | AI12: 0 | AJ12: 0 | AK12: 0 | AL12: 0 | AM12: 0 | AN12: 0 | AO12: 0 | AP12: 0 | AQ12: 0 | AR12: 0 | AS12: 0 | AT12: 0 | AU12: 0 | AV12: 0 | AW12: 0 | AX12: 0 | AY12: 0 | AZ12: 0 | BA12: 0 | BB12: 0 | BC12: 0 | BD12: 0 | BE12: 0 | BF12: 0 | BG12: 0 | BH12: 0 | BI12: 0 | BJ12: 0 | BK12: 0 | BL12: 0 | BM12: 0
A13: S10 | B13: Maintenance & repairs | C13: 0.0033674113 | D13: 0.0016321551 | E13: 0.12108636 | F13: 0.00012070703 | G13: 0.0017851966 | H13: 3.6387551e-05 | I13: 0.0011692538 | J13: 0.0019419743 | K13: 0.0025854323 | L13: 0.0014662377 | M13: 0.0076226937 | N13: 0.0014943469 | O13: 0.0024906382 | P13: 0.00049075064 | Q13: 0.0013806706 | R13: 0.02672149 | S13: 6.1052173e-05 | T13: 0.00040294671 | U13: 0 | V13: 0.0028050441 | W13: 0.0051734962 | X13: 0.013504991 | Y13: 0.0038316519 | Z13: 0.0038745985 | AA13: 0.0013467785 | AB13: 0.0051927616 | AC13: 0.0014727532 | AD13: 0.0013979864 | AE13: 0.04552619 | AF13: 0.032854217 | AG13: 0.0027822076 | AH13: 0.0040313823 | AI13: 0.0086939028 | AJ13: 0.00019221471 | AK13: 0.0041927629 | AL13: 0.080514451 | AM13: 0.015559417 | AN13: 0.001908588 | AO13: 0.0029156527 | AP13: 0.0048664235 | AQ13: 0.00032545174 | AR13: 0.012951676 | AS13: 0.0027938058 | AT13: 0.0094156936 | AU13: 0.0015686489 | AV13: 0.00071346112 | AW13: 0.0016976354 | AX13: 0.0004617915 | AY13: 0.034299957 | AZ13: 0.0004180214 | BA13: 0.0054297586 | BB13: 0.0055558088 | BC13: 0.0039822706 | BD13: 0.001383198 | BE13: 0.040254519 | BF13: 0.023885293 | BG13: 0.0009699798 | BH13: 0.01171101 | BI13: 0.0027434352 | BJ13: 0 | BK13: 0.010875979 | BL13: 0.0014829133 | BM13: 0
A14: S11 | B14: Food processing | C14: 0.00041044149 | D14: 0.025179043 | E14: 5.5846832e-05 | F14: 0.00067726358 | G14: 0.00080020163 | H14: 0 | I14: 0 | J14: 0 | K14: 0 | L14: 0 | M14: 0.026641916 | N14: 0.052196935 | O14: 0.0019596849 | P14: 6.3580218e-05 | Q14: 0.00014744354 | R14: 0 | S14: 7.5138652e-05 | T14: 0 | U14: 0 | V14: 0.0012094423 | W14: 0.0012478542 | X14: 0 | Y14: 6.5070425e-05 | Z14: 0.0013961696 | AA14: 0 | AB14: 0 | AC14: 0 | AD14: 0 | AE14: 0 | AF14: 0 | AG14: 0.00016682177 | AH14: 4.6840597e-05 | AI14: 0 | AJ14: 0 | AK14: 0 | AL14: 0 | AM14: 0 | AN14: 0 | AO14: 0 | AP14: 0 | AQ14: 0 | AR14: 0.00026143899 | AS14: 0.00047190281 | AT14: 0 | AU14: 0 | AV14: 1.2020172e-06 | AW14: 0 | AX14: 1.0056432e-05 | AY14: 5.512801e-06 | AZ14: 8.1894988e-07 | BA14: 0.0024112817 | BB14: 0.0081351236 | BC14: 0.0031746033 | BD14: 5.1520666e-05 | BE14: 0.0004357394 | BF14: 0.034465513 | BG14: 0 | BH14: 0.00035706731 | BI14: 0.00025921314 | BJ14: 0 | BK14: 0.00045934195 | BL14: 8.2169279e-06 | BM14: 0
A15: S12 | B15: Beverage manufacturing | C15: 0 | D15: 7.2885816e-05 | E15: 0.0056824966 | F15: 0 | G15: 0 | H15: 0 | I15: 0 | J15: 0 | K15: 0 | L15: 0 | M15: 0.0055540768 | N15: 0.02591514 | O15: 0.00028324523 | P15: 9.189637e-06 | Q15: 1.7048732e-05 | R15: 0 | S15: 8.6881984e-06 | T15: 0 | U15: 0 | V15: 0.00013984646 | W15: 0.00014526117 | X15: 0 | Y15: 7.5240205e-06 | Z15: 0.00016143753 | AA15: 0 | AB15: 0 | AC15: 0 | AD15: 0 | AE15: 0 | AF15: 0 | AG15: 1.9289415e-05 | AH15: 5.4161259e-06 | AI15: 0 | AJ15: 0 | AK15: 0 | AL15: 0 | AM15: 0 | AN15: 0 | AO15: 0 | AP15: 0 | AQ15: 0 | AR15: 0 | AS15: 2.6232366e-05 | AT15: 0 | AU15: 0 | AV15: 0 | AW15: 0 | AX15: 3.6146904e-06 | AY15: 1.3507077e-05 | AZ15: 9.4694259e-08 | BA15: 0.00013810142 | BB15: 9.8654411e-05 | BC15: 0.00036707583 | BD15: 5.9572771e-06 | BE15: 5.0384061e-05 | BF15: 0.01108887 | BG15: 0 | BH15: 0 | BI15: 0.00026970213 | BJ15: 0 | BK15: 0.00020320593 | BL15: 2.3717816e-05 | BM15: 0
... A65: S62 | B65: State and local government | C65: 0.010805424 | D65: 0.016919906 | E65: 0.0011714924 | F65: 0 | G65: 0 | H65: 0.00016841235 | I65: 0 | J65: 0 | K65: 0 | L65: 0 | M65: 0.0014727772 | N65: 0.015510643 | O65: 0.0023010857 | P65: 0.0043404015 | Q65: 0.0050346357 | R65: 0.10217967 | S65: 0.029089377 | T65: 0.0032075077 | U65: 0.020479806 | V65: 0.0020111873 | W65: 0.10791661 | X65: 0.0054421016 | Y65: 0.003199175 | Z65: 0.0015345231 | AA65: 0.0013287595 | AB65: 0.002540476 | AC65: 0.00029034111 | AD65: 0.0002756355 | AE65: 0.0010747192 | AF65: 0.00012383963 | AG65: 0.0014196641 | AH65: 0.012080802 | AI65: 0.0025729975 | AJ65: 0.0014869155 | AK65: 0.0010934339 | AL65: 0 | AM65: 0.0099840125 | AN65: 0.050929074 | AO65: 0.0019366495 | AP65: 0 | AQ65: 0.00010543705 | AR65: 0.002217715 | AS65: 0.0026661228 | AT65: 0.0039352051 | AU65: 0.0018555627 | AV65: 0.002347114 | AW65: 0.098032457 | AX65: 0.00038668918 | AY65: 0.0012645126 | AZ65: 0.00018315943 | BA65: 0.013460131 | BB65: 0 | BC65: 0.001235562 | BD65: 0.0025059839 | BE65: 0.014824343 | BF65: 0.0058263177 | BG65: 0 | BH65: 0.0017933052 | BI65: 0 | BJ65: 0 | BK65: 0.0031024444 | BL65: 0.00055284499 | BM65: 0
B66: Earnings | C66: 0.30769255 | D66: 0.30769255 | E66: 0.3752401 | F66: 0.3752401 | G66: 0.30769255 | H66: 0.20418842 | I66: 0.32998528 | J66: 0.32998528 | K66: 0.32998528 | L66: 0.32998528 | M66: 0.22877599 | N66: 0.16226294 | O66: 0.35429438 | P66: 0.017891721 | Q66: 0.38965769 | R66: 0.17615165 | S66: 0.31292256 | T66: 0.46937431 | U66: 0.52789746 | V66: 0.29988711 | W66: 0.3635708 | X66: 0.3635708 | Y66: 0.17650513 | Z66: 0.21416742 | AA66: 0.17650513 | AB66: 0.085494943 | AC66: 0.17650513 | AD66: 0.19902163 | AE66: 0.10395696 | AF66: 0.10395696 | AG66: 0.27379109 | AH66: 0.26052229 | AI66: 0.15014072 | AJ66: 0.24799729 | AK66: 0.22670201 | AL66: 0 | AM66: 0.24289697 | AN66: 0.24289697 | AO66: 0.40191529 | AP66: 0.40191529 | AQ66: 0.40191529 | AR66: 0.40191529 | AS66: 0.40191529 | AT66: 0.53068867 | AU66: 0.59487622 | AV66: 0.59487622 | AW66: 0.26542777 | AX66: 0.31926114 | AY66: 0.4215471 | AZ66: 0.41599839 | BA66: 0.27168953 | BB66: 0.55452793 | BC66: 0.3511268 | BD66: 0.57850244 | BE66: 0.22631371 | BF66: 0.34752863 | BG66: 0.39080785 | BH66: 0.5071785 | BI66: 0.15186001 | BJ66: 0.60564844 | BK66: 0.5450836 | BL66: 0.60105476 | BM66: 0
B67: State tax/Output ratio (for multiplier calculation) | C67: 0.026821864 | D67: 0.02289008 | E67: 0.030768274 | F67: 0.030586531 | G67: 0.045728452 | H67: 0.026367732 | I67: 0.063710782 | J67: 0.063710782 | K67: 0.063812926 | L67: 0.063812926 | M67: 0.027868779 | N67: 0.022793097 | O67: 0.039621403 | P67: 0.0083858792 | Q67: 0.041029293 | R67: 0.025306856 | S67: 0.045627907 | T67: 0.064942352 | U67: 0.062003025 | V67: 0.048643051 | W67: 0.058071726 | X67: 0.056271923 | Y67: 0.042412349 | Z67: 0.046001159 | AA67: 0.03882952 | AB67: 0.030400747 | AC67: 0.04361239 | AD67: 0.042380786 | AE67: 0.060424135 | AF67: 0.029001373 | AG67: 0.051549852 | AH67: 0.18482459 | AI67: 0.02453971 | AJ67: 0.1172906 | AK67: 0.035952664 | AL67: 0.0059422807 | AM67: 0.088778692 | AN67: 0.078080461 | AO67: 0.059675366 | AP67: 0.059796103 | AQ67: 0.060336013 | AR67: 0.054650712 | AS67: 0.057973335 | AT67: 0.073720302 | AU67: 0.066828059 | AV67: 0.07210885 | AW67: 0.04858306 | AX67: 0.058862584 | AY67: 0.062152502 | AZ67: 0.059679136 | BA67: 0.051321601 | BB67: 0.047552388 | BC67: 0.054469371 | BD67: 0.064165031 | BE67: 0.10669617 | BF67: 0.051054084 | BG67: 0.045680612 | BH67: 0.061113159 | BI67: 0.018240429 | BJ67: 0.066269256 | BK67: 0.060628746 | BL67: 0.057776607
BM68: 0.8061

Sheet ttl req. - type 1
B1: 2022 Type 1 total requirements table
B2: Industry | C2: S1 | D2: S2 | E2: S3 | F2: S4 | G2: S5 | H2: S6 | I2: S7 | J2: S8 | K2: S9 | L2: S10 | M2: S11 | N2: S12 | O2: S13 | P2: S14 | Q2: S15 | R2: S16 | S2: S17 | T2: S18 | U2: S19 | V2: S20 | W2: S21 | X2: S22 | Y2: S23 | Z2: S24 | AA2: S25 | AB2: S26 | AC2: S27 | AD2: S28 | AE2: S29 | AF2: S30 | AG2: S31 | AH2: S32 | AI2: S33 | AJ2: S34 | AK2: S35 | AL2: S36 | AM2: S37 | AN2: S38 | AO2: S39 | AP2: S40 | AQ2: S41 | AR2: S42 | AS2: S43 | AT2: S44 | AU2: S45 | AV2: S46 | AW2: S47 | AX2: S48 | AY2: S49 | AZ2: S50 | BA2: S51 | BB2: S52 | BC2: S53 | BD2: S54 | BE2: S55 | BF2: S56 | BG2: S57 | BH2: S58 | BI2: S59 | BJ2: S60 | BK2: S61 | BL2: S62 | BM2: PCE
A3: S1 | B3: Crop production | C3: 1.0185688 | D3: 0.056986962 | E3: 0.00029893352 | F3: 0.00028142484 | G3: 0.0119804 | H3: 9.1497223e-05 | I3: 0.0013885232 | J3: 0.00067279466 | K3: 0.00055005882 | L3: 0.0012619442 | M3: 0.05843926 | N3: 0.0032544388 | O3: 0.0053086733 | P3: 2.5840209e-05 | Q3: 0.0015120578 | R3: 0.00015525979 | S3: 2.5152883e-05 | T3: 2.1732232e-05 | U3: 9.5971343e-05 | V3: 0.00022363623 | W3: 0.00029676602 | X3: 0.00021603581 | Y3: 0.00022021775 | Z3: 0.00017267427 | AA3: 6.909001e-05 | AB3: 0.00015910108 | AC3: 6.4609698e-05 | AD3: 6.1259965e-05 | AE3: 0.00015889704 | AF3: 0.0001126005 | AG3: 0.00013855945 | AH3: 8.599502e-05 | AI3: 0.00024944567 | AJ3: 4.4421557e-05 | AK3: 0.00013390521 | AL3: 0.00035493498 | AM3: 0.00014323478 | AN3: 8.7927467e-05 | AO3: 0.00013274849 | AP3: 0.0001207888 | AQ3: 2.0029466e-05 | AR3: 0.00018774559 | AS3: 0.00025142251 | AT3: 8.0718568e-05 | AU3: 5.7027238e-05 | AV3: 0.00019702677 | AW3: 8.182921e-05 | AX3: 2.6848655e-05 | AY3: 0.00016680824 | AZ3: 1.3674993e-05 | BA3: 0.00043512409 | BB3: 0.0008478035 | BC3: 0.00030569688 | BD3: 5.8139547e-05 | BE3: 0.00022228463 | BF3: 0.0034762426 | BG3: 2.5302294e-05 | BH3: 0.00017109484 | BI3: 6.2167264e-05 | BJ3: 0 | BK3: 6.0535254e-05 | BL3: 8.1000609e-06 | BM3: 0
A4: S2 | B4: Animal production | C4: 0.0023454538 | D4: 1.0326181 | E4: 8.0817283e-05 | F4: 0.0019480979 | G4: 0.038116359 | H4: 9.5566533e-05 | I4: 7.8635624e-05 | J4: 7.6857787e-05 | K4: 8.8855207e-05 | L4: 6.8888352e-05 | M4: 0.021284362 | N4: 0.0012255386 | O4: 0.00013398659 | P4: 1.6636692e-05 | Q4: 7.5835785e-05 | R4: 8.6197653e-05 | S4: 1.5942985e-05 | T4: 1.5409672e-05 | U4: 7.2740163e-05 | V4: 0.00012785443 | W4: 0.00017308096 | X4: 0.00013960601 | Y4: 0.00014997969 | Z4: 8.4807166e-05 | AA4: 4.8343221e-05 | AB4: 0.00011265749 | AC4: 5.3935263e-05 | AD4: 5.1236458e-05 | AE4: 8.8086682e-05 | AF4: 5.5607459e-05 | AG4: 7.4715265e-05 | AH4: 4.5779407e-05 | AI4: 0.0001818666 | AJ4: 3.9050504e-05 | AK4: 0.00011461113 | AL4: 0.00010367798 | AM4: 5.0850504e-05 | AN4: 5.996183e-05 | AO4: 0.00011122248 | AP4: 0.00011299013 | AQ4: 1.7007802e-05 | AR4: 0.0015145958 | AS4: 0.00015932852 | AT4: 0.00011849933 | AU4: 3.7498315e-05 | AV4: 4.4630142e-05 | AW4: 8.6979478e-05 | AX4: 2.4866605e-05 | AY4: 8.5022682e-05 | AZ4: 1.0535254e-05 | BA4: 0.00082497574 | BB4: 0.00037805252 | BC4: 0.00011514603 | BD4: 0.00013954497 | BE4: 0.00012963605 | BF4: 0.0023618938 | BG4: 1.6145006e-05 | BH4: 0.0012835618 | BI4: 3.5605387e-05 | BJ4: 0 | BK4: 2.7522874e-05 | BL4: 5.0334132e-06 | BM4: 0
A5: S3 | B5: Commercial fishing | C5: 3.7449379e-05 | D5: 4.5657256e-05 | E5: 1.0062964 | F5: 5.8704006e-06 | G5: 5.3439547e-05 | H5: 0.00013861598 | I5: 0.00020416727 | J5: 0.00019064558 | K5: 0.0002273656 | L5: 0.00017406759 | M5: 0.00076477231 | N5: 0.00024413614 | O5: 0.00017948699 | P5: 3.6053275e-05 | Q5: 0.00011468453 | R5: 0.00024034581 | S5: 3.161483e-05 | T5: 3.5257365e-05 | U5: 0.00017447114 | V5: 0.00024321222 | W5: 0.00041729255 | X5: 0.00034438722 | Y5: 0.00038395462 | Z5: 0.00012422041 | AA5: 0.00012213695 | AB5: 0.00028017788 | AC5: 0.00010880301 | AD5: 0.00010345817 | AE5: 0.0001843911 | AF5: 0.00012847221 | AG5: 0.00016215246 | AH5: 0.0001051469 | AI5: 0.00043415306 | AJ5: 7.2867064e-05 | AK5: 0.00020167128 | AL5: 3.2571909e-05 | AM5: 8.200749e-05 | AN5: 0.0001540377 | AO5: 0.00019201969 | AP5: 0.00011862566 | AQ5: 3.153203e-05 | AR5: 0.00011650801 | AS5: 0.00036873837 | AT5: 0.00011093214 | AU5: 9.4945297e-05 | AV5: 0.00010574271 | AW5: 0.00013207705 | AX5: 4.659901e-05 | AY5: 0.00023333227 | AZ5: 2.2457576e-05 | BA5: 0.00069495727 | BB5: 0.00054032111 | BC5: 0.00011160195 | BD5: 4.7879713e-05 | BE5: 0.00025500767 | BF5: 0.0070510095 | BG5: 3.7261476e-05 | BH5: 0.00010332511 | BI5: 4.9555864e-05 | BJ5: 0 | BK5: 3.4447356e-05 | BL5: 9.95118e-06 | BM5: 0
A6: S4 | B6: Forestry & logging | C6: 0.0044727274 | D6: 0.00034634336 | E6: 6.3193614e-05 | F6: 1.4666557 | G6: 0.022380372 | H6: 0.028679695 | I6: 1.7223527e-05 | J6: 1.6921728e-05 | K6: 2.122413e-05 | L6: 1.5131524e-05 | M6: 0.00053614835 | N6: 0.0022047303 | O6: 0.0078405531 | P6: 0.00010151487 | Q6: 0.00052004331 | R6: 9.1469671e-06 | S6: 7.8310116e-05 | T6: 2.1766858e-06 | U6: 1.0427685e-05 | V6: 1.925353e-05 | W6: 1.0283099e-05 | X6: 2.9581707e-05 | Y6: 2.3898395e-05 | Z6: 1.1053935e-05 | AA6: 4.6774126e-06 | AB6: 1.4152601e-05 | AC6: 1.5520056e-05 | AD6: 1.4462077e-05 | AE6: 6.0367124e-05 | AF6: 0.00018340808 | AG6: 1.3367221e-05 | AH6: 8.8914604e-06 | AI6: 3.6022755e-05 | AJ6: 1.0594059e-05 | AK6: 3.9225307e-05 | AL6: 5.9350131e-05 | AM6: 1.9221545e-05 | AN6: 8.8263242e-06 | AO6: 3.7702857e-05 | AP6: 5.5448644e-05 | AQ6: 4.9945785e-06 | AR6: 0.0010503835 | AS6: 2.1452221e-05 | AT6: 5.7804127e-05 | AU6: 7.6643601e-06 | AV6: 0.00025878014 | AW6: 2.0897436e-05 | AX6: 4.2611744e-05 | AY6: 1.0968552e-05 | AZ6: 3.1719153e-06 | BA6: 4.6901003e-05 | BB6: 2.1522838e-05 | BC6: 1.4247404e-05 | BD6: 1.8105747e-05 | BE6: 3.9413967e-05 | BF6: 7.7961695e-05 | BG6: 7.8671122e-06 | BH6: 1.5045039e-05 | BI6: 1.753105e-05 | BJ6: 0 | BK6: 5.698356e-06 | BL6: 1.1974968e-06 | BM6: 0
A7: S5 | B7: Support activities for agriculture | C7: 0.061709222 | D7: 0.0072818331 | E7: 2.3693619e-05 | F7: 0.011714736 | G7: 1.0143418 | H7: 0.0002459315 | I7: 0.0001038675 | J7: 5.843556e-05 | K7: 4.7029812e-05 | L7: 8.9921489e-05 | M7: 0.0036311472 | N7: 0.00022918805 | O7: 0.00039646257 | P7: 5.0152948e-06 | Q7: 0.00071939434 | R7: 2.3477059e-05 | S7: 8.2231497e-06 | T7: 4.145757e-06 | U7: 1.3162006e-05 | V7: 5.91769e-05 | W7: 2.9863345e-05 | X7: 6.9920092e-05 | Y7: 3.3302348e-05 | Z7: 2.6073951e-05 | AA7: 1.0215244e-05 | AB7: 2.6877724e-05 | AC7: 1.0354012e-05 | AD7: 9.8140735e-06 | AE7: 2.7345776e-05 | AF7: 2.0131322e-05 | AG7: 2.0980357e-05 | AH7: 3.4377602e-05 | AI7: 4.0223407e-05 | AJ7: 1.7772903e-05 | AK7: 5.3713964e-05 | AL7: 0.0023810749 | AM7: 0.00047127605 | AN7: 1.4753288e-05 | AO7: 5.2361255e-05 | AP7: 6.0323765e-05 | AQ7: 5.9625889e-06 | AR7: 5.1235971e-05 | AS7: 4.6417876e-05 | AT7: 2.1996307e-05 | AU7: 1.2284285e-05 | AV7: 2.2396637e-05 | AW7: 1.3962785e-05 | AX7: 7.6931222e-06 | AY7: 3.2864818e-05 | AZ7: 3.455473e-06 | BA7: 6.5220178e-05 | BB7: 7.3077764e-05 | BC7: 3.003715e-05 | BD7: 7.234282e-06 | BE7: 4.902162e-05 | BF7: 0.00024306698 | BG7: 9.0721864e-06 | BH7: 3.832739e-05 | BI7: 1.4909634e-05 | BJ7: 0 | BK7: 2.9710105e-05 | BL7: 2.1823382e-05 | BM7: 0
A8: S6 | B8: Mining | C8: 0.00031673147 | D8: 3.7487845e-05 | E8: 5.6656321e-06 | F8: 6.5444773e-06 | G8: 1.571768e-05 | H8: 1.0060518 | I8: 6.0405746e-05 | J8: 1.9120179e-05 | K8: 1.9575227e-05 | L8: 1.6637174e-05 | M8: 5.4392096e-05 | N8: 2.3863787e-05 | O8: 3.533062e-05 | P8: 1.5893026e-05 | Q8: 1.3810941e-05 | R8: 6.9450003e-06 | S8: 8.1729424e-06 | T8: 2.209383e-06 | U8: 1.1742235e-05 | V8: 1.4981745e-05 | W8: 7.5395208e-06 | X8: 5.7508858e-05 | Y8: 2.0263265e-05 | Z8: 1.6221153e-05 | AA8: 5.1257033e-06 | AB8: 1.7103106e-05 | AC8: 6.5404936e-06 | AD8: 6.2111193e-06 | AE8: 0.00087898653 | AF8: 0.0058289721 | AG8: 1.4317227e-05 | AH8: 2.1969294e-05 | AI8: 2.305724e-05 | AJ8: 3.4193066e-06 | AK8: 2.1711743e-05 | AL8: 3.9868585e-06 | AM8: 2.2705526e-05 | AN8: 8.7336166e-06 | AO8: 2.1904631e-05 | AP8: 2.5571751e-05 | AQ8: 2.6532103e-06 | AR8: 3.8087617e-05 | AS8: 1.8649994e-05 | AT8: 2.280682e-05 | AU8: 2.0309504e-05 | AV8: 6.023521e-06 | AW8: 3.6546837e-05 | AX8: 1.5342138e-06 | AY8: 1.5056749e-05 | AZ8: 1.7798519e-06 | BA8: 4.3490346e-05 | BB8: 4.8649277e-05 | BC8: 9.0146753e-06 | BD8: 6.6732052e-06 | BE8: 7.4062942e-05 | BF8: 4.7958181e-05 | BG8: 6.9315428e-06 | BH8: 2.9792362e-05 | BI8: 2.5592738e-05 | BJ8: 0 | BK8: 5.9258853e-06 | BL8: 2.3908276e-06 | BM8: 0
A9: S7 | B9: Single family construction | C9: 0 | D9: 0 | E9: 0 | F9: 0 | G9: 0 | H9: 0 | I9: 1 | J9: 0 | K9: 0 | L9: 0 | M9: 0 | N9: 0 | O9: 0 | P9: 0 | Q9: 0 | R9: 0 | S9: 0 | T9: 0 | U9: 0 | V9: 0 | W9: 0 | X9: 0 | Y9: 0 | Z9: 0 | AA9: 0 | AB9: 0 | AC9: 0 | AD9: 0 | AE9: 0 | AF9: 0 | AG9: 0 | AH9: 0 | AI9: 0 | AJ9: 0 | AK9: 0 | AL9: 0 | AM9: 0 | AN9: 0 | AO9: 0 | AP9: 0 | AQ9: 0 | AR9: 0 | AS9: 0 | AT9: 0 | AU9: 0 | AV9: 0 | AW9: 0 | AX9: 0 | AY9: 0 | AZ9: 0 | BA9: 0 | BB9: 0 | BC9: 0 | BD9: 0 | BE9: 0 | BF9: 0 | BG9: 0 | BH9: 0 | BI9: 0 | BJ9: 0 | BK9: 0 | BL9: 0 | BM9: 0
A10: S8 | B10: Construction of other buildings | C10: 0 | D10: 0 | E10: 0 | F10: 0 | G10: 0 | H10: 0 | I10: 0 | J10: 1 | K10: 0 | L10: 0 | M10: 0 | N10: 0 | O10: 0 | P10: 0 | Q10: 0 | R10: 0 | S10: 0 | T10: 0 | U10: 0 | V10: 0 | W10: 0 | X10: 0 | Y10: 0 | Z10: 0 | AA10: 0 | AB10: 0 | AC10: 0 | AD10: 0 | AE10: 0 | AF10: 0 | AG10: 0 | AH10: 0 | AI10: 0 | AJ10: 0 | AK10: 0 | AL10: 0 | AM10: 0 | AN10: 0 | AO10: 0 | AP10: 0 | AQ10: 0 | AR10: 0 | AS10: 0 | AT10: 0 | AU10: 0 | AV10: 0 | AW10: 0 | AX10: 0 | AY10: 0 | AZ10: 0 | BA10: 0 | BB10: 0 | BC10: 0 | BD10: 0 | BE10: 0 | BF10: 0 | BG10: 0 | BH10: 0 | BI10: 0 | BJ10: 0 | BK10: 0 | BL10: 0 | BM10: 0
A11: S9 | B11: Heavy and civil engineering construction | C11: 0 | D11: 0 | E11: 0 | F11: 0 | G11: 0 | H11: 0 | I11: 0 | J11: 0 | K11: 1 | L11: 0 | M11: 0 | N11: 0 | O11: 0 | P11: 0 | Q11: 0 | R11: 0 | S11: 0 | T11: 0 | U11: 0 | V11: 0 | W11: 0 | X11: 0 | Y11: 0 | Z11: 0 | AA11: 0 | AB11: 0 | AC11: 0 | AD11: 0 | AE11: 0 | AF11: 0 | AG11: 0 | AH11: 0 | AI11: 0 | AJ11: 0 | AK11: 0 | AL11: 0 | AM11: 0 | AN11: 0 | AO11: 0 | AP11: 0 | AQ11: 0 | AR11: 0 | AS11: 0 | AT11: 0 | AU11: 0 | AV11: 0 | AW11: 0 | AX11: 0 | AY11: 0 | AZ11: 0 | BA11: 0 | BB11: 0 | BC11: 0 | BD11: 0 | BE11: 0 | BF11: 0 | BG11: 0 | BH11: 0 | BI11: 0 | BJ11: 0 | BK11: 0 | BL11: 0 | BM11: 0
A12: S10 | B12: Maintenance & repairs | C12: 0.0072461512 | D12: 0.0051007553 | E12: 0.12454484 | F12: 0.00062638617 | G12: 0.0072731014 | H12: 0.0053256445 | I12: 0.0074641809 | J12: 0.0074046541 | K12: 0.0083134404 | L12: 1.0062214 | M12: 0.015281372 | N12: 0.0082931368 | O12: 0.0078488918 | P12: 0.0021613111 | Q12: 0.0039241375 | R12: 0.029475652 | S12: 0.0010705442 | T12: 0.0013229419 | U12: 0.0030259963 | V12: 0.0079954442 | W12: 0.012364791 | X12: 0.021585156 | Y12: 0.011816587 | Z12: 0.0085572689 | AA12: 0.0031521674 | AB12: 0.01047507 | AC12: 0.0049433583 | AD12: 0.0046895782 | AE12: 0.052703736 | AF12: 0.038836805 | AG12: 0.0070905294 | AH12: 0.0081845049 | AI12: 0.019184346 | AJ12: 0.0026133594 | AK12: 0.014116043 | AL12: 0.082280108 | AM12: 0.020337121 | AN12: 0.0054231693 | AO12: 0.015876903 | AP12: 0.012739919 | AQ12: 0.0018856179 | AR12: 0.020092033 | AS12: 0.012838811 | AT12: 0.013373191 | AU12: 0.0050105126 | AV12: 0.0037865575 | AW12: 0.0074493368 | AX12: 0.0013287367 | AY12: 0.038219838 | AZ12: 0.0010762012 | BA12: 0.014793948 | BB12: 0.0118302 | BC12: 0.0062644359 | BD12: 0.0022927836 | BE12: 0.048366831 | BF12: 0.031755821 | BG12: 0.0030348373 | BH12: 0.017105506 | BI12: 0.0052626753 | BJ12: 0 | BK12: 0.012284982 | BL12: 0.0017828788 | BM12: 0
A13: S11 | B13: Food processing | C13: 0.00076541781 | D13: 0.026952884 | E13: 0.0015157133 | F13: 0.0011134221 | G13: 0.0021432872 | H13: 0.00081534034 | I13: 0.0011411771 | J13: 0.0010691048 | K13: 0.0012647045 | L13: 0.00097735122 | M13: 1.030166 | N13: 0.056367097 | O13: 0.0030751347 | P13: 0.00026926598 | Q13: 0.00078948899 | R13: 0.0013093349 | S13: 0.00029048509 | T13: 0.00022327967 | U13: 0.00096955007 | V13: 0.0028488716 | W13: 0.0035811492 | X13: 0.0019404714 | Y13: 0.002221151 | Z13: 0.0023541091 | AA13: 0.00072039773 | AB13: 0.0015802417 | AC13: 0.00061858722 | AD13: 0.00058795288 | AE13: 0.0010434426 | AF13: 0.00072261614 | AG13: 0.0010852637 | AH13: 0.0006371112 | AI13: 0.0024138987 | AJ13: 0.00041591356 | AK13: 0.0011864227 | AL13: 0.00019843297 | AM13: 0.00047312985 | AN13: 0.00087533853 | AO13: 0.0011734315 | AP13: 0.00070676485 | AQ13: 0.00018553975 | AR13: 0.00099189062 | AS13: 0.0025928352 | AT13: 0.00064342893 | AU13: 0.00053729875 | AV13: 0.00060282645 | AW13: 0.00076820249 | AX13: 0.0002657612 | AY13: 0.0012760276 | AZ13: 0.00012696893 | BA13: 0.0042377891 | BB13: 0.010740585 | BC13: 0.0038936709 | BD13: 0.00031280974 | BE13: 0.0018842772 | BF13: 0.037663318 | BG13: 0.00021710888 | BH13: 0.0010051811 | BI13: 0.00049697385 | BJ13: 0 | BK13: 0.00067902801 | BL13: 6.5249232e-05 | BM13: 0
A14: S12 | B14: Beverage manufacturing | C14: 7.080554e-05 | D14: 0.00029207174 | E14: 0.0062281637 | F14: 1.609249e-05 | G14: 0.00010702394 | H14: 0.0002452254 | I14: 0.0003585379 | J14: 0.0003342072 | K14: 0.00039781902 | L14: 0.00030591033 | M14: 0.0064708858 | N14: 1.0273106 | O14: 0.00062144678 | P14: 7.3277326e-05 | Q14: 0.00021886878 | R14: 0.00041985606 | S14: 6.9601733e-05 | T14: 6.5119838e-05 | U14: 0.00030511199 | V14: 0.00060537059 | W14: 0.00088380419 | X14: 0.00060547261 | Y14: 0.00068307883 | Z14: 0.00041672477 | AA14: 0.00021834225 | AB14: 0.00049259165 | AC14: 0.00019232653 | AD14: 0.00018286243 | AE14: 0.00032610183 | AF14: 0.00022656566 | AG14: 0.00030626146 | AH14: 0.0001912983 | AI14: 0.00076103021 | AJ14: 0.00012914738 | AK14: 0.00036141939 | AL14: 6.7903159e-05 | AM14: 0.00014656433 | AN14: 0.00027285238 | AO14: 0.00034988879 | AP14: 0.00021138184 | AQ14: 5.6448925e-05 | AR14: 0.00021023823 | AS14: 0.00068096848 | AT14: 0.00019527045 | AU14: 0.00016718402 | AV14: 0.00018674783 | AW14: 0.00023828389 | AX14: 8.4861399e-05 | AY14: 0.00041825827 | AZ14: 3.9592933e-05 | BA14: 0.00070106135 | BB14: 0.00090543296 | BC14: 0.00058850177 | BD14: 8.752013e-05 | BE14: 0.0005032324 | BF14: 0.012122718 | BG14: 6.6785475e-05 | BH14: 0.00018755304 | BI14: 0.00034379283 | BJ14: 0 | BK14: 0.000272194 | BL14: 4.1854617e-05 | BM14: 0
... A64: S62 | B64: State and local government | C64: 0.016374961 | D64: 0.023407154 | E64: 0.006038375 | F64: 0.00095252438 | G64: 0.017059639 | H64: 0.0055049697 | I64: 0.0072713899 | J64: 0.0079736934 | K64: 0.0088686479 | L64: 0.0085857151 | M64: 0.00845396 | N64: 0.025882633 | O64: 0.0077589936 | P64: 0.0060603277 | Q64: 0.0078664682 | R64: 0.10431947 | S64: 0.029889074 | T64: 0.0050353114 | U64: 0.024891788 | V64: 0.0084386585 | W64: 0.12435872 | X64: 0.012855144 | Y64: 0.011111434 | Z64: 0.0061454605 | AA64: 0.003181719 | AB64: 0.0092792529 | AC64: 0.0041933888 | AD64: 0.0040102653 | AE64: 0.0052678711 | AF64: 0.0027682852 | AG64: 0.0056668172 | AH64: 0.015386907 | AI64: 0.010334048 | AJ64: 0.0040552721 | AK64: 0.010218331 | AL64: 0.0019727492 | AM64: 0.014410242 | AN64: 0.053821882 | AO64: 0.012069103 | AP64: 0.011256408 | AQ64: 0.0017099948 | AR64: 0.010846148 | AS64: 0.013443247 | AT64: 0.0082393736 | AU64: 0.0058529933 | AV64: 0.0065754151 | AW64: 0.11580959 | AX64: 0.0012661494 | AY64: 0.004678821 | AZ64: 0.000807955 | BA64: 0.020646545 | BB64: 0.0047845332 | BC64: 0.0031555308 | BD64: 0.0031382833 | BE64: 0.020889461 | BF64: 0.010626808 | BG64: 0.0021857523 | BH64: 0.0069705667 | BI64: 0.0019559383 | BJ64: 0 | BK64: 0.0061443791 | BL64: 1.0009263 | BM64: 0
B65: Earnings Multiplier (2022 Type I) | C65: 0.41330547 | D65: 0.40443071 | E65: 0.50734397 | F65: 0.56607437 | G65: 0.42710244 | H65: 0.3516819 | I65: 0.46314317 | J65: 0.49006396 | K65: 0.49427718 | L65: 0.46987238 | M65: 0.42066327 | N65: 0.33802929 | O65: 0.48423133 | P65: 0.047534659 | Q65: 0.45119462 | R65: 0.3273552 | S65: 0.36183525 | T65: 0.51784916 | U65: 0.64301135 | V65: 0.50549734 | W65: 0.55084512 | X65: 0.55885688 | Y65: 0.37396528 | Z65: 0.33890538 | AA65: 0.23139202 | AB65: 0.23358028 | AC65: 0.24134689 | AD65: 0.26069107 | AE65: 0.2320754 | AF65: 0.19565967 | AG65: 0.37158721 | AH65: 0.34746952 | AI65: 0.36202585 | AJ65: 0.35165504 | AK65: 0.47804751 | AL65: 0.088669664 | AM65: 0.34177309 | AN65: 0.33949734 | AO65: 0.60517985 | AP65: 0.58477076 | AQ65: 0.42816991 | AR65: 0.53698272 | AS65: 0.59057705 | AT65: 0.64792639 | AU65: 0.66578548 | AV65: 0.66787897 | AW65: 0.45875962 | AX65: 0.3348045 | AY65: 0.5218433 | AZ65: 0.47911575 | BA65: 0.48353595 | BB65: 0.66155646 | BC65: 0.40508788 | BD65: 0.60361332 | BE65: 0.41705614 | BF65: 0.50386815 | BG65: 0.42592077 | BH65: 0.61624447 | BI65: 0.20519186 | BJ65: 0.60564844 | BK65: 0.5755631 | BL65: 0.60760978 | BM65: 1
B67: Output Multipliers type 1 | C67: 1.3700296 | D67: 1.3255298 | E67: 1.4311491 | F67: 1.5222268 | G67: 1.432057 | H67: 1.4978496 | I67: 1.4745155 | J67: 1.5152142 | K67: 1.5218928 | L67: 1.4720762 | M67: 1.5958613 | N67: 1.5841104 | O67: 1.418927 | P67: 1.1010756 | Q67: 1.1899905 | R67: 1.359643 | S67: 1.1275683 | T67: 1.1399945 | U67: 1.3238189 | V67: 1.6421301 | W67: 1.5399394 | X67: 1.6430268 | Y67: 1.6375634 | Z67: 1.4518621 | AA67: 1.1822146 | AB67: 1.5166323 | AC67: 1.2124286 | AD67: 1.2034986 | AE67: 1.5638055 | AF67: 1.4042618 | AG67: 1.3089899 | AH67: 1.2825017 | AI67: 1.7149724 | AJ67: 1.363162 | AK67: 1.8639635 | AL67: 1.3208347 | AM67: 1.3348462 | AN67: 1.2754109 | AO67: 1.6827391 | AP67: 1.5996094 | AQ67: 1.0896405 | AR67: 1.4706667 | AS67: 1.6171634 | AT67: 1.3571027 | AU67: 1.2316069 | AV67: 1.2295735 | AW67: 1.5621899 | AX67: 1.0525687 | AY67: 1.3132425 | AZ67: 1.1607409 | BA67: 1.6391653 | BB67: 1.3623604 | BC67: 1.1670253 | BD67: 1.0701682 | BE67: 1.5887531 | BF67: 1.5189485 | BG67: 1.1186764 | BH67: 1.3578701 | BI67: 1.1720234 | BJ67: 1 | BK67: 1.102632 | BL67: 1.0213749

Sheet fd, income ML (2)
A1: 2022Detailed Output, Earnings, Employment, and Tax Multipliers for Hawaii
C3: Final demand multipliers | T3: Direct effect multipliers | X3: FD Shares
C4: Output multipliers | F4: Earnings multipliers | I4: State tax multipliers | K4: State income tax multipliers | M4: State GET multipliers | O4: State TAT multipliers | Q4: State Other Taxes multipliers | T4: Earnings/earnings multipliers | W4: Direct Earning Coefficient | X4: PCE | Y4: Visitor's expenditures | Z4: State and local government consumption | AA4: Federal military consumption | AB4: Federal civilian consumption | AD4: PCE | AU4: VE | BL4: S&LG | CC4: FDC | CT4: FNDC
B5: Industry | C5: type 1 | D5: type 2 | F5: type 1 | G5: type 2 | I5: type 1 | J5: type 2 | K5: type 1 | L5: type 2 | M5: type 1 | N5: type 2 | O5: type 1 | P5: type 2 | Q5: type 1 | R5: type 2 | T5: type 1 | U5: type 2 | AD5: Output multipliers | AG5: Earnings multipliers | AJ5: State tax multipliers | AL5: State income tax multipliers | AN5: State GET multipliers | AP5: State TAT multipliers | AR5: State Other Taxes multipliers | AU5: Output multipliers | AX5: Earnings multipliers | BA5: State tax multipliers | BC5: State income tax multipliers | BE5: State GET multipliers | BG5: State TAT multipliers | BI5: State Other Taxes multipliers | BL5: Output multipliers | BO5: Earnings multipliers | BR5: State tax multipliers | BT5: State income tax multipliers | BV5: State GET multipliers | BX5: State TAT multipliers | BZ5: State Other Taxes multipliers | CC5: Output multipliers | CF5: Earnings multipliers | CI5: State tax multipliers | CK5: State income tax multipliers | CM5: State GET multipliers | CO5: State TAT multipliers | CQ5: State Other Taxes multipliers | CT5: Output multipliers | CW5: Earnings multipliers | CZ5: State tax multipliers | DB5: State income tax multipliers | DD5: State GET multipliers | DF5: State TAT multipliers | DH5: State Other Taxes multipliers
A6: 1 | B6: Crop production | C6: 1.3700296 | D6: 1.878914 | F6: 0.41330547 | G6: 0.54943284 | I6: 0.049811614 | J6: 0.079954802 | K6: 0.023577817 | L6: 0.033345632 | M6: 0.011720837 | N6: 0.024385689 | O6: 0.0010067034 | P6: 0.0021199625 | Q6: 0.013506257 | R6: 0.020103518 | T6: =+F6/$W6 -> 1.3432417 | U6: =+G6/$W6 -> 1.7856553 | W6: 0.30769255 | X6: =+'I-O'!BO3/'I-O'!BO$75 -> 0.0013728 | Y6: =+'I-O'!BP3/'I-O'!BP$75 -> 0.0010847772 | Z6: =+'I-O'!BT3/'I-O'!BT$75 -> 0.00058759361 | AA6: =+'I-O'!BU3/'I-O'!BU$75 -> 0 | AB6: =+'I-O'!BW3/'I-O'!BW$75 -> 0 | AD6: type 1 | AE6: type 2 | AG6: type 1 | AH6: type 2 | AJ6: type 1 | AK6: type 2 | AL6: type 1 | AM6: type 2 | AN6: type 1 | AO6: type 2 | AP6: type 1 | AQ6: type 2 | AR6: type 1 | AS6: type 2 | AU6: type 1 | AV6: type 2 | AX6: type 1 | AY6: type 2 | BA6: type 1 | BB6: type 2 | BC6: type 1 | BD6: type 2 | BE6: type 1 | BF6: type 2 | BG6: type 1 | BH6: type 2 | BI6: type 1 | BJ6: type 2 | BL6: type 1 | BM6: type 2 | BO6: type 1 | BP6: type 2 | BR6: type 1 | BS6: type 2 | BT6: type 1 | BU6: type 2 | BV6: type 1 | BW6: type 2 | BX6: type 1 | BY6: type 2 | BZ6: type 1 | CA6: type 2 | CC6: type 1 | CD6: type 2 | CF6: type 1 | CG6: type 2 | CI6: type 1 | CJ6: type 2 | CK6: type 1 | CL6: type 2 | CM6: type 1 | CN6: type 2 | CO6: type 1 | CP6: type 2 | CQ6: type 1 | CR6: type 2 | CT6: type 1 | CU6: type 2 | CW6: type 1 | CX6: type 2 | CZ6: type 1 | DA6: type 2 | DB6: type 1 | DC6: type 2 | DD6: type 1 | DE6: type 2 | DF6: type 1 | DG6: type 2 | DH6: type 1 | DI6: type 2
A7: =A6+1 -> 2 | B7: Animal production | C7: 1.3255298 | D7: 1.8234871 | F7: 0.40443071 | G7: 0.53763507 | I7: 0.038064329 | J7: 0.067560263 | K7: 0.019364517 | L7: 0.028922591 | M7: 0.0066948245 | N7: 0.019087729 | O7: 0.00065799961 | P7: 0.0017473541 | Q7: 0.011346988 | R7: 0.017802589 | T7: =+F7/$W7 -> 1.3143988 | U7: =+G7/$W7 -> 1.7473126 | W7: 0.30769255 | X7: =+'I-O'!BO4/'I-O'!BO$75 -> 0.00044429918 | Y7: =+'I-O'!BP4/'I-O'!BP$75 -> 7.3931158e-05 | Z7: =+'I-O'!BT4/'I-O'!BT$75 -> 5.4976499e-05 | AA7: =+'I-O'!BU4/'I-O'!BU$75 -> 0 | AB7: =+'I-O'!BW4/'I-O'!BW$75 -> 0 | AD7: =+C6*$X6 -> 0.0018807767 | AE7: =+D6*$X6 -> 0.0025793731 | AG7: =+F6*$X6 -> 0.00056738575 | AH7: =+G6*$X6 -> 0.00075426141 | AJ7: =+I6*$X6 -> 6.8381384e-05 | AK7: =+J6*$X6 -> 0.00010976195 | AL7: =+K6*$X6 -> 3.2367628e-05 | AM7: =+L6*$X6 -> 4.5776884e-05 | AN7: =+M6*$X6 -> 1.6090365e-05 | AO7: =+N6*$X6 -> 3.3476674e-05 | AP7: =+O6*$X6 -> 1.3820025e-06 | AQ7: =+P6*$X6 -> 2.9102845e-06 | ... AS7: =+R6*$X6 -> 2.759811e-05 | AU7: =+$Y6*C6 -> 0.0014861769 | AV7: =+$Y6*D6 -> 0.0020382031 | AX7: =+$Y6*F6 -> 0.00044834435 | AY7: =+$Y6*G6 -> 0.00059601223 | BA7: =+$Y6*I6 -> 5.4034504e-05 | BB7: =+$Y6*J6 -> 8.6733147e-05 | BC7: =+$Y6*K6 -> 2.5576679e-05 | BD7: =+$Y6*L6 -> 3.6172582e-05 | BE7: =+$Y6*M6 -> 1.2714497e-05 | BF7: =+$Y6*N6 -> 2.645304e-05 | BG7: =+$Y6*O6 -> 1.0920489e-06 | BH7: =+$Y6*P6 -> 2.299687e-06 | ... BJ7: =+$Y6*R6 -> 2.1807839e-05 | BL7: =+C6*$Z6 -> 0.00080502065 | BM7: =+D6*$Z6 -> 0.0011040379 | BO7: =+F6*$Z6 -> 0.00024285565 | BP7: =+G6*$Z6 -> 0.00032284323 | BR7: =+I6*$Z6 -> 2.9268986e-05 | BS7: =+J6*$Z6 -> 4.6980931e-05 | BT7: =+K6*$Z6 -> 1.3854175e-05 | BU7: =+L6*$Z6 -> 1.959368e-05 | BV7: =+M6*$Z6 -> 6.8870889e-06 | BW7: =+N6*$Z6 -> 1.4328875e-05 | BX7: =+O6*$Z6 -> 5.9153251e-07 | BY7: =+P6*$Z6 -> 1.2456764e-06 | ... CA7: =+R6*$Z6 -> 1.1812699e-05 | CC7: =+C6*$AA6 -> 0 | CD7: =+D6*$AA6 -> 0 | CF7: =+F6*$AA6 -> 0 | CG7: =+G6*$AA6 -> 0 | CI7: =+I6*$AA6 -> 0 | CJ7: =+J6*$AA6 -> 0 | CK7: =+K6*$AA6 -> 0 | CL7: =+L6*$AA6 -> 0 | CM7: =+M6*$AA6 -> 0 | CN7: =+N6*$AA6 -> 0 | CO7: =+O6*$AA6 -> 0 | CP7: =+P6*$AA6 -> 0 | ... CR7: =+R6*$AA6 -> 0 | CT7: =+C6*$AB6 -> 0 | CU7: =+D6*$AB6 -> 0 | CW7: =+F6*$AB6 -> 0 | CX7: =+G6*$AB6 -> 0 | CZ7: =+I6*$AB6 -> 0 | DA7: =+J6*$AB6 -> 0 | DB7: =+K6*$AB6 -> 0 | DC7: =+L6*$AB6 -> 0 | DD7: =+M6*$AB6 -> 0 | DE7: =+N6*$AB6 -> 0 | DF7: =+O6*$AB6 -> 0 | DG7: =+P6*$AB6 -> 0 | ... DI7: =+R6*$AB6 -> 0
A8: =A7+1 -> 3 | B8: Commercial fishing | C8: 1.4311491 | D8: 2.0558189 | F8: 0.50734397 | G8: 0.67444411 | I8: 0.058773103 | J8: 0.095774705 | K8: 0.03082976 | L8: 0.042820024 | M8: 0.016477139 | N8: 0.032023598 | O8: 0.00064616984 | P8: 0.0020127263 | Q8: 0.010820034 | R8: 0.018918357 | T8: =+F8/$W8 -> 1.3520516 | U8: =+G8/$W8 -> 1.7973668 | W8: 0.3752401 | X8: =+'I-O'!BO5/'I-O'!BO$75 -> 0.00033285234 | Y8: =+'I-O'!BP5/'I-O'!BP$75 -> 9.1018812e-05 | Z8: =+'I-O'!BT5/'I-O'!BT$75 -> 7.4389257e-05 | AA8: =+'I-O'!BU5/'I-O'!BU$75 -> 0 | AB8: =+'I-O'!BW5/'I-O'!BW$75 -> 0 | AD8: =+C7*$X7 -> 0.00058893181 | AE8: =+D7*$X7 -> 0.00081017383 | AG8: =+F7*$X7 -> 0.00017968823 | AH8: =+G7*$X7 -> 0.00023887082 | AJ8: =+I7*$X7 -> 1.691195e-05 | AK8: =+J7*$X7 -> 3.001697e-05 | AL8: =+K7*$X7 -> 8.603639e-06 | AM8: =+L7*$X7 -> 1.2850283e-05 | AN8: =+M7*$X7 -> 2.9745051e-06 | AO8: =+N7*$X7 -> 8.4806625e-06 | AP8: =+O7*$X7 -> 2.9234869e-07 | AQ8: =+P7*$X7 -> 7.7634798e-07 | ... AS8: =+R7*$X7 -> 7.9096757e-06 | AU8: =+$Y7*C7 -> 9.7997953e-05 | AV8: =+$Y7*D7 -> 0.00013481251 | AX8: =+$Y7*F7 -> 2.990003e-05 | AY8: =+$Y7*G7 -> 3.9747983e-05 | BA8: =+$Y7*I7 -> 2.8141399e-06 | BB8: =+$Y7*J7 -> 4.9948084e-06 | BC8: =+$Y7*K7 -> 1.4316411e-06 | BD8: =+$Y7*L7 -> 2.1382806e-06 | BE8: =+$Y7*M7 -> 4.9495613e-07 | BF8: =+$Y7*N7 -> 1.4111779e-06 | BG8: =+$Y7*O7 -> 4.8646673e-08 | BH8: =+$Y7*P7 -> 1.2918391e-07 | ... BJ8: =+$Y7*R7 -> 1.316166e-06 | BL8: =+C7*$Z7 -> 7.2872988e-05 | BM8: =+D7*$Z7 -> 0.00010024894 | BO8: =+F7*$Z7 -> 2.2234184e-05 | BP8: =+G7*$Z7 -> 2.9557294e-05 | BR8: =+I7*$Z7 -> 2.0926435e-06 | BS8: =+J7*$Z7 -> 3.7142267e-06 | BT8: =+K7*$Z7 -> 1.0645933e-06 | BU8: =+L7*$Z7 -> 1.5900628e-06 | BV8: =+M7*$Z7 -> 3.6805801e-07 | BW8: =+N7*$Z7 -> 1.0493765e-06 | BX8: =+O7*$Z7 -> 3.6174515e-08 | BY8: =+P7*$Z7 -> 9.6063409e-08 | ... CA8: =+R7*$Z7 -> 9.78724e-07 | CC8: =+C7*$AA7 -> 0 | CD8: =+D7*$AA7 -> 0 | CF8: =+F7*$AA7 -> 0 | CG8: =+G7*$AA7 -> 0 | CI8: =+I7*$AA7 -> 0 | CJ8: =+J7*$AA7 -> 0 | CK8: =+K7*$AA7 -> 0 | CL8: =+L7*$AA7 -> 0 | CM8: =+M7*$AA7 -> 0 | CN8: =+N7*$AA7 -> 0 | CO8: =+O7*$AA7 -> 0 | CP8: =+P7*$AA7 -> 0 | ... CR8: =+R7*$AA7 -> 0 | CT8: =+C7*$AB7 -> 0 | CU8: =+D7*$AB7 -> 0 | CW8: =+F7*$AB7 -> 0 | CX8: =+G7*$AB7 -> 0 | CZ8: =+I7*$AB7 -> 0 | DA8: =+J7*$AB7 -> 0 | DB8: =+K7*$AB7 -> 0 | DC8: =+L7*$AB7 -> 0 | DD8: =+M7*$AB7 -> 0 | DE8: =+N7*$AB7 -> 0 | DF8: =+O7*$AB7 -> 0 | DG8: =+P7*$AB7 -> 0 | ... DI8: =+R7*$AB7 -> 0
A9: =A8+1 -> 4 | B9: Forestry & logging | C9: 1.5222268 | D9: 2.2192086 | F9: 0.56607437 | G9: 0.75251811 | I9: 0.048089113 | J9: 0.089374041 | K9: 0.031976121 | L9: 0.045354384 | M9: 0.0054054892 | N9: 0.022751614 | O9: 9.1402346e-05 | P9: 0.0016161521 | Q9: 0.010616101 | R9: 0.01965189 | T9: =+F9/$W9 -> 1.5085658 | U9: =+G9/$W9 -> 2.005431 | W9: 0.3752401 | X9: =+'I-O'!BO6/'I-O'!BO$75 -> 0 | Y9: =+'I-O'!BP6/'I-O'!BP$75 -> 0 | Z9: =+'I-O'!BT6/'I-O'!BT$75 -> 0 | AA9: =+'I-O'!BU6/'I-O'!BU$75 -> 0 | AB9: =+'I-O'!BW6/'I-O'!BW$75 -> 0 | AD9: =+C8*$X8 -> 0.00047636134 | AE9: =+D8*$X8 -> 0.00068428413 | AG9: =+F8*$X8 -> 0.00016887063 | AH9: =+G8*$X8 -> 0.0002244903 | AJ9: =+I8*$X8 -> 1.9562765e-05 | AK9: =+J8*$X8 -> 3.1878835e-05 | AL9: =+K8*$X8 -> 1.0261758e-05 | AM9: =+L8*$X8 -> 1.4252746e-05 | AN9: =+M8*$X8 -> 5.4844542e-06 | AO9: =+N8*$X8 -> 1.065913e-05 | AP9: =+O8*$X8 -> 2.1507915e-07 | AQ9: =+P8*$X8 -> 6.6994068e-07 | ... AS9: =+R8*$X8 -> 6.2970194e-06 | AU9: =+$Y8*C8 -> 0.00013026149 | AV9: =+$Y8*D8 -> 0.00018711819 | AX9: =+$Y8*F8 -> 4.6177845e-05 | AY9: =+$Y8*G8 -> 6.1387102e-05 | BA9: =+$Y8*I8 -> 5.349458e-06 | BB9: =+$Y8*J8 -> 8.7172999e-06 | BC9: =+$Y8*K8 -> 2.8060881e-06 | BD9: =+$Y8*L8 -> 3.8974278e-06 | BE9: =+$Y8*M8 -> 1.4997296e-06 | BF9: =+$Y8*N8 -> 2.9147498e-06 | BG9: =+$Y8*O8 -> 5.8813612e-08 | BH9: =+$Y8*P8 -> 1.8319596e-07 | ... BJ9: =+$Y8*R8 -> 1.7219264e-06 | BL9: =+C8*$Z8 -> 0.00010646212 | BM9: =+D8*$Z8 -> 0.00015293084 | BO9: =+F8*$Z8 -> 3.7740941e-05 | BP9: =+G8*$Z8 -> 5.0171396e-05 | BR9: =+I8*$Z8 -> 4.3720875e-06 | BS9: =+J8*$Z8 -> 7.1246092e-06 | BT9: =+K8*$Z8 -> 2.2934029e-06 | BU9: =+L8*$Z8 -> 3.1853498e-06 | BV9: =+M8*$Z8 -> 1.2257221e-06 | BW9: =+N8*$Z8 -> 2.3822116e-06 | BX9: =+O8*$Z8 -> 4.8068095e-08 | BY9: =+P8*$Z8 -> 1.4972522e-07 | ... CA9: =+R8*$Z8 -> 1.4073225e-06 | CC9: =+C8*$AA8 -> 0 | CD9: =+D8*$AA8 -> 0 | CF9: =+F8*$AA8 -> 0 | CG9: =+G8*$AA8 -> 0 | CI9: =+I8*$AA8 -> 0 | CJ9: =+J8*$AA8 -> 0 | CK9: =+K8*$AA8 -> 0 | CL9: =+L8*$AA8 -> 0 | CM9: =+M8*$AA8 -> 0 | CN9: =+N8*$AA8 -> 0 | CO9: =+O8*$AA8 -> 0 | CP9: =+P8*$AA8 -> 0 | ... CR9: =+R8*$AA8 -> 0 | CT9: =+C8*$AB8 -> 0 | CU9: =+D8*$AB8 -> 0 | CW9: =+F8*$AB8 -> 0 | CX9: =+G8*$AB8 -> 0 | CZ9: =+I8*$AB8 -> 0 | DA9: =+J8*$AB8 -> 0 | DB9: =+K8*$AB8 -> 0 | DC9: =+L8*$AB8 -> 0 | DD9: =+M8*$AB8 -> 0 | DE9: =+N8*$AB8 -> 0 | DF9: =+O8*$AB8 -> 0 | DG9: =+P8*$AB8 -> 0 | ... DI9: =+R8*$AB8 -> 0
A10: =A9+1 -> 5 | B10: Support activities for agriculture | C10: 1.432057 | D10: 1.957929 | F10: 0.42710244 | G10: 0.56777402 | I10: 0.065141687 | J10: 0.096291116 | K10: 0.025662069 | L10: 0.035755954 | M10: 0.026738047 | N10: 0.039825678 | O10: 0.00049353912 | P10: 0.001643961 | Q10: 0.012248032 | R10: 0.019065523 | T10: =+F10/$W10 -> 1.3880819 | U10: =+G10/$W10 -> 1.8452641 | W10: 0.30769255 | X10: =+'I-O'!BO7/'I-O'!BO$75 -> 0.0014894769 | Y10: =+'I-O'!BP7/'I-O'!BP$75 -> 0 | Z10: =+'I-O'!BT7/'I-O'!BT$75 -> 0 | AA10: =+'I-O'!BU7/'I-O'!BU$75 -> 0 | AB10: =+'I-O'!BW7/'I-O'!BW$75 -> 0 | AD10: =+C9*$X9 -> 0 | AE10: =+D9*$X9 -> 0 | AG10: =+F9*$X9 -> 0 | AH10: =+G9*$X9 -> 0 | AJ10: =+I9*$X9 -> 0 | AK10: =+J9*$X9 -> 0 | AL10: =+K9*$X9 -> 0 | AM10: =+L9*$X9 -> 0 | AN10: =+M9*$X9 -> 0 | AO10: =+N9*$X9 -> 0 | AP10: =+O9*$X9 -> 0 | AQ10: =+P9*$X9 -> 0 | ... AS10: =+R9*$X9 -> 0 | AU10: =+$Y9*C9 -> 0 | AV10: =+$Y9*D9 -> 0 | AX10: =+$Y9*F9 -> 0 | AY10: =+$Y9*G9 -> 0 | BA10: =+$Y9*I9 -> 0 | BB10: =+$Y9*J9 -> 0 | BC10: =+$Y9*K9 -> 0 | BD10: =+$Y9*L9 -> 0 | BE10: =+$Y9*M9 -> 0 | BF10: =+$Y9*N9 -> 0 | BG10: =+$Y9*O9 -> 0 | BH10: =+$Y9*P9 -> 0 | ... BJ10: =+$Y9*R9 -> 0 | BL10: =+C9*$Z9 -> 0 | BM10: =+D9*$Z9 -> 0 | BO10: =+F9*$Z9 -> 0 | BP10: =+G9*$Z9 -> 0 | BR10: =+I9*$Z9 -> 0 | BS10: =+J9*$Z9 -> 0 | BT10: =+K9*$Z9 -> 0 | BU10: =+L9*$Z9 -> 0 | BV10: =+M9*$Z9 -> 0 | BW10: =+N9*$Z9 -> 0 | BX10: =+O9*$Z9 -> 0 | BY10: =+P9*$Z9 -> 0 | ... CA10: =+R9*$Z9 -> 0 | CC10: =+C9*$AA9 -> 0 | CD10: =+D9*$AA9 -> 0 | CF10: =+F9*$AA9 -> 0 | CG10: =+G9*$AA9 -> 0 | CI10: =+I9*$AA9 -> 0 | CJ10: =+J9*$AA9 -> 0 | CK10: =+K9*$AA9 -> 0 | CL10: =+L9*$AA9 -> 0 | CM10: =+M9*$AA9 -> 0 | CN10: =+N9*$AA9 -> 0 | CO10: =+O9*$AA9 -> 0 | CP10: =+P9*$AA9 -> 0 | ... CR10: =+R9*$AA9 -> 0 | CT10: =+C9*$AB9 -> 0 | CU10: =+D9*$AB9 -> 0 | CW10: =+F9*$AB9 -> 0 | CX10: =+G9*$AB9 -> 0 | CZ10: =+I9*$AB9 -> 0 | DA10: =+J9*$AB9 -> 0 | DB10: =+K9*$AB9 -> 0 | DC10: =+L9*$AB9 -> 0 | DD10: =+M9*$AB9 -> 0 | DE10: =+N9*$AB9 -> 0 | DF10: =+O9*$AB9 -> 0 | DG10: =+P9*$AB9 -> 0 | ... DI10: =+R9*$AB9 -> 0
A11: =A10+1 -> 6 | B11: Mining | C11: 1.4978496 | D11: 1.9308596 | F11: 0.3516819 | G11: 0.46751277 | I11: 0.056316205 | J11: 0.081965064 | K11: 0.026068495 | L11: 0.034379935 | M11: 0.014158335 | N11: 0.024934866 | O11: 0.0015339173 | P11: 0.0024811901 | Q11: 0.014555458 | R11: 0.020169073 | T11: =+F11/$W11 -> 1.7223401 | U11: =+G11/$W11 -> 2.2896146 | W11: 0.20418842 | X11: =+'I-O'!BO8/'I-O'!BO$75 -> 0 | Y11: =+'I-O'!BP8/'I-O'!BP$75 -> 0 | Z11: =+'I-O'!BT8/'I-O'!BT$75 -> 0 | AA11: =+'I-O'!BU8/'I-O'!BU$75 -> 0 | AB11: =+'I-O'!BW8/'I-O'!BW$75 -> 9.0479776e-05 | AD11: =+C10*$X10 -> 0.0021330158 | AE11: =+D10*$X10 -> 0.00291629 | AG11: =+F10*$X10 -> 0.00063615922 | AH11: =+G10*$X10 -> 0.00084568628 | AJ11: =+I10*$X10 -> 9.7027037e-05 | AK11: =+J10*$X10 -> 0.00014342339 | AL11: =+K10*$X10 -> 3.8223059e-05 | AM11: =+L10*$X10 -> 5.3257666e-05 | AN11: =+M10*$X10 -> 3.9825703e-05 | AO11: =+N10*$X10 -> 5.9319427e-05 | AP11: =+O10*$X10 -> 7.3511512e-07 | AQ11: =+P10*$X10 -> 2.448642e-06 | ... AS11: =+R10*$X10 -> 2.8397656e-05 | AU11: =+$Y10*C10 -> 0 | AV11: =+$Y10*D10 -> 0 | AX11: =+$Y10*F10 -> 0 | AY11: =+$Y10*G10 -> 0 | BA11: =+$Y10*I10 -> 0 | BB11: =+$Y10*J10 -> 0 | BC11: =+$Y10*K10 -> 0 | BD11: =+$Y10*L10 -> 0 | BE11: =+$Y10*M10 -> 0 | BF11: =+$Y10*N10 -> 0 | BG11: =+$Y10*O10 -> 0 | BH11: =+$Y10*P10 -> 0 | ... BJ11: =+$Y10*R10 -> 0 | BL11: =+C10*$Z10 -> 0 | BM11: =+D10*$Z10 -> 0 | BO11: =+F10*$Z10 -> 0 | BP11: =+G10*$Z10 -> 0 | BR11: =+I10*$Z10 -> 0 | BS11: =+J10*$Z10 -> 0 | BT11: =+K10*$Z10 -> 0 | BU11: =+L10*$Z10 -> 0 | BV11: =+M10*$Z10 -> 0 | BW11: =+N10*$Z10 -> 0 | BX11: =+O10*$Z10 -> 0 | BY11: =+P10*$Z10 -> 0 | ... CA11: =+R10*$Z10 -> 0 | CC11: =+C10*$AA10 -> 0 | CD11: =+D10*$AA10 -> 0 | CF11: =+F10*$AA10 -> 0 | CG11: =+G10*$AA10 -> 0 | CI11: =+I10*$AA10 -> 0 | CJ11: =+J10*$AA10 -> 0 | CK11: =+K10*$AA10 -> 0 | CL11: =+L10*$AA10 -> 0 | CM11: =+M10*$AA10 -> 0 | CN11: =+N10*$AA10 -> 0 | CO11: =+O10*$AA10 -> 0 | CP11: =+P10*$AA10 -> 0 | ... CR11: =+R10*$AA10 -> 0 | CT11: =+C10*$AB10 -> 0 | CU11: =+D10*$AB10 -> 0 | CW11: =+F10*$AB10 -> 0 | CX11: =+G10*$AB10 -> 0 | CZ11: =+I10*$AB10 -> 0 | DA11: =+J10*$AB10 -> 0 | DB11: =+K10*$AB10 -> 0 | DC11: =+L10*$AB10 -> 0 | DD11: =+M10*$AB10 -> 0 | DE11: =+N10*$AB10 -> 0 | DF11: =+O10*$AB10 -> 0 | DG11: =+P10*$AB10 -> 0 | ... DI11: =+R10*$AB10 -> 0
A12: =A11+1 -> 7 | B12: Single family construction | C12: 1.4745155 | D12: 2.0447628 | F12: 0.46314317 | G12: 0.61568522 | I12: 0.10147814 | J12: 0.13525609 | K12: 0.031368155 | L12: 0.042313804 | M12: 0.053871173 | N12: 0.068063194 | O12: 0.0017761671 | P12: 0.0030236665 | Q12: 0.014462641 | R12: 0.021855422 | T12: =+F12/$W12 -> 1.4035268 | U12: =+G12/$W12 -> 1.865796 | W12: 0.32998528 | X12: =+'I-O'!BO9/'I-O'!BO$75 -> 0 | Y12: =+'I-O'!BP9/'I-O'!BP$75 -> 0 | Z12: =+'I-O'!BT9/'I-O'!BT$75 -> 0 | AA12: =+'I-O'!BU9/'I-O'!BU$75 -> 0 | AB12: =+'I-O'!BW9/'I-O'!BW$75 -> 0 | AD12: =+C11*$X11 -> 0 | AE12: =+D11*$X11 -> 0 | AG12: =+F11*$X11 -> 0 | AH12: =+G11*$X11 -> 0 | AJ12: =+I11*$X11 -> 0 | AK12: =+J11*$X11 -> 0 | AL12: =+K11*$X11 -> 0 | AM12: =+L11*$X11 -> 0 | AN12: =+M11*$X11 -> 0 | AO12: =+N11*$X11 -> 0 | AP12: =+O11*$X11 -> 0 | AQ12: =+P11*$X11 -> 0 | ... AS12: =+R11*$X11 -> 0 | AU12: =+$Y11*C11 -> 0 | AV12: =+$Y11*D11 -> 0 | AX12: =+$Y11*F11 -> 0 | AY12: =+$Y11*G11 -> 0 | BA12: =+$Y11*I11 -> 0 | BB12: =+$Y11*J11 -> 0 | BC12: =+$Y11*K11 -> 0 | BD12: =+$Y11*L11 -> 0 | BE12: =+$Y11*M11 -> 0 | BF12: =+$Y11*N11 -> 0 | BG12: =+$Y11*O11 -> 0 | BH12: =+$Y11*P11 -> 0 | ... BJ12: =+$Y11*R11 -> 0 | BL12: =+C11*$Z11 -> 0 | BM12: =+D11*$Z11 -> 0 | BO12: =+F11*$Z11 -> 0 | BP12: =+G11*$Z11 -> 0 | BR12: =+I11*$Z11 -> 0 | BS12: =+J11*$Z11 -> 0 | BT12: =+K11*$Z11 -> 0 | BU12: =+L11*$Z11 -> 0 | BV12: =+M11*$Z11 -> 0 | BW12: =+N11*$Z11 -> 0 | BX12: =+O11*$Z11 -> 0 | BY12: =+P11*$Z11 -> 0 | ... CA12: =+R11*$Z11 -> 0 | CC12: =+C11*$AA11 -> 0 | CD12: =+D11*$AA11 -> 0 | CF12: =+F11*$AA11 -> 0 | CG12: =+G11*$AA11 -> 0 | CI12: =+I11*$AA11 -> 0 | CJ12: =+J11*$AA11 -> 0 | CK12: =+K11*$AA11 -> 0 | CL12: =+L11*$AA11 -> 0 | CM12: =+M11*$AA11 -> 0 | CN12: =+N11*$AA11 -> 0 | CO12: =+O11*$AA11 -> 0 | CP12: =+P11*$AA11 -> 0 | ... CR12: =+R11*$AA11 -> 0 | CT12: =+C11*$AB11 -> 0.00013552509 | CU12: =+D11*$AB11 -> 0.00017470375 | CW12: =+F11*$AB11 -> 3.1820099e-05 | CX12: =+G11*$AB11 -> 4.230045e-05 | CZ12: =+I11*$AB11 -> 5.0954776e-06 | DA12: =+J11*$AB11 -> 7.4161806e-06 | DB12: =+K11*$AB11 -> 2.3586715e-06 | DC12: =+L11*$AB11 -> 3.1106888e-06 | DD12: =+M11*$AB11 -> 1.2810429e-06 | DE12: =+N11*$AB11 -> 2.2561011e-06 | DF12: =+O11*$AB11 -> 1.3878849e-07 | DG12: =+P11*$AB11 -> 2.2449753e-07 | ... DI12: =+R11*$AB11 -> 1.8248932e-06
A13: =A12+1 -> 8 | B13: Construction of other buildings | C13: 1.5152142 | D13: 2.1186079 | F13: 0.49006396 | G13: 0.65147272 | I13: 0.10431306 | J13: 0.1400544 | K13: 0.033237908 | L13: 0.044819787 | M13: 0.054756076 | N13: 0.069773026 | O13: 0.0022917198 | P13: 0.0036117317 | Q13: 0.014027356 | R13: 0.021849852 | T13: =+F13/$W13 -> 1.4851086 | U13: =+G13/$W13 -> 1.9742478 | W13: 0.32998528 | X13: =+'I-O'!BO10/'I-O'!BO$75 -> 0 | Y13: =+'I-O'!BP10/'I-O'!BP$75 -> 0 | Z13: =+'I-O'!BT10/'I-O'!BT$75 -> 0 | AA13: =+'I-O'!BU10/'I-O'!BU$75 -> 0 | AB13: =+'I-O'!BW10/'I-O'!BW$75 -> 0 | AD13: =+C12*$X12 -> 0 | AE13: =+D12*$X12 -> 0 | AG13: =+F12*$X12 -> 0 | AH13: =+G12*$X12 -> 0 | AJ13: =+I12*$X12 -> 0 | AK13: =+J12*$X12 -> 0 | AL13: =+K12*$X12 -> 0 | AM13: =+L12*$X12 -> 0 | AN13: =+M12*$X12 -> 0 | AO13: =+N12*$X12 -> 0 | AP13: =+O12*$X12 -> 0 | AQ13: =+P12*$X12 -> 0 | ... AS13: =+R12*$X12 -> 0 | AU13: =+$Y12*C12 -> 0 | AV13: =+$Y12*D12 -> 0 | AX13: =+$Y12*F12 -> 0 | AY13: =+$Y12*G12 -> 0 | BA13: =+$Y12*I12 -> 0 | BB13: =+$Y12*J12 -> 0 | BC13: =+$Y12*K12 -> 0 | BD13: =+$Y12*L12 -> 0 | BE13: =+$Y12*M12 -> 0 | BF13: =+$Y12*N12 -> 0 | BG13: =+$Y12*O12 -> 0 | BH13: =+$Y12*P12 -> 0 | ... BJ13: =+$Y12*R12 -> 0 | BL13: =+C12*$Z12 -> 0 | BM13: =+D12*$Z12 -> 0 | BO13: =+F12*$Z12 -> 0 | BP13: =+G12*$Z12 -> 0 | BR13: =+I12*$Z12 -> 0 | BS13: =+J12*$Z12 -> 0 | BT13: =+K12*$Z12 -> 0 | BU13: =+L12*$Z12 -> 0 | BV13: =+M12*$Z12 -> 0 | BW13: =+N12*$Z12 -> 0 | BX13: =+O12*$Z12 -> 0 | BY13: =+P12*$Z12 -> 0 | ... CA13: =+R12*$Z12 -> 0 | CC13: =+C12*$AA12 -> 0 | CD13: =+D12*$AA12 -> 0 | CF13: =+F12*$AA12 -> 0 | CG13: =+G12*$AA12 -> 0 | CI13: =+I12*$AA12 -> 0 | CJ13: =+J12*$AA12 -> 0 | CK13: =+K12*$AA12 -> 0 | CL13: =+L12*$AA12 -> 0 | CM13: =+M12*$AA12 -> 0 | CN13: =+N12*$AA12 -> 0 | CO13: =+O12*$AA12 -> 0 | CP13: =+P12*$AA12 -> 0 | ... CR13: =+R12*$AA12 -> 0 | CT13: =+C12*$AB12 -> 0 | CU13: =+D12*$AB12 -> 0 | CW13: =+F12*$AB12 -> 0 | CX13: =+G12*$AB12 -> 0 | CZ13: =+I12*$AB12 -> 0 | DA13: =+J12*$AB12 -> 0 | DB13: =+K12*$AB12 -> 0 | DC13: =+L12*$AB12 -> 0 | DD13: =+M12*$AB12 -> 0 | DE13: =+N12*$AB12 -> 0 | DF13: =+O12*$AB12 -> 0 | DG13: =+P12*$AB12 -> 0 | ... DI13: =+R12*$AB12 -> 0
A14: =A13+1 -> 9 | B14: Heavy and civil engineering construction | C14: 1.5218928 | D14: 2.130474 | F14: 0.49427718 | G14: 0.65707361 | I14: 0.10067601 | J14: 0.13672463 | K14: 0.033509372 | L14: 0.045190824 | M14: 0.050237778 | N14: 0.065383834 | O14: 0.0025399429 | P14: 0.0038713034 | Q14: 0.014388922 | R14: 0.02227867 | T14: =+F14/$W14 -> 1.4978765 | U14: =+G14/$W14 -> 1.991221 | W14: 0.32998528 | X14: =+'I-O'!BO11/'I-O'!BO$75 -> 0 | Y14: =+'I-O'!BP11/'I-O'!BP$75 -> 0 | Z14: =+'I-O'!BT11/'I-O'!BT$75 -> 0 | AA14: =+'I-O'!BU11/'I-O'!BU$75 -> 0 | AB14: =+'I-O'!BW11/'I-O'!BW$75 -> 0 | AD14: =+C13*$X13 -> 0 | AE14: =+D13*$X13 -> 0 | AG14: =+F13*$X13 -> 0 | AH14: =+G13*$X13 -> 0 | AJ14: =+I13*$X13 -> 0 | AK14: =+J13*$X13 -> 0 | AL14: =+K13*$X13 -> 0 | AM14: =+L13*$X13 -> 0 | AN14: =+M13*$X13 -> 0 | AO14: =+N13*$X13 -> 0 | AP14: =+O13*$X13 -> 0 | AQ14: =+P13*$X13 -> 0 | ... AS14: =+R13*$X13 -> 0 | AU14: =+$Y13*C13 -> 0 | AV14: =+$Y13*D13 -> 0 | AX14: =+$Y13*F13 -> 0 | AY14: =+$Y13*G13 -> 0 | BA14: =+$Y13*I13 -> 0 | BB14: =+$Y13*J13 -> 0 | BC14: =+$Y13*K13 -> 0 | BD14: =+$Y13*L13 -> 0 | BE14: =+$Y13*M13 -> 0 | BF14: =+$Y13*N13 -> 0 | BG14: =+$Y13*O13 -> 0 | BH14: =+$Y13*P13 -> 0 | ... BJ14: =+$Y13*R13 -> 0 | BL14: =+C13*$Z13 -> 0 | BM14: =+D13*$Z13 -> 0 | BO14: =+F13*$Z13 -> 0 | BP14: =+G13*$Z13 -> 0 | BR14: =+I13*$Z13 -> 0 | BS14: =+J13*$Z13 -> 0 | BT14: =+K13*$Z13 -> 0 | BU14: =+L13*$Z13 -> 0 | BV14: =+M13*$Z13 -> 0 | BW14: =+N13*$Z13 -> 0 | BX14: =+O13*$Z13 -> 0 | BY14: =+P13*$Z13 -> 0 | ... CA14: =+R13*$Z13 -> 0 | CC14: =+C13*$AA13 -> 0 | CD14: =+D13*$AA13 -> 0 | CF14: =+F13*$AA13 -> 0 | CG14: =+G13*$AA13 -> 0 | CI14: =+I13*$AA13 -> 0 | CJ14: =+J13*$AA13 -> 0 | CK14: =+K13*$AA13 -> 0 | CL14: =+L13*$AA13 -> 0 | CM14: =+M13*$AA13 -> 0 | CN14: =+N13*$AA13 -> 0 | CO14: =+O13*$AA13 -> 0 | CP14: =+P13*$AA13 -> 0 | ... CR14: =+R13*$AA13 -> 0 | CT14: =+C13*$AB13 -> 0 | CU14: =+D13*$AB13 -> 0 | CW14: =+F13*$AB13 -> 0 | CX14: =+G13*$AB13 -> 0 | CZ14: =+I13*$AB13 -> 0 | DA14: =+J13*$AB13 -> 0 | DB14: =+K13*$AB13 -> 0 | DC14: =+L13*$AB13 -> 0 | DD14: =+M13*$AB13 -> 0 | DE14: =+N13*$AB13 -> 0 | DF14: =+O13*$AB13 -> 0 | DG14: =+P13*$AB13 -> 0 | ... DI14: =+R13*$AB13 -> 0
A15: =A14+1 -> 10 | B15: Maintenance & repairs | C15: 1.4720762 | D15: 2.0506088 | F15: 0.46987238 | G15: 0.62463078 | I15: 0.10408979 | J15: 0.13835852 | K15: 0.031724652 | L15: 0.042829335 | M15: 0.057285193 | N15: 0.071683416 | O15: 0.0019951487 | P15: 0.0032607736 | Q15: 0.013084799 | R15: 0.020584993 | T15: =+F15/$W15 -> 1.4239192 | U15: =+G15/$W15 -> 1.892905 | W15: 0.32998528 | X15: =+'I-O'!BO12/'I-O'!BO$75 -> 0.0056221616 | Y15: =+'I-O'!BP12/'I-O'!BP$75 -> 0 | Z15: =+'I-O'!BT12/'I-O'!BT$75 -> 0 | AA15: =+'I-O'!BU12/'I-O'!BU$75 -> 0.0034347757 | AB15: =+'I-O'!BW12/'I-O'!BW$75 -> 0 | AD15: =+C14*$X14 -> 0 | AE15: =+D14*$X14 -> 0 | AG15: =+F14*$X14 -> 0 | AH15: =+G14*$X14 -> 0 | AJ15: =+I14*$X14 -> 0 | AK15: =+J14*$X14 -> 0 | AL15: =+K14*$X14 -> 0 | AM15: =+L14*$X14 -> 0 | AN15: =+M14*$X14 -> 0 | AO15: =+N14*$X14 -> 0 | AP15: =+O14*$X14 -> 0 | AQ15: =+P14*$X14 -> 0 | ... AS15: =+R14*$X14 -> 0 | AU15: =+$Y14*C14 -> 0 | AV15: =+$Y14*D14 -> 0 | AX15: =+$Y14*F14 -> 0 | AY15: =+$Y14*G14 -> 0 | BA15: =+$Y14*I14 -> 0 | BB15: =+$Y14*J14 -> 0 | BC15: =+$Y14*K14 -> 0 | BD15: =+$Y14*L14 -> 0 | BE15: =+$Y14*M14 -> 0 | BF15: =+$Y14*N14 -> 0 | BG15: =+$Y14*O14 -> 0 | BH15: =+$Y14*P14 -> 0 | ... BJ15: =+$Y14*R14 -> 0 | BL15: =+C14*$Z14 -> 0 | BM15: =+D14*$Z14 -> 0 | BO15: =+F14*$Z14 -> 0 | BP15: =+G14*$Z14 -> 0 | BR15: =+I14*$Z14 -> 0 | BS15: =+J14*$Z14 -> 0 | BT15: =+K14*$Z14 -> 0 | BU15: =+L14*$Z14 -> 0 | BV15: =+M14*$Z14 -> 0 | BW15: =+N14*$Z14 -> 0 | BX15: =+O14*$Z14 -> 0 | BY15: =+P14*$Z14 -> 0 | ... CA15: =+R14*$Z14 -> 0 | CC15: =+C14*$AA14 -> 0 | CD15: =+D14*$AA14 -> 0 | CF15: =+F14*$AA14 -> 0 | CG15: =+G14*$AA14 -> 0 | CI15: =+I14*$AA14 -> 0 | CJ15: =+J14*$AA14 -> 0 | CK15: =+K14*$AA14 -> 0 | CL15: =+L14*$AA14 -> 0 | CM15: =+M14*$AA14 -> 0 | CN15: =+N14*$AA14 -> 0 | CO15: =+O14*$AA14 -> 0 | CP15: =+P14*$AA14 -> 0 | ... CR15: =+R14*$AA14 -> 0 | CT15: =+C14*$AB14 -> 0 | CU15: =+D14*$AB14 -> 0 | CW15: =+F14*$AB14 -> 0 | CX15: =+G14*$AB14 -> 0 | CZ15: =+I14*$AB14 -> 0 | DA15: =+J14*$AB14 -> 0 | DB15: =+K14*$AB14 -> 0 | DC15: =+L14*$AB14 -> 0 | DD15: =+M14*$AB14 -> 0 | DE15: =+N14*$AB14 -> 0 | DF15: =+O14*$AB14 -> 0 | DG15: =+P14*$AB14 -> 0 | ... DI15: =+R14*$AB14 -> 0
A16: =A15+1 -> 11 | B16: Food processing | C16: 1.5958613 | D16: 2.113805 | F16: 0.42066327 | G16: 0.55921403 | I16: 0.064371558 | J16: 0.095051365 | K16: 0.031255458 | L16: 0.041197163 | M16: 0.015719985 | N16: 0.028610302 | O16: 0.0038267074 | P16: 0.0049597851 | Q16: 0.013569407 | R16: 0.020284115 | T16: =+F16/$W16 -> 1.8387562 | U16: =+G16/$W16 -> 2.4443738 | W16: 0.22877599 | X16: =+'I-O'!BO13/'I-O'!BO$75 -> 0.0037793376 | Y16: =+'I-O'!BP13/'I-O'!BP$75 -> 0.0016232211 | Z16: =+'I-O'!BT13/'I-O'!BT$75 -> 0.0014020593 | AA16: =+'I-O'!BU13/'I-O'!BU$75 -> 0.00049205336 | AB16: =+'I-O'!BW13/'I-O'!BW$75 -> 0.00019148082 | AD16: =+C15*$X15 -> 0.00827625 | AE16: =+D15*$X15 -> 0.011528854 | AG16: =+F15*$X15 -> 0.0026416984 | AH16: =+G15*$X15 -> 0.0035117752 | AJ16: =+I15*$X15 -> 0.00058520963 | AK16: =+J15*$X15 -> 0.00077787394 | AL16: =+K15*$X15 -> 0.00017836112 | AM16: =+L15*$X15 -> 0.00024079344 | AN16: =+M15*$X15 -> 0.00032206661 | AO16: =+N15*$X15 -> 0.00040301575 | AP16: =+O15*$X15 -> 1.1217048e-05 | AQ16: =+P15*$X15 -> 1.8332596e-05 | ... AS16: =+R15*$X15 -> 0.00011573216 | AU16: =+$Y15*C15 -> 0 | AV16: =+$Y15*D15 -> 0 | AX16: =+$Y15*F15 -> 0 | AY16: =+$Y15*G15 -> 0 | BA16: =+$Y15*I15 -> 0 | BB16: =+$Y15*J15 -> 0 | BC16: =+$Y15*K15 -> 0 | BD16: =+$Y15*L15 -> 0 | BE16: =+$Y15*M15 -> 0 | BF16: =+$Y15*N15 -> 0 | BG16: =+$Y15*O15 -> 0 | BH16: =+$Y15*P15 -> 0 | ... BJ16: =+$Y15*R15 -> 0 | BL16: =+C15*$Z15 -> 0 | BM16: =+D15*$Z15 -> 0 | BO16: =+F15*$Z15 -> 0 | BP16: =+G15*$Z15 -> 0 | BR16: =+I15*$Z15 -> 0 | BS16: =+J15*$Z15 -> 0 | BT16: =+K15*$Z15 -> 0 | BU16: =+L15*$Z15 -> 0 | BV16: =+M15*$Z15 -> 0 | BW16: =+N15*$Z15 -> 0 | BX16: =+O15*$Z15 -> 0 | BY16: =+P15*$Z15 -> 0 | ... CA16: =+R15*$Z15 -> 0 | CC16: =+C15*$AA15 -> 0.0050562514 | CD16: =+D15*$AA15 -> 0.0070433813 | CF16: =+F15*$AA15 -> 0.0016139062 | CG16: =+G15*$AA15 -> 0.0021454666 | CI16: =+I15*$AA15 -> 0.00035752509 | CJ16: =+J15*$AA15 -> 0.00047523047 | CK16: =+K15*$AA15 -> 0.00010896706 | CL16: =+L15*$AA15 -> 0.00014710916 | CM16: =+M15*$AA15 -> 0.00019676179 | CN16: =+N15*$AA15 -> 0.00024621645 | CO16: =+O15*$AA15 -> 6.8528881e-06 | CP16: =+P15*$AA15 -> 1.1200026e-05 | ... CR16: =+R15*$AA15 -> 7.0704833e-05 | CT16: =+C15*$AB15 -> 0 | CU16: =+D15*$AB15 -> 0 | CW16: =+F15*$AB15 -> 0 | CX16: =+G15*$AB15 -> 0 | CZ16: =+I15*$AB15 -> 0 | DA16: =+J15*$AB15 -> 0 | DB16: =+K15*$AB15 -> 0 | DC16: =+L15*$AB15 -> 0 | DD16: =+M15*$AB15 -> 0 | DE16: =+N15*$AB15 -> 0 | DF16: =+O15*$AB15 -> 0 | DG16: =+P15*$AB15 -> 0 | ... DI16: =+R15*$AB15 -> 0
A17: =A16+1 -> 12 | B17: Beverage manufacturing | C17: 1.5841104 | D17: 2.0003106 | F17: 0.33802929 | G17: 0.4493635 | I17: 0.05726688 | J17: 0.081920026 | K17: 0.025324344 | L17: 0.033313127 | M17: 0.015481775 | N17: 0.025839952 | O17: 0.0031189649 | P17: 0.0040294638 | Q17: 0.013341795 | R17: 0.018737484 | T17: =+F17/$W17 -> 2.0832193 | U17: =+G17/$W17 -> 2.7693539 | W17: 0.16226294 | X17: =+'I-O'!BO14/'I-O'!BO$75 -> 0.0042703435 | Y17: =+'I-O'!BP14/'I-O'!BP$75 -> 0.00067466467 | Z17: =+'I-O'!BT14/'I-O'!BT$75 -> 0.0016426879 | AA17: =+'I-O'!BU14/'I-O'!BU$75 -> 3.0036365e-07 | AB17: =+'I-O'!BW14/'I-O'!BW$75 -> 5.5978913e-05 | AD17: =+C16*$X16 -> 0.0060312985 | AE17: =+D16*$X16 -> 0.0079887827 | AG17: =+F16*$X16 -> 0.0015898285 | AH17: =+G16*$X16 -> 0.0021134586 | AJ17: =+I16*$X16 -> 0.00024328185 | AK17: =+J16*$X16 -> 0.0003592312 | AL17: =+K16*$X16 -> 0.00011812493 | AM17: =+L16*$X16 -> 0.00015569799 | AN17: =+M16*$X16 -> 5.9411132e-05 | AO17: =+N16*$X16 -> 0.00010812799 | AP17: =+O16*$X16 -> 1.4462419e-05 | AQ17: =+P16*$X16 -> 1.8744702e-05 | ... AS17: =+R16*$X16 -> 7.666052e-05 | AU17: =+$Y16*C16 -> 0.0025904356 | AV17: =+$Y16*D16 -> 0.0034311728 | AX17: =+$Y16*F16 -> 0.00068282949 | AY17: =+$Y16*G16 -> 0.000907728 | BA17: =+$Y16*I16 -> 0.00010448927 | BB17: =+$Y16*J16 -> 0.00015428938 | BC17: =+$Y16*K16 -> 5.0734518e-05 | BD17: =+$Y16*L16 -> 6.6872103e-05 | BE17: =+$Y16*M16 -> 2.5517011e-05 | BF17: =+$Y16*N16 -> 4.6440845e-05 | BG17: =+$Y16*O16 -> 6.2115921e-06 | BH17: =+$Y16*P16 -> 8.0508276e-06 | ... BJ17: =+$Y16*R16 -> 3.2925604e-05 | BL17: =+C16*$Z16 -> 0.0022374921 | BM17: =+D16*$Z16 -> 0.00296368 | BO17: =+F16*$Z16 -> 0.00058979486 | BP17: =+G16*$Z16 -> 0.00078405124 | BR17: =+I16*$Z16 -> 9.0252742e-05 | BS17: =+J16*$Z16 -> 0.00013326765 | BT17: =+K16*$Z16 -> 4.3822006e-05 | BU17: =+L16*$Z16 -> 5.7760866e-05 | BV17: =+M16*$Z16 -> 2.2040352e-05 | BW17: =+N16*$Z16 -> 4.011334e-05 | BX17: =+O16*$Z16 -> 5.3652707e-06 | BY17: =+P16*$Z16 -> 6.9539128e-06 | ... CA17: =+R16*$Z16 -> 2.8439533e-05 | CC17: =+C16*$AA16 -> 0.00078524889 | CD17: =+D16*$AA16 -> 0.0010401048 | CF17: =+F16*$AA16 -> 0.00020698878 | CG17: =+G16*$AA16 -> 0.00027516314 | CI17: =+I16*$AA16 -> 3.1674241e-05 | CJ17: =+J16*$AA16 -> 4.6770343e-05 | CK17: =+K16*$AA16 -> 1.5379353e-05 | CL17: =+L16*$AA16 -> 2.0271202e-05 | CM17: =+M16*$AA16 -> 7.7350716e-06 | CN17: =+N16*$AA16 -> 1.4077795e-05 | CO17: =+O16*$AA16 -> 1.8829442e-06 | CP17: =+P16*$AA16 -> 2.4404789e-06 | ... CR17: =+R16*$AA16 -> 9.9808671e-06 | CT17: =+C16*$AB16 -> 0.00030557683 | CU17: =+D16*$AB16 -> 0.00040475312 | CW17: =+F16*$AB16 -> 8.054895e-05 | CX17: =+G16*$AB16 -> 0.00010707876 | CZ17: =+I16*$AB16 -> 1.2325919e-05 | DA17: =+J16*$AB16 -> 1.8200514e-05 | DB17: =+K16*$AB16 -> 5.9848208e-06 | DC17: =+L16*$AB16 -> 7.8884666e-06 | DD17: =+M16*$AB16 -> 3.0100757e-06 | DE17: =+N16*$AB16 -> 5.4783242e-06 | DF17: =+O16*$AB16 -> 7.3274108e-07 | DG17: =+P16*$AB16 -> 9.4970373e-07 | ... DI17: =+R16*$AB16 -> 3.8840191e-06
A18: =A17+1 -> 13 | B18: Apparel and textile manufacturing | C18: 1.418927 | D18: 2.0151392 | F18: 0.48423133 | G18: 0.64371903 | I18: 0.067233143 | J18: 0.10254909 | K18: 0.037903784 | L18: 0.049347818 | M18: 0.013692009 | N18: 0.028530231 | O18: 0.0025253249 | P18: 0.0038296264 | Q18: 0.013112025 | R18: 0.020841419 | T18: =+F18/$W18 -> 1.3667485 | U18: =+G18/$W18 -> 1.8169044 | W18: 0.35429438 | X18: =+'I-O'!BO15/'I-O'!BO$75 -> 0.00025298303 | Y18: =+'I-O'!BP15/'I-O'!BP$75 -> 0.00040645012 | Z18: =+'I-O'!BT15/'I-O'!BT$75 -> 7.3016843e-05 | AA18: =+'I-O'!BU15/'I-O'!BU$75 -> 1.1622672e-07 | AB18: =+'I-O'!BW15/'I-O'!BW$75 -> 2.1051215e-05 | AD18: =+C17*$X17 -> 0.0067646956 | AE18: =+D17*$X17 -> 0.0085420135 | AG18: =+F17*$X17 -> 0.0014435012 | AH18: =+G17*$X17 -> 0.0019189365 | AJ18: =+I17*$X17 -> 0.00024454924 | AK18: =+J17*$X17 -> 0.00034982665 | AL18: =+K17*$X17 -> 0.00010814365 | AM18: =+L17*$X17 -> 0.00014225849 | AN18: =+M17*$X17 -> 6.6112498e-05 | AO18: =+N17*$X17 -> 0.00011034547 | AP18: =+O17*$X17 -> 1.3319051e-05 | AQ18: =+P17*$X17 -> 1.7207194e-05 | ... AS18: =+R17*$X17 -> 8.0015493e-05 | AU18: =+$Y17*C17 -> 0.0010687433 | AV18: =+$Y17*D17 -> 0.0013495389 | AX18: =+$Y17*F17 -> 0.00022805642 | AY18: =+$Y17*G17 -> 0.00030316968 | BA18: =+$Y17*I17 -> 3.863594e-05 | BB18: =+$Y17*J17 -> 5.5268547e-05 | BC18: =+$Y17*K17 -> 1.708544e-05 | BD18: =+$Y17*L17 -> 2.2475189e-05 | BE18: =+$Y17*M17 -> 1.0445007e-05 | BF18: =+$Y17*N17 -> 1.7433303e-05 | BG18: =+$Y17*O17 -> 2.1042554e-06 | BH18: =+$Y17*P17 -> 2.7185369e-06 | ... BJ18: =+$Y17*R17 -> 1.2641518e-05 | BL18: =+C17*$Z17 -> 0.002602199 | BM18: =+D17*$Z17 -> 0.0032858861 | BO18: =+F17*$Z17 -> 0.00055527662 | BP18: =+G17*$Z17 -> 0.00073816398 | BR18: =+I17*$Z17 -> 9.407161e-05 | BS18: =+J17*$Z17 -> 0.00013456904 | BT18: =+K17*$Z17 -> 4.1599994e-05 | BU18: =+L17*$Z17 -> 5.472307e-05 | BV18: =+M17*$Z17 -> 2.5431725e-05 | BW18: =+N17*$Z17 -> 4.2446977e-05 | BX18: =+O17*$Z17 -> 5.1234859e-06 | BY18: =+P17*$Z17 -> 6.6191514e-06 | ... CA18: =+R17*$Z17 -> 3.0779838e-05 | CC18: =+C17*$AA17 -> 4.7580919e-07 | CD18: =+D17*$AA17 -> 6.0082061e-07 | CF18: =+F17*$AA17 -> 1.0153171e-07 | CG18: =+G17*$AA17 -> 1.3497246e-07 | CI18: =+I17*$AA17 -> 1.7200889e-08 | CJ18: =+J17*$AA17 -> 2.4605798e-08 | CK18: =+K17*$AA17 -> 7.6065125e-09 | CL18: =+L17*$AA17 -> 1.0006052e-08 | CM18: =+M17*$AA17 -> 4.6501626e-09 | CN18: =+N17*$AA17 -> 7.7613823e-09 | CO18: =+O17*$AA17 -> 9.3682369e-10 | CP18: =+P17*$AA17 -> 1.2103045e-09 | ... CR18: =+R17*$AA17 -> 5.6280591e-09 | CT18: =+C17*$AB17 -> 8.8676779e-05 | CU18: =+D17*$AB17 -> 0.00011197522 | CW18: =+F17*$AB17 -> 1.8922512e-05 | CX18: =+G17*$AB17 -> 2.515488e-05 | CZ18: =+I17*$AB17 -> 3.2057377e-06 | DA18: =+J17*$AB17 -> 4.585794e-06 | DB18: =+K17*$AB17 -> 1.4176293e-06 | DC18: =+L17*$AB17 -> 1.8648326e-06 | DD18: =+M17*$AB17 -> 8.6665295e-07 | DE18: =+N17*$AB17 -> 1.4464924e-06 | DF18: =+O17*$AB17 -> 1.7459626e-07 | DG18: =+P17*$AB17 -> 2.25565e-07 | ... DI18: =+R17*$AB17 -> 1.048904e-06
... A40: =A39+1 -> 35 | B40: Other finance and insurance | C40: 1.8639635 | D40: 2.4525619 | F40: 0.47804751 | G40: 0.6354985 | I40: 0.088972378 | J40: 0.12383733 | K40: 0.035384707 | L40: 0.046682597 | M40: 0.018829262 | N40: 0.033477994 | O40: 0.0049164824 | P40: 0.0062041274 | Q40: 0.029841927 | R40: 0.037472614 | T40: =+F40/$W40 -> 2.1087043 | U40: =+G40/$W40 -> 2.8032327 | W40: 0.22670201 | X40: =+'I-O'!BO37/'I-O'!BO$75 -> 0.0047783734 | Y40: =+'I-O'!BP37/'I-O'!BP$75 -> 0 | Z40: =+'I-O'!BT37/'I-O'!BT$75 -> 0 | AA40: =+'I-O'!BU37/'I-O'!BU$75 -> 0 | AB40: =+'I-O'!BW37/'I-O'!BW$75 -> 0 | AD40: =+C39*$X39 -> 0.027738231 | AE40: =+D39*$X39 -> 0.036548641 | AG40: =+F39*$X39 -> 0.0071556344 | AH40: =+G39*$X39 -> 0.0095124329 | AJ40: =+I39*$X39 -> 0.0030292709 | AK40: =+J39*$X39 -> 0.0035511455 | AL40: =+K39*$X39 -> 0.00055256901 | AM40: =+L39*$X39 -> 0.000721681 | AN40: =+M39*$X39 -> 0.0001209052 | AO40: =+N39*$X39 -> 0.00034017415 | AP40: =+O39*$X39 -> 2.0929533e-05 | AQ40: =+P39*$X39 -> 4.0203594e-05 | ... AS40: =+R39*$X39 -> 0.0024490868 | AU40: =+$Y39*C39 -> 0 | AV40: =+$Y39*D39 -> 0 | AX40: =+$Y39*F39 -> 0 | AY40: =+$Y39*G39 -> 0 | BA40: =+$Y39*I39 -> 0 | BB40: =+$Y39*J39 -> 0 | BC40: =+$Y39*K39 -> 0 | BD40: =+$Y39*L39 -> 0 | BE40: =+$Y39*M39 -> 0 | BF40: =+$Y39*N39 -> 0 | BG40: =+$Y39*O39 -> 0 | BH40: =+$Y39*P39 -> 0 | ... BJ40: =+$Y39*R39 -> 0 | BL40: =+C39*$Z39 -> 0 | BM40: =+D39*$Z39 -> 0 | BO40: =+F39*$Z39 -> 0 | BP40: =+G39*$Z39 -> 0 | BR40: =+I39*$Z39 -> 0 | BS40: =+J39*$Z39 -> 0 | BT40: =+K39*$Z39 -> 0 | BU40: =+L39*$Z39 -> 0 | BV40: =+M39*$Z39 -> 0 | BW40: =+N39*$Z39 -> 0 | BX40: =+O39*$Z39 -> 0 | BY40: =+P39*$Z39 -> 0 | ... CA40: =+R39*$Z39 -> 0 | CC40: =+C39*$AA39 -> 0 | CD40: =+D39*$AA39 -> 0 | CF40: =+F39*$AA39 -> 0 | CG40: =+G39*$AA39 -> 0 | CI40: =+I39*$AA39 -> 0 | CJ40: =+J39*$AA39 -> 0 | CK40: =+K39*$AA39 -> 0 | CL40: =+L39*$AA39 -> 0 | CM40: =+M39*$AA39 -> 0 | CN40: =+N39*$AA39 -> 0 | CO40: =+O39*$AA39 -> 0 | CP40: =+P39*$AA39 -> 0 | ... CR40: =+R39*$AA39 -> 0 | CT40: =+C39*$AB39 -> 0 | CU40: =+D39*$AB39 -> 0 | CW40: =+F39*$AB39 -> 0 | CX40: =+G39*$AB39 -> 0 | CZ40: =+I39*$AB39 -> 0 | DA40: =+J39*$AB39 -> 0 | DB40: =+K39*$AB39 -> 0 | DC40: =+L39*$AB39 -> 0 | DD40: =+M39*$AB39 -> 0 | DE40: =+N39*$AB39 -> 0 | DF40: =+O39*$AB39 -> 0 | DG40: =+P39*$AB39 -> 0 | ... DI40: =+R39*$AB39 -> 0
A41: =A40+1 -> 36 | B41: Owner-occupied dwellings | C41: 1.3208347 | D41: 1.4300097 | F41: 0.088669664 | G41: 0.11787414 | I41: 0.029176152 | J41: 0.035643006 | K41: 0.0061836243 | L41: 0.0082791902 | M41: 0.0092969883 | N41: 0.012014078 | O41: 0.00051303497 | P41: 0.00075187116 | Q41: 0.013182504 | R41: 0.014597867 | T41: NA | U41: NA | W41: 0 | X41: =+'I-O'!BO38/'I-O'!BO$75 -> 0.17124624 | Y41: =+'I-O'!BP38/'I-O'!BP$75 -> 0.016938875 | Z41: =+'I-O'!BT38/'I-O'!BT$75 -> 0 | AA41: =+'I-O'!BU38/'I-O'!BU$75 -> 0 | AB41: =+'I-O'!BW38/'I-O'!BW$75 -> 0 | AD41: =+C40*$X40 -> 0.0089067137 | AE41: =+D40*$X40 -> 0.011719256 | AG41: =+F40*$X40 -> 0.0022842895 | AH41: =+G40*$X40 -> 0.0030366491 | AJ41: =+I40*$X40 -> 0.00042514324 | AK41: =+J40*$X40 -> 0.00059174101 | AL41: =+K40*$X40 -> 0.00016908134 | AM41: =+L40*$X40 -> 0.00022306688 | AN41: =+M40*$X40 -> 8.9973243e-05 | AO41: =+N40*$X40 -> 0.00015997036 | AP41: =+O40*$X40 -> 2.3492789e-05 | AQ41: =+P40*$X40 -> 2.9645637e-05 | ... AS41: =+R40*$X40 -> 0.00017905814 | AU41: =+$Y40*C40 -> 0 | AV41: =+$Y40*D40 -> 0 | AX41: =+$Y40*F40 -> 0 | AY41: =+$Y40*G40 -> 0 | BA41: =+$Y40*I40 -> 0 | BB41: =+$Y40*J40 -> 0 | BC41: =+$Y40*K40 -> 0 | BD41: =+$Y40*L40 -> 0 | BE41: =+$Y40*M40 -> 0 | BF41: =+$Y40*N40 -> 0 | BG41: =+$Y40*O40 -> 0 | BH41: =+$Y40*P40 -> 0 | ... BJ41: =+$Y40*R40 -> 0 | BL41: =+C40*$Z40 -> 0 | BM41: =+D40*$Z40 -> 0 | BO41: =+F40*$Z40 -> 0 | BP41: =+G40*$Z40 -> 0 | BR41: =+I40*$Z40 -> 0 | BS41: =+J40*$Z40 -> 0 | BT41: =+K40*$Z40 -> 0 | BU41: =+L40*$Z40 -> 0 | BV41: =+M40*$Z40 -> 0 | BW41: =+N40*$Z40 -> 0 | BX41: =+O40*$Z40 -> 0 | BY41: =+P40*$Z40 -> 0 | ... CA41: =+R40*$Z40 -> 0 | CC41: =+C40*$AA40 -> 0 | CD41: =+D40*$AA40 -> 0 | CF41: =+F40*$AA40 -> 0 | CG41: =+G40*$AA40 -> 0 | CI41: =+I40*$AA40 -> 0 | CJ41: =+J40*$AA40 -> 0 | CK41: =+K40*$AA40 -> 0 | CL41: =+L40*$AA40 -> 0 | CM41: =+M40*$AA40 -> 0 | CN41: =+N40*$AA40 -> 0 | CO41: =+O40*$AA40 -> 0 | CP41: =+P40*$AA40 -> 0 | ... CR41: =+R40*$AA40 -> 0 | CT41: =+C40*$AB40 -> 0 | CU41: =+D40*$AB40 -> 0 | CW41: =+F40*$AB40 -> 0 | CX41: =+G40*$AB40 -> 0 | CZ41: =+I40*$AB40 -> 0 | DA41: =+J40*$AB40 -> 0 | DB41: =+K40*$AB40 -> 0 | DC41: =+L40*$AB40 -> 0 | DD41: =+M40*$AB40 -> 0 | DE41: =+N40*$AB40 -> 0 | DF41: =+O40*$AB40 -> 0 | DG41: =+P40*$AB40 -> 0 | ... DI41: =+R40*$AB40 -> 0
A42: =A41+1 -> 37 | B42: Real estate | C42: 1.3348462 | D42: 1.755656 | F42: 0.34177309 | G42: 0.45434037 | I42: 0.11351556 | J42: 0.13844175 | K42: 0.02239259 | L42: 0.030469851 | M42: 0.064575648 | N42: 0.075048545 | O42: 0.002720517 | P42: 0.0036411 | Q42: 0.023826805 | R42: 0.029282253 | T42: =+F42/$W42 -> 1.4070702 | U42: =+G42/$W42 -> 1.8705065 | W42: 0.24289697 | X42: =+'I-O'!BO39/'I-O'!BO$75 -> 0.04357891 | Y42: =+'I-O'!BP39/'I-O'!BP$75 -> 0.02002153 | Z42: =+'I-O'!BT39/'I-O'!BT$75 -> 0.013964627 | AA42: =+'I-O'!BU39/'I-O'!BU$75 -> 1.8292499e-06 | AB42: =+'I-O'!BW39/'I-O'!BW$75 -> 0.0001103289 | AD42: =+C41*$X41 -> 0.22618798 | AE42: =+D41*$X41 -> 0.24488379 | AG42: =+F41*$X41 -> 0.015184347 | AH42: =+G41*$X41 -> 0.020185503 | AJ42: =+I41*$X41 -> 0.0049963064 | AK42: =+J41*$X41 -> 0.0061037309 | AL42: =+K41*$X41 -> 0.0010589224 | AM42: =+L41*$X41 -> 0.0014177802 | AN42: =+M41*$X41 -> 0.0015920743 | AO42: =+N41*$X41 -> 0.0020573658 | AP42: =+O41*$X41 -> 8.7855311e-05 | AQ42: =+P41*$X41 -> 0.00012875511 | ... AS42: =+R41*$X41 -> 0.0024998298 | AU42: =+$Y41*C41 -> 0.022373455 | AV42: =+$Y41*D41 -> 0.024222756 | AX42: =+$Y41*F41 -> 0.0015019644 | AY42: =+$Y41*G41 -> 0.0019966553 | BA42: =+$Y41*I41 -> 0.0004942112 | BB42: =+$Y41*J41 -> 0.00060375244 | BC42: =+$Y41*K41 -> 0.00010474364 | BD42: =+$Y41*L41 -> 0.00014024017 | BE42: =+$Y41*M41 -> 0.00015748053 | BF42: =+$Y41*N41 -> 0.00020350498 | BG42: =+$Y41*O41 -> 8.6902353e-06 | BH42: =+$Y41*P41 -> 1.2735852e-05 | ... BJ42: =+$Y41*R41 -> 0.00024727144 | BL42: =+C41*$Z41 -> 0 | BM42: =+D41*$Z41 -> 0 | BO42: =+F41*$Z41 -> 0 | BP42: =+G41*$Z41 -> 0 | BR42: =+I41*$Z41 -> 0 | BS42: =+J41*$Z41 -> 0 | BT42: =+K41*$Z41 -> 0 | BU42: =+L41*$Z41 -> 0 | BV42: =+M41*$Z41 -> 0 | BW42: =+N41*$Z41 -> 0 | BX42: =+O41*$Z41 -> 0 | BY42: =+P41*$Z41 -> 0 | ... CA42: =+R41*$Z41 -> 0 | CC42: =+C41*$AA41 -> 0 | CD42: =+D41*$AA41 -> 0 | CF42: =+F41*$AA41 -> 0 | CG42: =+G41*$AA41 -> 0 | CI42: =+I41*$AA41 -> 0 | CJ42: =+J41*$AA41 -> 0 | CK42: =+K41*$AA41 -> 0 | CL42: =+L41*$AA41 -> 0 | CM42: =+M41*$AA41 -> 0 | CN42: =+N41*$AA41 -> 0 | CO42: =+O41*$AA41 -> 0 | CP42: =+P41*$AA41 -> 0 | ... CR42: =+R41*$AA41 -> 0 | CT42: =+C41*$AB41 -> 0 | CU42: =+D41*$AB41 -> 0 | CW42: =+F41*$AB41 -> 0 | CX42: =+G41*$AB41 -> 0 | CZ42: =+I41*$AB41 -> 0 | DA42: =+J41*$AB41 -> 0 | DB42: =+K41*$AB41 -> 0 | DC42: =+L41*$AB41 -> 0 | DD42: =+M41*$AB41 -> 0 | DE42: =+N41*$AB41 -> 0 | DF42: =+O41*$AB41 -> 0 | DG42: =+P41*$AB41 -> 0 | ... DI42: =+R41*$AB41 -> 0
A43: =A42+1 -> 38 | B43: Rental & leasing and others | C43: 1.2754109 | D43: 1.6934186 | F43: 0.33949734 | G43: 0.45131508 | I43: 0.09608714 | J43: 0.12084735 | K43: 0.022264881 | L43: 0.030288358 | M43: 0.061744095 | N43: 0.072147257 | O43: 0.0023667457 | P43: 0.0032811989 | Q43: 0.0097114187 | R43: 0.015130541 | T43: =+F43/$W43 -> 1.397701 | U43: =+G43/$W43 -> 1.8580514 | W43: 0.24289697 | X43: =+'I-O'!BO40/'I-O'!BO$75 -> 0.0070652304 | Y43: =+'I-O'!BP40/'I-O'!BP$75 -> 0.049463339 | Z43: =+'I-O'!BT40/'I-O'!BT$75 -> 0.005576519 | AA43: =+'I-O'!BU40/'I-O'!BU$75 -> 2.1251125e-05 | AB43: =+'I-O'!BW40/'I-O'!BW$75 -> 5.0437964e-05 | AD43: =+C42*$X42 -> 0.058171142 | AE43: =+D42*$X42 -> 0.076509574 | AG43: =+F42*$X42 -> 0.014894099 | AH43: =+G42*$X42 -> 0.019799658 | AJ43: =+I42*$X42 -> 0.0049468844 | AK43: =+J42*$X42 -> 0.0060331405 | AL43: =+K42*$X42 -> 0.00097584466 | AM43: =+L42*$X42 -> 0.0013278429 | AN43: =+M42*$X42 -> 0.0028141363 | AO43: =+N42*$X42 -> 0.0032705338 | AP43: =+O42*$X42 -> 0.00011855717 | AQ43: =+P42*$X42 -> 0.00015867517 | ... AS43: =+R42*$X42 -> 0.0012760887 | AU43: =+$Y42*C42 -> 0.026725663 | AV43: =+$Y42*D42 -> 0.03515092 | AX43: =+$Y42*F42 -> 0.0068428202 | AY43: =+$Y42*G42 -> 0.0090965895 | BA43: =+$Y42*I42 -> 0.0022727552 | BB43: =+$Y42*J42 -> 0.0027718157 | BC43: =+$Y42*K42 -> 0.00044833392 | BD43: =+$Y42*L42 -> 0.00061005305 | BE43: =+$Y42*M42 -> 0.0012929033 | BF43: =+$Y42*N42 -> 0.0015025867 | BG43: =+$Y42*O42 -> 5.4468915e-05 | BH43: =+$Y42*P42 -> 7.2900395e-05 | ... BJ43: =+$Y42*R42 -> 0.00058627552 | BL43: =+C42*$Z42 -> 0.01864063 | BM43: =+D42*$Z42 -> 0.024517082 | BO43: =+F42*$Z42 -> 0.0047727338 | BP43: =+G42*$Z42 -> 0.006344694 | BR43: =+I42*$Z42 -> 0.0015852025 | BS43: =+J42*$Z42 -> 0.0019332874 | BT43: =+K42*$Z42 -> 0.00031270417 | BU43: =+L42*$Z42 -> 0.00042550012 | BV43: =+M42*$Z42 -> 0.00090177486 | BW43: =+N42*$Z42 -> 0.001048025 | BX43: =+O42*$Z42 -> 3.7991007e-05 | BY43: =+P42*$Z42 -> 5.0846606e-05 | ... CA43: =+R42*$Z42 -> 0.00040891575 | CC43: =+C42*$AA42 -> 2.4417672e-06 | CD43: =+D42*$AA42 -> 3.2115334e-06 | CF43: =+F42*$AA42 -> 6.2518837e-07 | CG43: =+G42*$AA42 -> 8.3110205e-07 | CI43: =+I42*$AA42 -> 2.0764832e-07 | CJ43: =+J42*$AA42 -> 2.5324455e-07 | CK43: =+K42*$AA42 -> 4.0961641e-08 | CL43: =+L42*$AA42 -> 5.573697e-08 | CM43: =+M42*$AA42 -> 1.1812499e-07 | CN43: =+N42*$AA42 -> 1.3728254e-07 | CO43: =+O42*$AA42 -> 4.9765054e-09 | CP43: =+P42*$AA42 -> 6.6604817e-09 | ... CR43: =+R42*$AA42 -> 5.3564557e-08 | CT43: =+C42*$AB42 -> 0.00014727211 | CU43: =+D42*$AB42 -> 0.00019369959 | CW43: =+F42*$AB42 -> 3.7707448e-05 | CX43: =+G42*$AB42 -> 5.0126872e-05 | CZ43: =+I42*$AB42 -> 1.2524047e-05 | DA43: =+J42*$AB42 -> 1.5274126e-05 | DB43: =+K42*$AB42 -> 2.4705498e-06 | DC43: =+L42*$AB42 -> 3.3617051e-06 | DD43: =+M42*$AB42 -> 7.12456e-06 | DE43: =+N42*$AB42 -> 8.2800233e-06 | DF43: =+O42*$AB42 -> 3.0015165e-07 | DG43: =+P42*$AB42 -> 4.0171856e-07 | ... DI43: =+R42*$AB42 -> 3.2306787e-06
A44: =A43+1 -> 39 | B44: Legal services | C44: 1.6827391 | D44: 2.4278698 | F44: 0.60517985 | G44: 0.80450348 | I44: 0.11150755 | J44: 0.15564451 | K44: 0.04285265 | L44: 0.05715511 | M44: 0.040395873 | N44: 0.058940301 | O44: 0.01225248 | P44: 0.013882562 | Q44: 0.016006543 | R44: 0.025666541 | T44: =+F44/$W44 -> 1.5057398 | U44: =+G44/$W44 -> 2.0016742 | W44: 0.40191529 | X44: =+'I-O'!BO41/'I-O'!BO$75 -> 0.012314235 | Y44: =+'I-O'!BP41/'I-O'!BP$75 -> 0 | Z44: =+'I-O'!BT41/'I-O'!BT$75 -> 0 | AA44: =+'I-O'!BU41/'I-O'!BU$75 -> 3.7465673e-07 | AB44: =+'I-O'!BW41/'I-O'!BW$75 -> 8.0664399e-06 | AD44: =+C43*$X43 -> 0.0090110715 | AE44: =+D43*$X43 -> 0.011964393 | AG44: =+F43*$X43 -> 0.0023986269 | AH44: =+G43*$X43 -> 0.003188645 | AJ44: =+I43*$X43 -> 0.00067887778 | AK44: =+J43*$X43 -> 0.0008538144 | AL44: =+K43*$X43 -> 0.00015730651 | AM44: =+L43*$X43 -> 0.00021399423 | AN44: =+M43*$X43 -> 0.00043623625 | AO44: =+N43*$X43 -> 0.00050973699 | AP44: =+O43*$X43 -> 1.6721604e-05 | AQ44: =+P43*$X43 -> 2.3182426e-05 | ... AS44: =+R43*$X43 -> 0.00010690076 | AU44: =+$Y43*C43 -> 0.063086079 | AV44: =+$Y43*D43 -> 0.083762139 | AX44: =+$Y43*F43 -> 0.016792672 | AY44: =+$Y43*G43 -> 0.02232355 | BA44: =+$Y43*I43 -> 0.0047527907 | BB44: =+$Y43*J43 -> 0.0059775136 | BC44: =+$Y43*K43 -> 0.0011012953 | BD44: =+$Y43*L43 -> 0.0014981633 | BE44: =+$Y43*M43 -> 0.0030540691 | BF44: =+$Y43*N43 -> 0.0035686442 | BG44: =+$Y43*O43 -> 0.00011706714 | BH44: =+$Y43*P43 -> 0.00016229905 | ... BJ44: =+$Y43*R43 -> 0.00074840706 | BL44: =+C43*$Z43 -> 0.0071123529 | BM44: =+D43*$Z43 -> 0.0094433812 | BO44: =+F43*$Z43 -> 0.0018932134 | BP44: =+G43*$Z43 -> 0.0025167671 | BR44: =+I43*$Z43 -> 0.00053583177 | BS44: =+J43*$Z43 -> 0.00067390758 | BT44: =+K43*$Z43 -> 0.00012416053 | BU44: =+L43*$Z43 -> 0.00016890361 | BV44: =+M43*$Z43 -> 0.00034431712 | BW44: =+N43*$Z43 -> 0.00040233055 | BX44: =+O43*$Z43 -> 1.3198202e-05 | BY44: =+P43*$Z43 -> 1.8297668e-05 | ... CA44: =+R43*$Z43 -> 8.4375749e-05 | CC44: =+C43*$AA43 -> 2.7103915e-05 | CD44: =+D43*$AA43 -> 3.5987051e-05 | CF44: =+F43*$AA43 -> 7.2147004e-06 | CG44: =+G43*$AA43 -> 9.5909531e-06 | CI44: =+I43*$AA43 -> 2.0419598e-06 | CJ44: =+J43*$AA43 -> 2.5681422e-06 | CK44: =+K43*$AA43 -> 4.7315376e-07 | CL44: =+L43*$AA43 -> 6.4366169e-07 | CM44: =+M43*$AA43 -> 1.3121315e-06 | CN44: =+N43*$AA43 -> 1.5332104e-06 | CO44: =+O43*$AA43 -> 5.0296009e-08 | CP44: =+P43*$AA43 -> 6.9729167e-08 | ... CR44: =+R43*$AA43 -> 3.2154101e-07 | CT44: =+C43*$AB43 -> 6.4329127e-05 | CU44: =+D43*$AB43 -> 8.5412588e-05 | CW44: =+F43*$AB43 -> 1.7123555e-05 | CX44: =+G43*$AB43 -> 2.2763414e-05 | CZ44: =+I43*$AB43 -> 4.8464397e-06 | DA44: =+J43*$AB43 -> 6.0952945e-06 | DB44: =+K43*$AB43 -> 1.1229953e-06 | DC44: =+L43*$AB43 -> 1.5276831e-06 | DD44: =+M43*$AB43 -> 3.1142464e-06 | DE44: =+N43*$AB43 -> 3.6389607e-06 | DF44: =+O43*$AB43 -> 1.1937383e-07 | DG44: =+P43*$AB43 -> 1.6549699e-07 | ... DI44: =+R43*$AB43 -> 7.6315368e-07
A45: =A44+1 -> 40 | B45: Architectural and engineering services | C45: 1.5996094 | D45: 2.3196113 | F45: 0.58477076 | G45: 0.77737239 | I45: 0.099691003 | J45: 0.1423395 | K45: 0.041663198 | L45: 0.055483321 | M45: 0.040000426 | N45: 0.057919461 | O45: 0.0019900351 | P45: 0.0035651445 | Q45: 0.016037344 | R45: 0.025371568 | T45: =+F45/$W45 -> 1.4549602 | U45: =+G45/$W45 -> 1.9341698 | W45: 0.40191529 | X45: =+'I-O'!BO42/'I-O'!BO$75 -> 0 | Y45: =+'I-O'!BP42/'I-O'!BP$75 -> 0 | Z45: =+'I-O'!BT42/'I-O'!BT$75 -> 0 | AA45: =+'I-O'!BU42/'I-O'!BU$75 -> 0.00024676228 | AB45: =+'I-O'!BW42/'I-O'!BW$75 -> 0.0031830164 | AD45: =+C44*$X44 -> 0.020721644 | AE45: =+D44*$X44 -> 0.029897358 | AG45: =+F44*$X44 -> 0.0074523267 | AH45: =+G44*$X44 -> 0.0099068446 | AJ45: =+I44*$X44 -> 0.0013731301 | AK45: =+J44*$X44 -> 0.0019166431 | AL45: =+K44*$X44 -> 0.00052769759 | AM45: =+L44*$X44 -> 0.00070382144 | AN45: =+M44*$X44 -> 0.00049744426 | AO45: =+N44*$X44 -> 0.0007258047 | AP45: =+O44*$X44 -> 0.00015087991 | AQ45: =+P44*$X44 -> 0.00017095313 | ... AS45: =+R44*$X44 -> 0.00031606381 | AU45: =+$Y44*C44 -> 0 | AV45: =+$Y44*D44 -> 0 | AX45: =+$Y44*F44 -> 0 | AY45: =+$Y44*G44 -> 0 | BA45: =+$Y44*I44 -> 0 | BB45: =+$Y44*J44 -> 0 | BC45: =+$Y44*K44 -> 0 | BD45: =+$Y44*L44 -> 0 | BE45: =+$Y44*M44 -> 0 | BF45: =+$Y44*N44 -> 0 | BG45: =+$Y44*O44 -> 0 | BH45: =+$Y44*P44 -> 0 | ... BJ45: =+$Y44*R44 -> 0 | BL45: =+C44*$Z44 -> 0 | BM45: =+D44*$Z44 -> 0 | BO45: =+F44*$Z44 -> 0 | BP45: =+G44*$Z44 -> 0 | BR45: =+I44*$Z44 -> 0 | BS45: =+J44*$Z44 -> 0 | BT45: =+K44*$Z44 -> 0 | BU45: =+L44*$Z44 -> 0 | BV45: =+M44*$Z44 -> 0 | BW45: =+N44*$Z44 -> 0 | BX45: =+O44*$Z44 -> 0 | BY45: =+P44*$Z44 -> 0 | ... CA45: =+R44*$Z44 -> 0 | CC45: =+C44*$AA44 -> 6.3044953e-07 | CD45: =+D44*$AA44 -> 9.0961774e-07 | CF45: =+F44*$AA44 -> 2.267347e-07 | CG45: =+G44*$AA44 -> 3.0141264e-07 | CI45: =+I44*$AA44 -> 4.1777052e-08 | CJ45: =+J44*$AA44 -> 5.8313264e-08 | CK45: =+K44*$AA44 -> 1.6055034e-08 | CL45: =+L44*$AA44 -> 2.1413546e-08 | CM45: =+M44*$AA44 -> 1.5134586e-08 | CN45: =+N44*$AA44 -> 2.208238e-08 | CO45: =+O44*$AA44 -> 4.590474e-09 | CP45: =+P44*$AA44 -> 5.2011954e-09 | ... CR45: =+R44*$AA44 -> 9.6161422e-09 | CT45: =+C44*$AB44 -> 1.3573714e-05 | CU45: =+D44*$AB44 -> 1.9584266e-05 | CW45: =+F44*$AB44 -> 4.8816469e-06 | CX45: =+G44*$AB44 -> 6.4894789e-06 | CZ45: =+I44*$AB44 -> 8.9946892e-07 | DA45: =+J44*$AB44 -> 1.2554971e-06 | DB45: =+K44*$AB44 -> 3.4566833e-07 | DC45: =+L44*$AB44 -> 4.6103826e-07 | DD45: =+M44*$AB44 -> 3.2585088e-07 | DE45: =+N44*$AB44 -> 4.754384e-07 | DF45: =+O44*$AB44 -> 9.8833894e-08 | DG45: =+P44*$AB44 -> 1.1198285e-07 | ... DI45: =+R44*$AB44 -> 2.0703761e-07
A46: =A45+1 -> 41 | B46: Computer systems design services | C46: 1.0896405 | D46: 1.6168268 | F46: 0.42816991 | G46: 0.56919308 | I46: 0.067028891 | J46: 0.098256173 | K46: 0.03095735 | L46: 0.041076462 | M46: 0.024966566 | N46: 0.038086907 | O46: 0.0012993875 | P46: 0.0024526846 | Q46: 0.0098055874 | R46: 0.016640118 | T46: =+F46/$W46 -> 1.0653238 | U46: =+G46/$W46 -> 1.4162016 | W46: 0.40191529 | X46: =+'I-O'!BO43/'I-O'!BO$75 -> 0 | Y46: =+'I-O'!BP43/'I-O'!BP$75 -> 0.0051226052 | Z46: =+'I-O'!BT43/'I-O'!BT$75 -> 0 | AA46: =+'I-O'!BU43/'I-O'!BU$75 -> 0 | AB46: =+'I-O'!BW43/'I-O'!BW$75 -> 0 | AD46: =+C45*$X45 -> 0 | AE46: =+D45*$X45 -> 0 | AG46: =+F45*$X45 -> 0 | AH46: =+G45*$X45 -> 0 | AJ46: =+I45*$X45 -> 0 | AK46: =+J45*$X45 -> 0 | AL46: =+K45*$X45 -> 0 | AM46: =+L45*$X45 -> 0 | AN46: =+M45*$X45 -> 0 | AO46: =+N45*$X45 -> 0 | AP46: =+O45*$X45 -> 0 | AQ46: =+P45*$X45 -> 0 | ... AS46: =+R45*$X45 -> 0 | AU46: =+$Y45*C45 -> 0 | AV46: =+$Y45*D45 -> 0 | AX46: =+$Y45*F45 -> 0 | AY46: =+$Y45*G45 -> 0 | BA46: =+$Y45*I45 -> 0 | BB46: =+$Y45*J45 -> 0 | BC46: =+$Y45*K45 -> 0 | BD46: =+$Y45*L45 -> 0 | BE46: =+$Y45*M45 -> 0 | BF46: =+$Y45*N45 -> 0 | BG46: =+$Y45*O45 -> 0 | BH46: =+$Y45*P45 -> 0 | ... BJ46: =+$Y45*R45 -> 0 | BL46: =+C45*$Z45 -> 0 | BM46: =+D45*$Z45 -> 0 | BO46: =+F45*$Z45 -> 0 | BP46: =+G45*$Z45 -> 0 | BR46: =+I45*$Z45 -> 0 | BS46: =+J45*$Z45 -> 0 | BT46: =+K45*$Z45 -> 0 | BU46: =+L45*$Z45 -> 0 | BV46: =+M45*$Z45 -> 0 | BW46: =+N45*$Z45 -> 0 | BX46: =+O45*$Z45 -> 0 | BY46: =+P45*$Z45 -> 0 | ... CA46: =+R45*$Z45 -> 0 | CC46: =+C45*$AA45 -> 0.00039472328 | CD46: =+D45*$AA45 -> 0.00057239259 | CF46: =+F45*$AA45 -> 0.00014429937 | CG46: =+G45*$AA45 -> 0.00019182619 | CI46: =+I45*$AA45 -> 2.459998e-05 | CJ46: =+J45*$AA45 -> 3.5124019e-05 | CK46: =+K45*$AA45 -> 1.0280906e-05 | CL46: =+L45*$AA45 -> 1.3691191e-05 | CM46: =+M45*$AA45 -> 9.8705964e-06 | CN46: =+N45*$AA45 -> 1.4292339e-05 | CO46: =+O45*$AA45 -> 4.910656e-07 | CP46: =+P45*$AA45 -> 8.7974321e-07 | ... CR46: =+R45*$AA45 -> 6.2607462e-06 | CT46: =+C45*$AB45 -> 0.0050915831 | CU46: =+D45*$AB45 -> 0.0073833608 | CW46: =+F45*$AB45 -> 0.0018613349 | CX46: =+G45*$AB45 -> 0.0024743891 | CZ46: =+I45*$AB45 -> 0.0003173181 | DA46: =+J45*$AB45 -> 0.00045306894 | DB46: =+K45*$AB45 -> 0.00013261464 | DC46: =+L45*$AB45 -> 0.00017660432 | DD46: =+M45*$AB45 -> 0.00012732201 | DE46: =+N45*$AB45 -> 0.00018435859 | DF46: =+O45*$AB45 -> 6.3343142e-06 | DG46: =+P45*$AB45 -> 1.1347913e-05 | ... DI46: =+R45*$AB45 -> 8.0758117e-05
A47: =A46+1 -> 42 | B47: R&D in the physical, engineering, & life sciences | C47: 1.4706667 | D47: 2.1318293 | F47: 0.53698272 | G47: 0.71384475 | I47: 0.087208129 | J47: 0.12637134 | K47: 0.03381565 | L47: 0.046506379 | M47: 0.03470436 | N47: 0.051159035 | O47: 0.0038310597 | P47: 0.0052774497 | Q47: 0.014857059 | R47: 0.023428481 | T47: =+F47/$W47 -> 1.3360595 | U47: =+G47/$W47 -> 1.7761075 | W47: 0.40191529 | X47: =+'I-O'!BO44/'I-O'!BO$75 -> 0 | Y47: =+'I-O'!BP44/'I-O'!BP$75 -> 0 | Z47: =+'I-O'!BT44/'I-O'!BT$75 -> 0 | AA47: =+'I-O'!BU44/'I-O'!BU$75 -> 0.031196134 | AB47: =+'I-O'!BW44/'I-O'!BW$75 -> 0.068818575 | AD47: =+C46*$X46 -> 0 | AE47: =+D46*$X46 -> 0 | AG47: =+F46*$X46 -> 0 | AH47: =+G46*$X46 -> 0 | AJ47: =+I46*$X46 -> 0 | AK47: =+J46*$X46 -> 0 | AL47: =+K46*$X46 -> 0 | AM47: =+L46*$X46 -> 0 | AN47: =+M46*$X46 -> 0 | AO47: =+N46*$X46 -> 0 | AP47: =+O46*$X46 -> 0 | AQ47: =+P46*$X46 -> 0 | ... AS47: =+R46*$X46 -> 0 | AU47: =+$Y46*C46 -> 0.0055817982 | AV47: =+$Y46*D46 -> 0.0082823656 | AX47: =+$Y46*F46 -> 0.0021933454 | AY47: =+$Y46*G46 -> 0.0029157514 | BA47: =+$Y46*I46 -> 0.00034336255 | BB47: =+$Y46*J46 -> 0.00050332758 | BC47: =+$Y46*K46 -> 0.00015858228 | BD47: =+$Y46*L46 -> 0.0002104185 | BE47: =+$Y46*M46 -> 0.00012789386 | BF47: =+$Y46*N46 -> 0.00019510419 | BG47: =+$Y46*O46 -> 6.656249e-06 | BH47: =+$Y46*P46 -> 1.2564135e-05 | ... BJ47: =+$Y46*R46 -> 8.5240757e-05 | BL47: =+C46*$Z46 -> 0 | BM47: =+D46*$Z46 -> 0 | BO47: =+F46*$Z46 -> 0 | BP47: =+G46*$Z46 -> 0 | BR47: =+I46*$Z46 -> 0 | BS47: =+J46*$Z46 -> 0 | BT47: =+K46*$Z46 -> 0 | BU47: =+L46*$Z46 -> 0 | BV47: =+M46*$Z46 -> 0 | BW47: =+N46*$Z46 -> 0 | BX47: =+O46*$Z46 -> 0 | BY47: =+P46*$Z46 -> 0 | ... CA47: =+R46*$Z46 -> 0 | CC47: =+C46*$AA46 -> 0 | CD47: =+D46*$AA46 -> 0 | CF47: =+F46*$AA46 -> 0 | CG47: =+G46*$AA46 -> 0 | CI47: =+I46*$AA46 -> 0 | CJ47: =+J46*$AA46 -> 0 | CK47: =+K46*$AA46 -> 0 | CL47: =+L46*$AA46 -> 0 | CM47: =+M46*$AA46 -> 0 | CN47: =+N46*$AA46 -> 0 | CO47: =+O46*$AA46 -> 0 | CP47: =+P46*$AA46 -> 0 | ... CR47: =+R46*$AA46 -> 0 | CT47: =+C46*$AB46 -> 0 | CU47: =+D46*$AB46 -> 0 | CW47: =+F46*$AB46 -> 0 | CX47: =+G46*$AB46 -> 0 | CZ47: =+I46*$AB46 -> 0 | DA47: =+J46*$AB46 -> 0 | DB47: =+K46*$AB46 -> 0 | DC47: =+L46*$AB46 -> 0 | DD47: =+M46*$AB46 -> 0 | DE47: =+N46*$AB46 -> 0 | DF47: =+O46*$AB46 -> 0 | DG47: =+P46*$AB46 -> 0 | ... DI47: =+R46*$AB46 -> 0
A48: =A47+1 -> 43 | B48: Other professional services | C48: 1.6171634 | D48: 2.3443143 | F48: 0.59057705 | G48: 0.78509105 | I48: 0.10068985 | J48: 0.14376181 | K48: 0.040914547 | L48: 0.054871892 | M48: 0.037579736 | N48: 0.055676693 | O48: 0.0071982443 | P48: 0.0087889933 | Q48: 0.014997326 | R48: 0.024424231 | T48: =+F48/$W48 -> 1.4694068 | U48: =+G48/$W48 -> 1.9533745 | W48: 0.40191529 | X48: =+'I-O'!BO45/'I-O'!BO$75 -> 0.011846377 | Y48: =+'I-O'!BP45/'I-O'!BP$75 -> 0.0018610495 | Z48: =+'I-O'!BT45/'I-O'!BT$75 -> 0.0015463365 | AA48: =+'I-O'!BU45/'I-O'!BU$75 -> 0.00080961998 | AB48: =+'I-O'!BW45/'I-O'!BW$75 -> 0.0076181037 | AD48: =+C47*$X47 -> 0 | AE48: =+D47*$X47 -> 0 | AG48: =+F47*$X47 -> 0 | AH48: =+G47*$X47 -> 0 | AJ48: =+I47*$X47 -> 0 | AK48: =+J47*$X47 -> 0 | AL48: =+K47*$X47 -> 0 | AM48: =+L47*$X47 -> 0 | AN48: =+M47*$X47 -> 0 | AO48: =+N47*$X47 -> 0 | AP48: =+O47*$X47 -> 0 | AQ48: =+P47*$X47 -> 0 | ... AS48: =+R47*$X47 -> 0 | AU48: =+$Y47*C47 -> 0 | AV48: =+$Y47*D47 -> 0 | AX48: =+$Y47*F47 -> 0 | AY48: =+$Y47*G47 -> 0 | BA48: =+$Y47*I47 -> 0 | BB48: =+$Y47*J47 -> 0 | BC48: =+$Y47*K47 -> 0 | BD48: =+$Y47*L47 -> 0 | BE48: =+$Y47*M47 -> 0 | BF48: =+$Y47*N47 -> 0 | BG48: =+$Y47*O47 -> 0 | BH48: =+$Y47*P47 -> 0 | ... BJ48: =+$Y47*R47 -> 0 | BL48: =+C47*$Z47 -> 0 | BM48: =+D47*$Z47 -> 0 | BO48: =+F47*$Z47 -> 0 | BP48: =+G47*$Z47 -> 0 | BR48: =+I47*$Z47 -> 0 | BS48: =+J47*$Z47 -> 0 | BT48: =+K47*$Z47 -> 0 | BU48: =+L47*$Z47 -> 0 | BV48: =+M47*$Z47 -> 0 | BW48: =+N47*$Z47 -> 0 | BX48: =+O47*$Z47 -> 0 | BY48: =+P47*$Z47 -> 0 | ... CA48: =+R47*$Z47 -> 0 | CC48: =+C47*$AA47 -> 0.045879115 | CD48: =+D47*$AA47 -> 0.066504832 | CF48: =+F47*$AA47 -> 0.016751785 | CG48: =+G47*$AA47 -> 0.022269197 | CI48: =+I47*$AA47 -> 0.0027205565 | CJ48: =+J47*$AA47 -> 0.0039422974 | CK48: =+K47*$AA47 -> 0.0010549176 | CL48: =+L47*$AA47 -> 0.0014508192 | CM48: =+M47*$AA47 -> 0.0010826419 | CN48: =+N47*$AA47 -> 0.0015959641 | CO48: =+O47*$AA47 -> 0.00011951425 | CP48: =+P47*$AA47 -> 0.00016463603 | ... CR48: =+R47*$AA47 -> 0.00073087805 | CT48: =+C47*$AB47 -> 0.10120918 | CU48: =+D47*$AB47 -> 0.14670945 | CW48: =+F47*$AB47 -> 0.036954386 | CX48: =+G47*$AB47 -> 0.049125779 | CZ48: =+I47*$AB47 -> 0.0060015392 | DA48: =+J47*$AB47 -> 0.0086966959 | DB48: =+K47*$AB47 -> 0.0023271448 | DC48: =+L47*$AB47 -> 0.0032005027 | DD48: =+M47*$AB47 -> 0.0023883046 | DE48: =+N47*$AB47 -> 0.0035206919 | DF48: =+O47*$AB47 -> 0.00026364807 | DG48: =+P47*$AB47 -> 0.00036318657 | ... DI48: =+R47*$AB47 -> 0.0016123147
A49: =A48+1 -> 44 | B49: Management of companies and enterprises | C49: 1.3571027 | D49: 2.1548652 | F49: 0.64792639 | G49: 0.86132913 | I49: 0.097204103 | J49: 0.14445866 | K49: 0.050236151 | L49: 0.065548857 | M49: 0.03240405 | N49: 0.052258353 | O49: 0.00099192365 | P49: 0.002737146 | Q49: 0.013571978 | R49: 0.023914305 | T49: =+F49/$W49 -> 1.2209162 | U49: =+G49/$W49 -> 1.6230404 | W49: 0.53068867 | X49: =+'I-O'!BO46/'I-O'!BO$75 -> 0 | Y49: =+'I-O'!BP46/'I-O'!BP$75 -> 0 | Z49: =+'I-O'!BT46/'I-O'!BT$75 -> 0 | AA49: =+'I-O'!BU46/'I-O'!BU$75 -> 0 | AB49: =+'I-O'!BW46/'I-O'!BW$75 -> 0 | AD49: =+C48*$X48 -> 0.019157527 | AE49: =+D48*$X48 -> 0.027771631 | AG49: =+F48*$X48 -> 0.0069961984 | AH49: =+G48*$X48 -> 0.0093004846 | AJ49: =+I48*$X48 -> 0.00119281 | AK49: =+J48*$X48 -> 0.0017030566 | AL49: =+K48*$X48 -> 0.00048468914 | AM49: =+L48*$X48 -> 0.00065003312 | AN49: =+M48*$X48 -> 0.00044518373 | AO49: =+N48*$X48 -> 0.0006595671 | AP49: =+O48*$X48 -> 8.5273116e-05 | AQ49: =+P48*$X48 -> 0.00010411773 | ... AS49: =+R48*$X48 -> 0.00028933865 | AU49: =+$Y48*C48 -> 0.0030096211 | AV49: =+$Y48*D48 -> 0.0043628849 | AX49: =+$Y48*F48 -> 0.0010990931 | AY49: =+$Y48*G48 -> 0.0014610933 | BA49: =+$Y48*I48 -> 0.0001873888 | BB49: =+$Y48*J48 -> 0.00026754784 | BC49: =+$Y48*K48 -> 7.6143996e-05 | BD49: =+$Y48*L48 -> 0.00010211931 | BE49: =+$Y48*M48 -> 6.993775e-05 | BF49: =+$Y48*N48 -> 0.00010361708 | BG49: =+$Y48*O48 -> 1.3396289e-05 | BH49: =+$Y48*P48 -> 1.6356752e-05 | ... BJ49: =+$Y48*R48 -> 4.5454703e-05 | BL49: =+C48*$Z48 -> 0.0025006787 | BM49: =+D48*$Z48 -> 0.0036250986 | BO49: =+F48*$Z48 -> 0.00091323082 | BP49: =+G48*$Z48 -> 0.0012140149 | BR49: =+I48*$Z48 -> 0.00015570039 | BS49: =+J48*$Z48 -> 0.00022230413 | BT49: =+K48*$Z48 -> 6.3267655e-05 | BU49: =+L48*$Z48 -> 8.4850407e-05 | BV49: =+M48*$Z48 -> 5.8110916e-05 | BW49: =+N48*$Z48 -> 8.60949e-05 | BX49: =+O48*$Z48 -> 1.1130908e-05 | BY49: =+P48*$Z48 -> 1.3590741e-05 | ... CA49: =+R48*$Z48 -> 3.7768079e-05 | CC49: =+C48*$AA48 -> 0.0013092878 | CD49: =+D48*$AA48 -> 0.0018980037 | CF49: =+F48*$AA48 -> 0.00047814298 | CG49: =+G48*$AA48 -> 0.0006356254 | CI49: =+I48*$AA48 -> 8.1520517e-05 | CJ49: =+J48*$AA48 -> 0.00011639243 | CK49: =+K48*$AA48 -> 3.3125234e-05 | CL49: =+L48*$AA48 -> 4.442538e-05 | CM49: =+M48*$AA48 -> 3.0425305e-05 | CN49: =+N48*$AA48 -> 4.5076963e-05 | CO49: =+O48*$AA48 -> 5.8278424e-06 | CP49: =+P48*$AA48 -> 7.1157446e-06 | ... CR49: =+R48*$AA48 -> 1.9774345e-05 | CT49: =+C48*$AB48 -> 0.012319718 | CU49: =+D48*$AB48 -> 0.017859229 | CW49: =+F48*$AB48 -> 0.0044990772 | CX49: =+G48*$AB48 -> 0.005980905 | CZ49: =+I48*$AB48 -> 0.00076706574 | DA49: =+J48*$AB48 -> 0.0010951924 | DB49: =+K48*$AB48 -> 0.00031169126 | DC49: =+L48*$AB48 -> 0.00041801976 | DD49: =+M48*$AB48 -> 0.00028628633 | DE49: =+N48*$AB48 -> 0.00042415082 | DF49: =+O48*$AB48 -> 5.4836971e-05 | DG49: =+P48*$AB48 -> 6.6955462e-05 | ... DI49: =+R48*$AB48 -> 0.00018606632
A50: =A49+1 -> 45 | B50: Travel arrangement and reservation services | C50: 1.2316069 | D50: 2.0513585 | F50: 0.66578548 | G50: 0.88507033 | I50: 0.082282795 | J50: 0.13083985 | K50: 0.042343446 | L50: 0.058078223 | M50: 0.027783923 | N50: 0.04818548 | O50: 0.0017849651 | P50: 0.0035782917 | Q50: 0.010370461 | R50: 0.020997857 | T50: =+F50/$W50 -> 1.1192 | U50: =+G50/$W50 -> 1.4878227 | W50: 0.59487622 | X50: =+'I-O'!BO47/'I-O'!BO$75 -> 0.0018213756 | Y50: =+'I-O'!BP47/'I-O'!BP$75 -> 0.01359017 | Z50: =+'I-O'!BT47/'I-O'!BT$75 -> 0 | AA50: =+'I-O'!BU47/'I-O'!BU$75 -> 0 | AB50: =+'I-O'!BW47/'I-O'!BW$75 -> 0 | AD50: =+C49*$X49 -> 0 | AE50: =+D49*$X49 -> 0 | AG50: =+F49*$X49 -> 0 | AH50: =+G49*$X49 -> 0 | AJ50: =+I49*$X49 -> 0 | AK50: =+J49*$X49 -> 0 | AL50: =+K49*$X49 -> 0 | AM50: =+L49*$X49 -> 0 | AN50: =+M49*$X49 -> 0 | AO50: =+N49*$X49 -> 0 | AP50: =+O49*$X49 -> 0 | AQ50: =+P49*$X49 -> 0 | ... AS50: =+R49*$X49 -> 0 | AU50: =+$Y49*C49 -> 0 | AV50: =+$Y49*D49 -> 0 | AX50: =+$Y49*F49 -> 0 | AY50: =+$Y49*G49 -> 0 | BA50: =+$Y49*I49 -> 0 | BB50: =+$Y49*J49 -> 0 | BC50: =+$Y49*K49 -> 0 | BD50: =+$Y49*L49 -> 0 | BE50: =+$Y49*M49 -> 0 | BF50: =+$Y49*N49 -> 0 | BG50: =+$Y49*O49 -> 0 | BH50: =+$Y49*P49 -> 0 | ... BJ50: =+$Y49*R49 -> 0 | BL50: =+C49*$Z49 -> 0 | BM50: =+D49*$Z49 -> 0 | BO50: =+F49*$Z49 -> 0 | BP50: =+G49*$Z49 -> 0 | BR50: =+I49*$Z49 -> 0 | BS50: =+J49*$Z49 -> 0 | BT50: =+K49*$Z49 -> 0 | BU50: =+L49*$Z49 -> 0 | BV50: =+M49*$Z49 -> 0 | BW50: =+N49*$Z49 -> 0 | BX50: =+O49*$Z49 -> 0 | BY50: =+P49*$Z49 -> 0 | ... CA50: =+R49*$Z49 -> 0 | CC50: =+C49*$AA49 -> 0 | CD50: =+D49*$AA49 -> 0 | CF50: =+F49*$AA49 -> 0 | CG50: =+G49*$AA49 -> 0 | CI50: =+I49*$AA49 -> 0 | CJ50: =+J49*$AA49 -> 0 | CK50: =+K49*$AA49 -> 0 | CL50: =+L49*$AA49 -> 0 | CM50: =+M49*$AA49 -> 0 | CN50: =+N49*$AA49 -> 0 | CO50: =+O49*$AA49 -> 0 | CP50: =+P49*$AA49 -> 0 | ... CR50: =+R49*$AA49 -> 0 | CT50: =+C49*$AB49 -> 0 | CU50: =+D49*$AB49 -> 0 | CW50: =+F49*$AB49 -> 0 | CX50: =+G49*$AB49 -> 0 | CZ50: =+I49*$AB49 -> 0 | DA50: =+J49*$AB49 -> 0 | DB50: =+K49*$AB49 -> 0 | DC50: =+L49*$AB49 -> 0 | DD50: =+M49*$AB49 -> 0 | DE50: =+N49*$AB49 -> 0 | DF50: =+O49*$AB49 -> 0 | DG50: =+P49*$AB49 -> 0 | ... DI50: =+R49*$AB49 -> 0
A51: =A50+1 -> 46 | B51: Administrative and support services | C51: 1.2295735 | D51: 2.0519027 | F51: 0.66787897 | G51: 0.88785334 | I51: 0.088833562 | J51: 0.1375433 | K51: 0.046553094 | L51: 0.062337347 | M51: 0.028800022 | N51: 0.049265729 | O51: 0.0017828773 | P51: 0.0035818429 | Q51: 0.011697568 | R51: 0.022358381 | T51: =+F51/$W51 -> 1.1227192 | U51: =+G51/$W51 -> 1.492501 | W51: 0.59487622 | X51: =+'I-O'!BO48/'I-O'!BO$75 -> 0.0090175319 | Y51: =+'I-O'!BP48/'I-O'!BP$75 -> 0.0056970354 | Z51: =+'I-O'!BT48/'I-O'!BT$75 -> 0 | AA51: =+'I-O'!BU48/'I-O'!BU$75 -> 0.0065131931 | AB51: =+'I-O'!BW48/'I-O'!BW$75 -> 0.0050359071 | AD51: =+C50*$X50 -> 0.0022432187 | AE51: =+D50*$X50 -> 0.0037362944 | AG51: =+F50*$X50 -> 0.0012126454 | AH51: =+G50*$X50 -> 0.0016120455 | AJ51: =+I50*$X50 -> 0.00014986788 | AK51: =+J50*$X50 -> 0.00023830852 | AL51: =+K50*$X50 -> 7.712332e-05 | AM51: =+L50*$X50 -> 0.00010578226 | AN51: =+M50*$X50 -> 5.0604961e-05 | AO51: =+N50*$X50 -> 8.7763858e-05 | AP51: =+O50*$X50 -> 3.2510919e-06 | AQ51: =+P50*$X50 -> 6.5174133e-06 | ... AS51: =+R50*$X50 -> 3.8244985e-05 | AU51: =+$Y50*C50 -> 0.016737747 | AV51: =+$Y50*D50 -> 0.027878311 | AX51: =+$Y50*F50 -> 0.0090481378 | AY51: =+$Y50*G50 -> 0.012028256 | BA51: =+$Y50*I50 -> 0.0011182372 | BB51: =+$Y50*J50 -> 0.0017781358 | BC51: =+$Y50*K50 -> 0.00057545463 | BD51: =+$Y50*L50 -> 0.00078929292 | BE51: =+$Y50*M50 -> 0.00037758824 | BF51: =+$Y50*N50 -> 0.00065484886 | BG51: =+$Y50*O50 -> 2.4257979e-05 | BH51: =+$Y50*P50 -> 4.8629593e-05 | ... BJ51: =+$Y50*R50 -> 0.00028536445 | BL51: =+C50*$Z50 -> 0 | BM51: =+D50*$Z50 -> 0 | BO51: =+F50*$Z50 -> 0 | BP51: =+G50*$Z50 -> 0 | BR51: =+I50*$Z50 -> 0 | BS51: =+J50*$Z50 -> 0 | BT51: =+K50*$Z50 -> 0 | BU51: =+L50*$Z50 -> 0 | BV51: =+M50*$Z50 -> 0 | BW51: =+N50*$Z50 -> 0 | BX51: =+O50*$Z50 -> 0 | BY51: =+P50*$Z50 -> 0 | ... CA51: =+R50*$Z50 -> 0 | CC51: =+C50*$AA50 -> 0 | CD51: =+D50*$AA50 -> 0 | CF51: =+F50*$AA50 -> 0 | CG51: =+G50*$AA50 -> 0 | CI51: =+I50*$AA50 -> 0 | CJ51: =+J50*$AA50 -> 0 | CK51: =+K50*$AA50 -> 0 | CL51: =+L50*$AA50 -> 0 | CM51: =+M50*$AA50 -> 0 | CN51: =+N50*$AA50 -> 0 | CO51: =+O50*$AA50 -> 0 | CP51: =+P50*$AA50 -> 0 | ... CR51: =+R50*$AA50 -> 0 | CT51: =+C50*$AB50 -> 0 | CU51: =+D50*$AB50 -> 0 | CW51: =+F50*$AB50 -> 0 | CX51: =+G50*$AB50 -> 0 | CZ51: =+I50*$AB50 -> 0 | DA51: =+J50*$AB50 -> 0 | DB51: =+K50*$AB50 -> 0 | DC51: =+L50*$AB50 -> 0 | DD51: =+M50*$AB50 -> 0 | DE51: =+N50*$AB50 -> 0 | DF51: =+O50*$AB50 -> 0 | DG51: =+P50*$AB50 -> 0 | ... DI51: =+R50*$AB50 -> 0
A52: =A51+1 -> 47 | B52: Waste management and remediation services | C52: 1.5621899 | D52: 2.12704 | F52: 0.45875962 | G52: 0.60985789 | I52: 0.083089538 | J52: 0.11654779 | K52: 0.034259962 | L52: 0.045102013 | M52: 0.032292499 | N52: 0.046350196 | O52: 0.0029325148 | P52: 0.0041682069 | Q52: 0.013604561 | R52: 0.020927371 | T52: =+F52/$W52 -> 1.7283784 | U52: =+G52/$W52 -> 2.2976417 | W52: 0.26542777 | X52: =+'I-O'!BO49/'I-O'!BO$75 -> 0.0010504811 | Y52: =+'I-O'!BP49/'I-O'!BP$75 -> 0 | Z52: =+'I-O'!BT49/'I-O'!BT$75 -> 0 | AA52: =+'I-O'!BU49/'I-O'!BU$75 -> 0.0031373114 | AB52: =+'I-O'!BW49/'I-O'!BW$75 -> 0.0019523707 | AD52: =+C51*$X51 -> 0.011087718 | AE52: =+D51*$X51 -> 0.018503098 | AG52: =+F51*$X51 -> 0.0060226199 | AH52: =+G51*$X51 -> 0.0080062458 | AJ52: =+I51*$X51 -> 0.00080105948 | AK52: =+J51*$X51 -> 0.0012403011 | AL52: =+K51*$X51 -> 0.00041979401 | AM52: =+L51*$X51 -> 0.00056212902 | AN52: =+M51*$X51 -> 0.00025970512 | AO52: =+N51*$X51 -> 0.00044425529 | AP52: =+O51*$X51 -> 1.6077153e-05 | AQ52: =+P51*$X51 -> 3.2299383e-05 | ... AS52: =+R51*$X51 -> 0.00020161742 | AU52: =+$Y51*C51 -> 0.0070049235 | AV52: =+$Y51*D51 -> 0.011689762 | AX52: =+$Y51*F51 -> 0.0038049301 | AY52: =+$Y51*G51 -> 0.0050581319 | BA52: =+$Y51*I51 -> 0.00050608795 | BB52: =+$Y51*J51 -> 0.00078358906 | BC52: =+$Y51*K51 -> 0.00026521463 | BD52: =+$Y51*L51 -> 0.00035513807 | BE52: =+$Y51*M51 -> 0.00016407475 | BF52: =+$Y51*N51 -> 0.00028066861 | BG52: =+$Y51*O51 -> 1.0157115e-05 | BH52: =+$Y51*P51 -> 2.0405886e-05 | ... BJ52: =+$Y51*R51 -> 0.00012737649 | BL52: =+C51*$Z51 -> 0 | BM52: =+D51*$Z51 -> 0 | BO52: =+F51*$Z51 -> 0 | BP52: =+G51*$Z51 -> 0 | BR52: =+I51*$Z51 -> 0 | BS52: =+J51*$Z51 -> 0 | BT52: =+K51*$Z51 -> 0 | BU52: =+L51*$Z51 -> 0 | BV52: =+M51*$Z51 -> 0 | BW52: =+N51*$Z51 -> 0 | BX52: =+O51*$Z51 -> 0 | BY52: =+P51*$Z51 -> 0 | ... CA52: =+R51*$Z51 -> 0 | CC52: =+C51*$AA51 -> 0.0080084493 | CD52: =+D51*$AA51 -> 0.013364439 | CF52: =+F51*$AA51 -> 0.0043500247 | CG52: =+G51*$AA51 -> 0.0057827602 | CI52: =+I51*$AA51 -> 0.00057859014 | CJ52: =+J51*$AA51 -> 0.00089584607 | CK52: =+K51*$AA51 -> 0.00030320929 | CL52: =+L51*$AA51 -> 0.00040601518 | CM52: =+M51*$AA51 -> 0.00018758011 | CN52: =+N51*$AA51 -> 0.00032087721 | CO52: =+O51*$AA51 -> 1.1612224e-05 | CP52: =+P51*$AA51 -> 2.3329234e-05 | ... CR52: =+R51*$AA51 -> 0.00014562445 | CT52: =+C51*$AB51 -> 0.0061920177 | CU52: =+D51*$AB51 -> 0.010333192 | CW52: =+F51*$AB51 -> 0.0033633764 | CX52: =+G51*$AB51 -> 0.0044711469 | CZ52: =+I51*$AB51 -> 0.00044735757 | DA52: =+J51*$AB51 -> 0.00069265529 | DB52: =+K51*$AB51 -> 0.00023443706 | DC52: =+L51*$AB51 -> 0.00031392509 | DD52: =+M51*$AB51 -> 0.00014503424 | DE52: =+N51*$AB51 -> 0.00024809764 | DF52: =+O51*$AB51 -> 8.9784046e-06 | DG52: =+P51*$AB51 -> 1.8037828e-05 | ... DI52: =+R51*$AB51 -> 0.00011259473
A53: =A52+1 -> 48 | B53: Colleges, universities, and professional schools | C53: 1.0525687 | D53: 1.4647983 | F53: 0.3348045 | G53: 0.44507659 | I53: 0.062413171 | J53: 0.086831128 | K53: 0.027500666 | L53: 0.035413236 | M53: 0.024250551 | N53: 0.034509911 | O53: 0.00038672429 | P53: 0.0012885371 | Q53: 0.01027523 | R53: 0.015619444 | T53: =+F53/$W53 -> 1.0486854 | U53: =+G53/$W53 -> 1.3940832 | W53: 0.31926114 | X53: =+'I-O'!BO50/'I-O'!BO$75 -> 0.0074792315 | Y53: =+'I-O'!BP50/'I-O'!BP$75 -> 0.0074834662 | Z53: =+'I-O'!BT50/'I-O'!BT$75 -> 0 | AA53: =+'I-O'!BU50/'I-O'!BU$75 -> 2.8176699e-05 | AB53: =+'I-O'!BW50/'I-O'!BW$75 -> 0 | AD53: =+C52*$X52 -> 0.0016410509 | AE53: =+D52*$X52 -> 0.0022344152 | AG53: =+F52*$X52 -> 0.0004819183 | AH53: =+G52*$X52 -> 0.00064064417 | AJ53: =+I52*$X52 -> 8.7283986e-05 | AK53: =+J52*$X52 -> 0.00012243124 | AL53: =+K52*$X52 -> 3.5989442e-05 | AM53: =+L52*$X52 -> 4.7378811e-05 | AN53: =+M52*$X52 -> 3.3922659e-05 | AO53: =+N52*$X52 -> 4.8690003e-05 | AP53: =+O52*$X52 -> 3.0805512e-06 | AQ53: =+P52*$X52 -> 4.3786224e-06 | ... AS53: =+R52*$X52 -> 2.1983807e-05 | AU53: =+$Y52*C52 -> 0 | AV53: =+$Y52*D52 -> 0 | AX53: =+$Y52*F52 -> 0 | AY53: =+$Y52*G52 -> 0 | BA53: =+$Y52*I52 -> 0 | BB53: =+$Y52*J52 -> 0 | BC53: =+$Y52*K52 -> 0 | BD53: =+$Y52*L52 -> 0 | BE53: =+$Y52*M52 -> 0 | BF53: =+$Y52*N52 -> 0 | BG53: =+$Y52*O52 -> 0 | BH53: =+$Y52*P52 -> 0 | ... BJ53: =+$Y52*R52 -> 0 | BL53: =+C52*$Z52 -> 0 | BM53: =+D52*$Z52 -> 0 | BO53: =+F52*$Z52 -> 0 | BP53: =+G52*$Z52 -> 0 | BR53: =+I52*$Z52 -> 0 | BS53: =+J52*$Z52 -> 0 | BT53: =+K52*$Z52 -> 0 | BU53: =+L52*$Z52 -> 0 | BV53: =+M52*$Z52 -> 0 | BW53: =+N52*$Z52 -> 0 | BX53: =+O52*$Z52 -> 0 | BY53: =+P52*$Z52 -> 0 | ... CA53: =+R52*$Z52 -> 0 | CC53: =+C52*$AA52 -> 0.0049010763 | CD53: =+D52*$AA52 -> 0.0066731868 | CF53: =+F52*$AA52 -> 0.0014392718 | CG53: =+G52*$AA52 -> 0.0019133141 | CI53: =+I52*$AA52 -> 0.00026067776 | CJ53: =+J52*$AA52 -> 0.0003656467 | CK53: =+K52*$AA52 -> 0.00010748417 | CL53: =+L52*$AA52 -> 0.00014149906 | CM53: =+M52*$AA52 -> 0.00010131163 | CN53: =+N52*$AA52 -> 0.000145415 | CO53: =+O52*$AA52 -> 9.2002121e-06 | CP53: =+P52*$AA52 -> 1.3076963e-05 | ... CR53: =+R52*$AA52 -> 6.565568e-05 | CT53: =+C52*$AB52 -> 0.0030499738 | CU53: =+D52*$AB52 -> 0.0041527704 | CW53: =+F52*$AB52 -> 0.00089566882 | CX53: =+G52*$AB52 -> 0.0011906687 | CZ53: =+I52*$AB52 -> 0.00016222157 | DA53: =+J52*$AB52 -> 0.00022754448 | DB53: =+K52*$AB52 -> 6.6888145e-05 | DC53: =+L52*$AB52 -> 8.8055848e-05 | DD53: =+M52*$AB52 -> 6.3046928e-05 | DE53: =+N52*$AB52 -> 9.0492762e-05 | DF53: =+O52*$AB52 -> 5.7253558e-06 | DG53: =+P52*$AB52 -> 8.1378848e-06 | ... DI53: =+R52*$AB52 -> 4.0857985e-05
... A67: =A66+1 -> 62 | B67: State and local government | C67: 1.0213749 | D67: 1.7694974 | F67: 0.60760978 | G67: 0.80773373 | I67: 0.05913851 | J67: 0.1034527 | K67: 0.049019591 | L67: 0.063379478 | M67: 0.00045820863 | N67: 0.019077097 | O67: 0.00016977664 | P67: 0.0018064041 | Q67: 0.009490934 | R67: 0.019189719 | T67: =+F67/$W67 -> 1.0109059 | U67: =+G67/$W67 -> 1.3438605 | W67: 0.60105476 | X67: =+'I-O'!BO64/'I-O'!BO$75 -> 0.070708724 | Y67: =+'I-O'!BP64/'I-O'!BP$75 -> 0.0044181299 | Z67: =+'I-O'!BT64/'I-O'!BT$75 -> 0.21514284 | AA67: =+'I-O'!BU64/'I-O'!BU$75 -> 1.2549282e-05 | AB67: =+'I-O'!BW64/'I-O'!BW$75 -> 0.010267109 | AD67: =+C66*$X66 -> 0.008332423 | AE67: =+D66*$X66 -> 0.013687696 | AG67: =+F66*$X66 -> 0.004349443 | AH67: =+G66*$X66 -> 0.005781987 | AJ67: =+I66*$X66 -> 0.00050083802 | AK67: =+J66*$X66 -> 0.00081805154 | AL67: =+K66*$X66 -> 0.00040032606 | AM67: =+L66*$X66 -> 0.0005031182 | AN67: =+M66*$X66 -> 1.4080434e-05 | AO67: =+N66*$X66 -> 0.00014735971 | AP67: =+O66*$X66 -> 2.4478487e-06 | AQ67: =+P66*$X66 -> 1.4163292e-05 | ... AS67: =+R66*$X66 -> 0.00015341033 | AU67: =+$Y66*C66 -> 0.0038109601 | AV67: =+$Y66*D66 -> 0.0062602755 | AX67: =+$Y66*F66 -> 0.0019892838 | AY67: =+$Y66*G66 -> 0.0026444795 | BA67: =+$Y66*I66 -> 0.00022906587 | BB67: =+$Y66*J66 -> 0.00037414828 | BC67: =+$Y66*K66 -> 0.0001830952 | BD67: =+$Y66*L66 -> 0.00023010874 | BE67: =+$Y66*M66 -> 6.4399001e-06 | BF67: =+$Y66*N66 -> 6.73972e-05 | BG67: =+$Y66*O66 -> 1.1195607e-06 | BH67: =+$Y66*P66 -> 6.4777966e-06 | ... BJ67: =+$Y66*R66 -> 7.0164544e-05 | BL67: =+C66*$Z66 -> 0 | BM67: =+D66*$Z66 -> 0 | BO67: =+F66*$Z66 -> 0 | BP67: =+G66*$Z66 -> 0 | BR67: =+I66*$Z66 -> 0 | BS67: =+J66*$Z66 -> 0 | BT67: =+K66*$Z66 -> 0 | BU67: =+L66*$Z66 -> 0 | BV67: =+M66*$Z66 -> 0 | BW67: =+N66*$Z66 -> 0 | BX67: =+O66*$Z66 -> 0 | BY67: =+P66*$Z66 -> 0 | ... CA67: =+R66*$Z66 -> 0 | CC67: =+C66*$AA66 -> 0 | CD67: =+D66*$AA66 -> 0 | CF67: =+F66*$AA66 -> 0 | CG67: =+G66*$AA66 -> 0 | CI67: =+I66*$AA66 -> 0 | CJ67: =+J66*$AA66 -> 0 | CK67: =+K66*$AA66 -> 0 | CL67: =+L66*$AA66 -> 0 | CM67: =+M66*$AA66 -> 0 | CN67: =+N66*$AA66 -> 0 | CO67: =+O66*$AA66 -> 0 | CP67: =+P66*$AA66 -> 0 | ... CR67: =+R66*$AA66 -> 0 | CT67: =+C66*$AB66 -> 0.81372807 | CU67: =+D66*$AB66 -> 1.3367135 | CW67: =+F66*$AB66 -> 0.42475807 | CX67: =+G66*$AB66 -> 0.5646575 | CZ67: =+I66*$AB66 -> 0.048910858 | DA67: =+J66*$AB66 -> 0.079889307 | DB67: =+K66*$AB66 -> 0.039095057 | DC67: =+L66*$AB66 -> 0.049133535 | DD67: =+M66*$AB66 -> 0.0013750675 | DE67: =+N66*$AB66 -> 0.01439086 | DF67: =+O66*$AB66 -> 0.00023905209 | DG67: =+P66*$AB66 -> 0.0013831593 | ... DI67: =+R66*$AB66 -> 0.014981752
AD68: =+C67*$X67 -> 0.072220117 | AE68: =+D67*$X67 -> 0.12511891 | AG68: =+F67*$X67 -> 0.042963312 | AH68: =+G67*$X67 -> 0.057113822 | AJ68: =+I67*$X67 -> 0.0041816086 | AK68: =+J67*$X67 -> 0.0073150082 | AL68: =+K67*$X67 -> 0.0034661127 | AM68: =+L67*$X67 -> 0.004481482 | AN68: =+M67*$X67 -> 3.2399348e-05 | AO68: =+N67*$X67 -> 0.0013489172 | AP68: =+O67*$X67 -> 1.2004689e-05 | AQ68: =+P67*$X67 -> 0.00012772853 | ... AS68: =+R67*$X67 -> 0.0013568805 | AU68: =+$Y67*C67 -> 0.0045125671 | AV68: =+$Y67*D67 -> 0.0078178696 | AX68: =+$Y67*F67 -> 0.0026844989 | AY68: =+$Y67*G67 -> 0.0035686726 | BA68: =+$Y67*I67 -> 0.00026128162 | BB68: =+$Y67*J67 -> 0.00045706746 | BC68: =+$Y67*K67 -> 0.00021657492 | BD68: =+$Y67*L67 -> 0.00028001877 | BE68: =+$Y67*M67 -> 2.0244253e-06 | BF68: =+$Y67*N67 -> 8.4285092e-05 | BG68: =+$Y67*O67 -> 7.5009523e-07 | BH68: =+$Y67*P67 -> 7.9809281e-06 | ... BJ68: =+$Y67*R67 -> 8.4782671e-05 | BL68: =+C67*$Z67 -> 0.2197415 | BM68: =+D67*$Z67 -> 0.38069471 | BO68: =+F67*$Z67 -> 0.13072289 | BP68: =+G67*$Z67 -> 0.17377813 | BR68: =+I67*$Z67 -> 0.012723227 | BS68: =+J67*$Z67 -> 0.022257107 | BT68: =+K67*$Z67 -> 0.010546214 | BU68: =+L67*$Z67 -> 0.013635641 | BV68: =+M67*$Z67 -> 9.8580306e-05 | BW68: =+N67*$Z67 -> 0.0041043008 | BX68: =+O67*$Z67 -> 3.6526228e-05 | BY68: =+P67*$Z67 -> 0.00038863491 | ... CA68: =+R67*$Z67 -> 0.0041285306 | CC68: =+C67*$AA67 -> 1.2817522e-05 | CD68: =+D67*$AA67 -> 2.2205922e-05 | CF68: =+F67*$AA67 -> 7.6250664e-06 | CG68: =+G67*$AA67 -> 1.0136478e-05 | CI68: =+I67*$AA67 -> 7.4214584e-07 | CJ68: =+J67*$AA67 -> 1.2982571e-06 | CK68: =+K67*$AA67 -> 6.1516067e-07 | CL68: =+L67*$AA67 -> 7.9536693e-07 | CM68: =+M67*$AA67 -> 5.7501893e-09 | CN68: =+N67*$AA67 -> 2.3940386e-07 | CO68: =+O67*$AA67 -> 2.1305749e-09 | CP68: =+P67*$AA67 -> 2.2669075e-08 | ... CR68: =+R67*$AA67 -> 2.4081719e-07 | CT68: =+C67*$AB67 -> 0.010486567 | CU68: =+D67*$AB67 -> 0.018167623 | CW68: =+F67*$AB67 -> 0.0062383957 | CX68: =+G67*$AB67 -> 0.00829309 | CZ68: =+I67*$AB67 -> 0.00060718151 | DA68: =+J67*$AB67 -> 0.0010621601 | DB68: =+K67*$AB67 -> 0.00050328947 | DC68: =+L67*$AB67 -> 0.00065072399 | DD68: =+M67*$AB67 -> 4.7044778e-06 | DE68: =+N67*$AB67 -> 0.00019586663 | DF68: =+O67*$AB67 -> 1.7431152e-06 | DG68: =+P67*$AB67 -> 1.8546548e-05 | ... DI68: =+R67*$AB67 -> 0.00019702293
B69: PCE | C69: =AD70 -> 1.1577493 | D69: =AE70 -> 1.5390686 | F69: =AG70 -> 0.30969976 | G69: =AH70 -> 0.41170328 | I69: =AJ70 -> 0.068577963 | J69: =AK70 -> 0.091164981 | K69: =AL70 -> 0.022222495 | L69: =AM70 -> 0.029541754 | M69: =AN70 -> 0.028813468 | N69: =AO70 -> 0.038303548 | O69: =AP70 -> 0.002532746 | P69: =AQ70 -> 0.0033669379 | ... R69: =AS70 -> 0.019952742
B70: Visitor's expenditures | C70: =AU70 -> 1.3425405 | D70: =AV70 -> 1.8182147 | F70: =AX70 -> 0.38633283 | G70: =AY70 -> 0.51357642 | I70: =BA70 -> 0.11168015 | J70: =BB70 -> 0.13985617 | K70: =BC70 -> 0.02552008 | L70: =BD70 -> 0.034650439 | M70: =BE70 -> 0.048237767 | N70: =BF70 -> 0.060076102 | O70: =BG70 -> 0.024805433 | P70: =BH70 -> 0.02584604 | ... R70: =BJ70 -> 0.019283588 | AD70: =+SUM(AD6:AD68) -> 1.1577493 | AE70: =+SUM(AE6:AE68) -> 1.5390686 | AF70: =+SUM(AF6:AF68) -> 0 | AG70: =+SUM(AG6:AG68) -> 0.30969976 | AH70: =+SUM(AH6:AH68) -> 0.41170328 | AI70: =+SUM(AI6:AI68) -> 0 | AJ70: =+SUM(AJ6:AJ68) -> 0.068577963 | AK70: =+SUM(AK6:AK68) -> 0.091164981 | ... AS70: =+SUM(AS6:AS68) -> 0.019952742 | AU70: =+SUM(AU6:AU68) -> 1.3425405 | AV70: =+SUM(AV6:AV68) -> 1.8182147 | AW70: =+SUM(AW6:AW68) -> 0 | AX70: =+SUM(AX6:AX68) -> 0.38633283 | AY70: =+SUM(AY6:AY68) -> 0.51357642 | AZ70: =+SUM(AZ6:AZ68) -> 0 | BA70: =+SUM(BA6:BA68) -> 0.11168015 | BB70: =+SUM(BB6:BB68) -> 0.13985617 | ... BJ70: =+SUM(BJ6:BJ68) -> 0.019283588 | BL70: =+SUM(BL6:BL68) -> 0.46964813 | BM70: =+SUM(BM6:BM68) -> 0.69995673 | BN70: =+SUM(BN6:BN68) -> 0 | BO70: =+SUM(BO6:BO68) -> 0.18705192 | BP70: =+SUM(BP6:BP68) -> 0.24865983 | BQ70: =+SUM(BQ6:BQ68) -> 0 | BR70: =+SUM(BR6:BR68) -> 0.027082074 | BS70: =+SUM(BS6:BS68) -> 0.040724142 | ... CA70: =+SUM(CA6:CA68) -> 0.010031533 | CC70: =+SUM(CC6:CC68) -> 0.99553514 | CD70: =+SUM(CD6:CD68) -> 1.7104684 | CE70: =+SUM(CE6:CE68) -> 0 | CF70: =+SUM(CF6:CF68) -> 0.58065413 | CG70: =+SUM(CG6:CG68) -> 0.7718999 | CH70: =+SUM(CH6:CH68) -> 0 | CI70: =+SUM(CI6:CI68) -> 0.065295283 | CJ70: =+SUM(CJ6:CJ68) -> 0.10764354 | ... CR70: =+SUM(CR6:CR68) -> 0.019291781 | CT70: =+SUM(CT6:CT68) -> 1.0839563 | CU70: =+SUM(CU6:CU68) -> 1.7172084 | CV70: =+SUM(CV6:CV68) -> 0 | CW70: =+SUM(CW6:CW68) -> 0.51431433 | CX70: =+SUM(CX6:CX68) -> 0.68371024 | CY70: =+SUM(CY6:CY68) -> 0 | CZ70: =+SUM(CZ6:CZ68) -> 0.065366557 | DA70: =+SUM(DA6:DA68) -> 0.10287652 | ... DI70: =+SUM(DI6:DI68) -> 0.020187763
B71: State and local government consumption | C71: =BL70 -> 0.46964813 | D71: =BM70 -> 0.69995673 | F71: =BO70 -> 0.18705192 | G71: =BP70 -> 0.24865983 | I71: =BR70 -> 0.027082074 | J71: =BS70 -> 0.040724142 | K71: =BT70 -> 0.014485111 | L71: =BU70 -> 0.018905784 | M71: =BV70 -> 0.0049179725 | N71: =BW70 -> 0.010649774 | O71: =BX70 -> 0.00063321689 | P71: =BY70 -> 0.0011370506 | ... R71: =CA70 -> 0.010031533
B72: Federal military consumption | C72: =CC70 -> 0.99553514 | D72: =CD70 -> 1.7104684 | F72: =CF70 -> 0.58065413 | G72: =CG70 -> 0.7718999 | I72: =CI70 -> 0.065295283 | J72: =CJ70 -> 0.10764354 | K72: =CK70 -> 0.053282944 | L72: =CL70 -> 0.067005777 | M72: =CM70 -> 0.0018064704 | N72: =CN70 -> 0.019599361 | O72: =CO70 -> 0.0001826016 | P72: =CP70 -> 0.0017466227 | ... R72: =CR70 -> 0.019291781
B73: Federal civilian consumption | C73: =CT70 -> 1.0839563 | D73: =CU70 -> 1.7172084 | F73: =CW70 -> 0.51431433 | G73: =CX70 -> 0.68371024 | I73: =CZ70 -> 0.065366557 | J73: =DA70 -> 0.10287652 | K73: =DB70 -> 0.045166536 | L73: =DC70 -> 0.057321534 | M73: =DD70 -> 0.0060728277 | N73: =DE70 -> 0.021832878 | O73: =DF70 -> 0.0021490158 | P73: =DG70 -> 0.0035343473 | ... R73: =DI70 -> 0.020187763

Sheet ttl req. - type 2
B1: 2022 Type 2 total requirements table
B2: Industry | C2: S1 | D2: S2 | E2: S3 | F2: S4 | G2: S5 | H2: S6 | I2: S7 | J2: S8 | K2: S9 | L2: S10 | M2: S11 | N2: S12 | O2: S13 | P2: S14 | Q2: S15 | R2: S16 | S2: S17 | T2: S18 | U2: S19 | V2: S20 | W2: S21 | X2: S22 | Y2: S23 | Z2: S24 | AA2: S25 | AB2: S26 | AC2: S27 | AD2: S28 | AE2: S29 | AF2: S30 | AG2: S31 | AH2: S32 | AI2: S33 | AJ2: S34 | AK2: S35 | AL2: S36 | AM2: S37 | AN2: S38 | AO2: S39 | AP2: S40 | AQ2: S41 | AR2: S42 | AS2: S43 | AT2: S44 | AU2: S45 | AV2: S46 | AW2: S47 | AX2: S48 | AY2: S49 | AZ2: S50 | BA2: S51 | BB2: S52 | BC2: S53 | BD2: S54 | BE2: S55 | BF2: S56 | BG2: S57 | BH2: S58 | BI2: S59 | BJ2: S60 | BK2: S61 | BL2: S62 | BM2: PCE
A3: S1 | B3: Other crops | C3: 1.0194398 | D3: 0.057839251 | E3: 0.0013681001 | F3: 0.0014743587 | G3: 0.012880467 | H3: 0.00083262463 | I3: 0.0023645419 | J3: 0.0017055457 | K3: 0.0015916887 | L3: 0.0022521439 | M3: 0.059325757 | N3: 0.003966795 | O3: 0.0063291328 | P3: 0.0001260138 | Q3: 0.0024628963 | R3: 0.0008451216 | S3: 0.00078767727 | T3: 0.0011130372 | U3: 0.0014510406 | V3: 0.0012889112 | W3: 0.001457606 | X3: 0.0013937597 | Y3: 0.0010083047 | Z3: 0.00088687671 | AA3: 0.00055672094 | AB3: 0.00065134351 | AC3: 0.00057321932 | AD3: 0.00061063513 | AE3: 0.00064796812 | AF3: 0.00052492978 | AG3: 0.00092163492 | AH3: 0.00081824534 | AI3: 0.0010123717 | AJ3: 0.00078549238 | AK3: 0.001141333 | AL3: 0.00054179566 | AM3: 0.00086348056 | AN3: 0.00080337739 | AO3: 0.0014080924 | AP3: 0.001353123 | AQ3: 0.0009223462 | AR3: 0.0013193723 | AS3: 0.0014959928 | AT3: 0.0014461457 | AU3: 0.0014600903 | AV3: 0.0016045016 | AW3: 0.0010486101 | AX3: 0.00073240899 | AY3: 0.0012665304 | AZ3: 0.001023354 | BA3: 0.0014541181 | BB3: 0.0022419544 | BC3: 0.001159371 | BD3: 0.0013301822 | BE3: 0.0011011804 | BF3: 0.0045380842 | BG3: 0.00092287923 | BH3: 0.0014697561 | BI3: 0.00049458449 | BJ3: 0.0012763314 | BK3: 0.0012734654 | BL3: 0.0012885648 | BM3: 0.00210738
A4: S2 | B4: Animal production | C4: 0.0027081541 | D4: 1.032973 | E4: 0.00052604198 | F4: 0.0024448621 | G4: 0.038491167 | H4: 0.00040418845 | I4: 0.00048507147 | J4: 0.00050691825 | K4: 0.00052261302 | L4: 0.00048122949 | M4: 0.02165352 | N4: 0.0015221795 | O4: 0.00055892856 | P4: 5.83512e-05 | Q4: 0.00047178607 | R4: 0.00037347143 | S4: 0.00033347507 | T4: 0.0004698533 | U4: 0.00063702111 | V4: 0.00057145861 | W4: 0.00065648052 | X4: 0.00063003638 | Y4: 0.0004781566 | Z4: 0.00038221692 | AA4: 0.00025140357 | AB4: 0.00031763817 | AC4: 0.0002657316 | AD4: 0.00028000848 | AE4: 0.00029174674 | AF4: 0.00022731053 | AG4: 0.00040080528 | AH4: 0.0003507047 | AI4: 0.00049956596 | AJ4: 0.00034764885 | AK4: 0.00053412643 | AL4: 0.00018149091 | AM4: 0.00035077684 | AN4: 0.00035789107 | AO4: 0.00064230402 | AP4: 0.00062616147 | AQ4: 0.00039275253 | AR4: 0.0019858303 | AS4: 0.00067759523 | AT4: 0.00068709351 | AU4: 0.00062176492 | AV4: 0.00063073391 | AW4: 0.0004895685 | AX4: 0.0003186776 | AY4: 0.00054297141 | AZ4: 0.000430988 | BA4: 0.0012493075 | BB4: 0.0009586079 | BC4: 0.00047063489 | BD4: 0.00066925179 | BE4: 0.00049562777 | BF4: 0.0028040682 | BG4: 0.00038991598 | BH4: 0.0018243532 | BI4: 0.00021567352 | BJ4: 0.00053149276 | BK4: 0.00053261394 | BL4: 0.00053824736 | BM4: 0.00087755985
A5: S3 | B5: Commercial fishing | C5: 0.00036376871 | D5: 0.00036496965 | E5: 1.006697 | F5: 0.0004528062 | G5: 0.00039065208 | H5: 0.00041628131 | I5: 0.00056983523 | J5: 0.00057756847 | K5: 0.00061761498 | L5: 0.00054504851 | M5: 0.0010969009 | N5: 0.00051102226 | O5: 0.0005618048 | P5: 7.3583575e-05 | Q5: 0.00047091869 | R5: 0.00049880436 | S5: 0.0003172966 | T5: 0.00044411765 | U5: 0.00068215142 | V5: 0.00064232031 | W5: 0.00085220432 | X5: 0.00078562456 | Y5: 0.00067921348 | Z5: 0.00039179823 | AA5: 0.00030482916 | AB5: 0.0004645978 | AC5: 0.00029935494 | AD5: 0.00030928302 | AE5: 0.00036762286 | AF5: 0.00028295246 | AG5: 0.00045553374 | AH5: 0.00037948641 | AI5: 0.00071998532 | AJ5: 0.0003505112 | AK5: 0.00057910675 | AL5: 0.00010257975 | AM5: 0.00035184947 | AN5: 0.00042208289 | AO5: 0.00066983066 | AP5: 0.00058032293 | AQ5: 0.00036958737 | AR5: 0.00054047492 | AS5: 0.00083501991 | AT5: 0.00062249302 | AU5: 0.00062060655 | AV5: 0.00063305685 | AW5: 0.00049428405 | AX5: 0.00031093905 | AY5: 0.00064534607 | AZ5: 0.00040073646 | BA5: 0.0010767261 | BB5: 0.0010626434 | BC5: 0.00043143321 | BD5: 0.00052445385 | BE5: 0.00058428829 | BF5: 0.0074488313 | BG5: 0.00037354104 | BH5: 0.00058987198 | BI5: 0.00021156212 | BJ5: 0.00047818094 | BK5: 0.00048887485 | BL5: 0.00048968066 | BM5: 0.00078953548
A6: S4 | B6: Forestry & logging | C6: 0.0045096784 | D6: 0.00038250093 | E6: 0.00010855199 | F6: 1.4667063 | G6: 0.022418556 | H6: 0.028711137 | I6: 5.8630196e-05 | J6: 6.0735214e-05 | K6: 6.5414293e-05 | L6: 5.7139809e-05 | M6: 0.00057375716 | N6: 0.0022349513 | O6: 0.0078838451 | P6: 0.00010576464 | Q6: 0.00056038174 | R6: 3.8413702e-05 | S6: 0.00011065949 | T6: 4.8474268e-05 | U6: 6.7915218e-05 | V6: 6.4446816e-05 | W6: 5.953064e-05 | X6: 7.9545527e-05 | Y6: 5.7332239e-05 | Z6: 4.1353298e-05 | AA6: 2.5364694e-05 | AB6: 3.5035521e-05 | AC6: 3.7097338e-05 | AD6: 3.7768799e-05 | AE6: 8.1115502e-05 | AF6: 0.00020090076 | AG6: 4.6588458e-05 | AH6: 3.9956488e-05 | AI6: 6.8389172e-05 | AJ6: 4.2033288e-05 | AK6: 8.1964479e-05 | AL6: 6.7277518e-05 | AM6: 4.9777292e-05 | AN6: 3.9178611e-05 | AO6: 9.1808118e-05 | AP6: 0.00010772926 | AQ6: 4.3274513e-05 | AR6: 0.0010983917 | AS6: 7.4251939e-05 | AT6: 0.00011573108 | AU6: 6.7187983e-05 | AV6: 0.00031849093 | AW6: 6.19122e-05 | AX6: 7.2544474e-05 | AY6: 5.7623225e-05 | AZ6: 4.6006591e-05 | BA6: 9.0130861e-05 | BB6: 8.0668371e-05 | BC6: 5.0463721e-05 | BD6: 7.2070955e-05 | BE6: 7.6700289e-05 | BF6: 0.00012300932 | BG6: 4.5945965e-05 | BH6: 7.0139517e-05 | BI6: 3.5875942e-05 | BJ6: 5.4147155e-05 | BK6: 5.7155773e-05 | BL6: 5.5520002e-05 | BM6: 8.9403606e-05
A7: S5 | B7: Support activities for agriculture | C7: 0.062619706 | D7: 0.0081727663 | E7: 0.0011413378 | F7: 0.012961759 | G7: 1.0152827 | H7: 0.0010206627 | I7: 0.0011241403 | J7: 0.001138013 | K7: 0.0011358887 | L7: 0.0011250183 | M7: 0.0045578396 | N7: 0.0009738435 | O7: 0.0014631911 | P7: 0.00010973091 | Q7: 0.0017133453 | R7: 0.00074461822 | S7: 0.00080532151 | T7: 0.0011449321 | U7: 0.0014296721 | V7: 0.0011727531 | W7: 0.0012433376 | X7: 0.0013010437 | Y7: 0.00085712234 | Z7: 0.00077265938 | AA7: 0.00051995608 | AB7: 0.00054143915 | AC7: 0.00054202474 | AD7: 0.00058409872 | AE7: 0.00053859205 | AF7: 0.00045115622 | AG7: 0.00083956162 | AH7: 0.00079982924 | AI7: 0.00083774166 | AJ7: 0.00079244497 | AK7: 0.00110682 | AL7: 0.0025764081 | AM7: 0.0012241788 | AN7: 0.00076264276 | AO7: 0.0013855312 | AP7: 0.0013485338 | AQ7: 0.00094919169 | AR7: 0.0012341723 | AS7: 0.0013474188 | AT7: 0.0014493339 | AU7: 0.0014789643 | AV7: 0.0014936884 | AW7: 0.0010245789 | AX7: 0.0007452446 | AY7: 0.00118245 | AZ7: 0.0010589148 | BA7: 0.0011304169 | BB7: 0.0015304415 | BC7: 0.00092241811 | BD7: 0.0013369532 | BE7: 0.00096776783 | BF7: 0.0013530541 | BG7: 0.00094734659 | BH7: 0.0013958719 | BI7: 0.0004669333 | BJ7: 0.0013342022 | BK7: 0.0012976363 | BL7: 0.0013603463 | BM7: 0.0022029318
A8: S6 | B8: Mining | C8: 0.00034320065 | D8: 6.3388659e-05 | E8: 3.8157283e-05 | F8: 4.2797379e-05 | G8: 4.3070452e-05 | H8: 1.0060743 | I8: 9.0066661e-05 | J8: 5.0505173e-05 | K8: 5.1230047e-05 | L8: 4.6729045e-05 | M8: 8.1332486e-05 | N8: 4.5512078e-05 | O8: 6.6342077e-05 | P8: 1.8937272e-05 | Q8: 4.2706639e-05 | R8: 2.7909694e-05 | S8: 3.134583e-05 | T8: 3.5373815e-05 | U8: 5.2922385e-05 | V8: 4.7355134e-05 | W8: 4.2817101e-05 | X8: 9.3299533e-05 | Y8: 4.4212992e-05 | Z8: 3.7925551e-05 | AA8: 1.9944661e-05 | AB8: 3.2062206e-05 | AC8: 2.1996988e-05 | AD8: 2.2906466e-05 | AE8: 0.00089384926 | AF8: 0.0058415027 | AG8: 3.8114655e-05 | AH8: 4.4222162e-05 | AI8: 4.6242335e-05 | AJ8: 2.5940227e-05 | AK8: 5.2327172e-05 | AL8: 9.6654986e-06 | AM8: 4.459358e-05 | AN8: 3.0475925e-05 | AO8: 6.0661951e-05 | AP8: 6.3022019e-05 | AQ8: 3.0074345e-05 | AR8: 7.2477412e-05 | AS8: 5.6472112e-05 | AT8: 6.4301742e-05 | AU8: 6.2948169e-05 | AV8: 4.8796259e-05 | AW8: 6.5927018e-05 | AX8: 2.2975981e-05 | AY8: 4.8476976e-05 | AZ8: 3.2463693e-05 | BA8: 7.4457268e-05 | BB8: 9.1017104e-05 | BC8: 3.4957576e-05 | BD8: 4.5330201e-05 | BE8: 0.00010077232 | BF8: 8.0227231e-05 | BG8: 3.4208637e-05 | BH8: 6.925829e-05 | BI8: 3.8733768e-05 | BJ8: 3.878733e-05 | BK8: 4.278647e-05 | BL8: 4.1303767e-05 | BM8: 6.4042648e-05
A9: S7 | B9: Single family construction | C9: 0 | D9: 0 | E9: 0 | F9: 0 | G9: 0 | H9: 0 | I9: 1 | J9: 0 | K9: 0 | L9: 0 | M9: 0 | N9: 0 | O9: 0 | P9: 0 | Q9: 0 | R9: 0 | S9: 0 | T9: 0 | U9: 0 | V9: 0 | W9: 0 | X9: 0 | Y9: 0 | Z9: 0 | AA9: 0 | AB9: 0 | AC9: 0 | AD9: 0 | AE9: 0 | AF9: 0 | AG9: 0 | AH9: 0 | AI9: 0 | AJ9: 0 | AK9: 0 | AL9: 0 | AM9: 0 | AN9: 0 | AO9: 0 | AP9: 0 | AQ9: 0 | AR9: 0 | AS9: 0 | AT9: 0 | AU9: 0 | AV9: 0 | AW9: 0 | AX9: 0 | AY9: 0 | AZ9: 0 | BA9: 0 | BB9: 0 | BC9: 0 | BD9: 0 | BE9: 0 | BF9: 0 | BG9: 0 | BH9: 0 | BI9: 0 | BJ9: 0 | BK9: 0 | BL9: 0 | BM9: 0
A10: S8 | B10: Construction of other buildings | C10: 0 | D10: 0 | E10: 0 | F10: 0 | G10: 0 | H10: 0 | I10: 0 | J10: 1 | K10: 0 | L10: 0 | M10: 0 | N10: 0 | O10: 0 | P10: 0 | Q10: 0 | R10: 0 | S10: 0 | T10: 0 | U10: 0 | V10: 0 | W10: 0 | X10: 0 | Y10: 0 | Z10: 0 | AA10: 0 | AB10: 0 | AC10: 0 | AD10: 0 | AE10: 0 | AF10: 0 | AG10: 0 | AH10: 0 | AI10: 0 | AJ10: 0 | AK10: 0 | AL10: 0 | AM10: 0 | AN10: 0 | AO10: 0 | AP10: 0 | AQ10: 0 | AR10: 0 | AS10: 0 | AT10: 0 | AU10: 0 | AV10: 0 | AW10: 0 | AX10: 0 | AY10: 0 | AZ10: 0 | BA10: 0 | BB10: 0 | BC10: 0 | BD10: 0 | BE10: 0 | BF10: 0 | BG10: 0 | BH10: 0 | BI10: 0 | BJ10: 0 | BK10: 0 | BL10: 0 | BM10: 0
